Workbook

Sheet Summary Dashboard
A1: Credit Risk Analysis Report
A2: Credit Card, Personal Loan, Car Loan & Home Loan Portfolio | 1,000 Customer Sample (Synthetic Data)
A4: Portfolio Overview
A5: Total Customers | C5: =COUNTA('Customer Data'!A2:A1001) -> 1000
A6: Average Annual Income (INR) | C6: =ROUND(AVERAGE('Customer Data'!J2:J1001),0) -> 1420784
A7: Average Credit Score | C7: =ROUND(AVERAGE('Customer Data'!P2:P1001),0) -> 601
A8: Average Debt-to-Income Ratio | C8: =AVERAGE('Customer Data'!U2:U1001) -> 0.10583152
A9: Average Risk Score | C9: =ROUND(AVERAGE('Customer Data'!Y2:Y1001),1) -> 33.9
A10: Average Existing Products per Customer | C10: =ROUND(AVERAGE('Customer Data'!K2:K1001),2) -> 1.32
A12: Eligibility Status Breakdown
A13: Eligible | C13: =COUNTIF('Customer Data'!AA2:AA1001,"Eligible") -> 325 | D13: =C13/$C$16 -> 0.325
A14: Review | C14: =COUNTIF('Customer Data'!AA2:AA1001,"Review") -> 212 | D14: =C14/$C$16 -> 0.212
A15: Not Eligible | C15: =COUNTIF('Customer Data'!AA2:AA1001,"Not Eligible") -> 463 | D15: =C15/$C$16 -> 0.463
A16: Total | C16: =SUM(C13:C15) -> 1000
A18: Risk Category Breakdown
A19: Low | C19: =COUNTIF('Customer Data'!Z2:Z1001,"Low") -> 413 | D19: =C19/$C$22 -> 0.413
A20: Medium | C20: =COUNTIF('Customer Data'!Z2:Z1001,"Medium") -> 553 | D20: =C20/$C$22 -> 0.553
A21: High | C21: =COUNTIF('Customer Data'!Z2:Z1001,"High") -> 34 | D21: =C21/$C$22 -> 0.034
A22: Total | C22: =SUM(C19:C21) -> 1000
A24: Requested Product Mix (New Applications)
C25: Applications | D25: Eligible
A26: Credit Card | C26: =COUNTIF('Customer Data'!S2:S1001,"Credit Card") -> 250 | D26: =COUNTIFS('Customer Data'!S2:S1001,"Credit Card",'Customer Data'!AA2:AA1001,"Eligible") -> 84
A27: Personal Loan | C27: =COUNTIF('Customer Data'!S2:S1001,"Personal Loan") -> 239 | D27: =COUNTIFS('Customer Data'!S2:S1001,"Personal Loan",'Customer Data'!AA2:AA1001,"Eligible") -> 77
A28: Car Loan | C28: =COUNTIF('Customer Data'!S2:S1001,"Car Loan") -> 236 | D28: =COUNTIFS('Customer Data'!S2:S1001,"Car Loan",'Customer Data'!AA2:AA1001,"Eligible") -> 75
A29: Home Loan | C29: =COUNTIF('Customer Data'!S2:S1001,"Home Loan") -> 275 | D29: =COUNTIFS('Customer Data'!S2:S1001,"Home Loan",'Customer Data'!AA2:AA1001,"Eligible") -> 89
A32: Existing Products Held With Bank
A33: Credit Card | C33: =COUNTIF('Customer Data'!L2:L1001,"Y") -> 548
A34: Personal Loan | C34: =COUNTIF('Customer Data'!M2:M1001,"Y") -> 312
A35: Car Loan | C35: =COUNTIF('Customer Data'!N2:N1001,"Y") -> 278
A36: Home Loan | C36: =COUNTIF('Customer Data'!O2:O1001,"Y") -> 185

Sheet Customer Data
A1: Customer ID | B1: Full Name | C1: Phone Number | D1: Email ID | E1: Age | F1: Gender | G1: City | H1: Occupation | I1: Employment Type | J1: Annual Income (INR) | K1: Existing Products Count | L1: Has Credit Card | M1: Has Personal Loan | N1: Has Car Loan | O1: Has Home Loan | P1: Credit Score (300-900) | Q1: Existing Outstanding Debt | R1: Monthly EMI Outstanding (INR) | S1: Requested Loan/Product Type | T1: Requested Amount | U1: Debt-to-Income Ratio | V1: Missed Payments (12M) | W1: Credit Utilization (%) | X1: Years with Bank | Y1: Risk Score (0-100) | Z1: Risk Category | AA1: Eligibility Status | AB1: Marital Status | AC1: Number of Dependents | AD1: Residence Type | AE1: Employment Tenure (Years) | AF1: Co-Applicant Income (INR) | AG1: Total Household Income (INR) | AH1: Existing Loans (Other Banks) | AI1: Previous Default History | AJ1: Requested Tenure (Months) | AK1: Offered Interest Rate (%) | AL1: Proposed EMI (INR) | AM1: Loan-to-Income Ratio | AN1: Total Monthly Obligations (INR) | AO1: FOIR (Fixed Obligation to Income Ratio) | AP1: Collateral Value (INR) | AQ1: Loan-to-Value Ratio | AR1: Application Date | AS1: KYC Status
A2: CUST00001 | B2: Rajesh Kumar | D2: rajesh.kumar760@outlook.com | E2: 36 | F2: Male | G2: Chennai | H2: Salaried - Government | I2: Salaried | J2: 664647 | K2: 2 | L2: N | M2: Y | N2: Y | O2: N | P2: 327 | Q2: 223817.91 | R2: 3926.63 | S2: Home Loan | T2: 3349189 | U2: =IFERROR((R2*12)/J2,0) -> 0.070894114 | V2: 0 | W2: 31.4 | X2: 13.1 | Y2: =ROUND(0.4*((900-P2)/600*100)+0.3*MIN(U2*100,100)+0.2*MIN(V2*20,100)+0.1*W2,1) -> 43.5 | Z2: =IF(Y2<=30,"Low",IF(Y2<=60,"Medium","High")) -> Medium | AA2: =IF(AND(P2>=650,U2<=0.4,V2<=2,Y2<=50),"Eligible",IF(AND(P2>=550,V2<=4,Y2<=75),"Review","Not Eligible")) -> Not Eligible | AB2: Single | AC2: 0 | AD2: Owned | AE2: 4.4 | AF2: 722621 | AG2: =J2+AF2 -> 1387268 | AH2: 0 | AI2: N | AJ2: 240 | AK2: =(IF(S2="Credit Card",0.36,IF(S2="Personal Loan",0.14,IF(S2="Car Loan",0.09,0.085))))+IF(Z2="Low",0,IF(Z2="Medium",0.015,0.03)) -> 0.1 | AL2: =-PMT(AK2/12,AJ2,T2) -> 32320.399 | AM2: =IFERROR(T2/J2,0) -> 5.0390493 | AN2: =R2+AL2 -> 36247.029 | AO2: =IFERROR((AN2*12)/J2,0) -> 0.65442911 | AP2: 4561172 | AQ2: =IF(AP2>0,T2/AP2,"N/A") -> 0.73428255 | AR2: 46204 | AS2: Verified
A3: CUST00002 | B3: Aditya Yadav | D3: aditya.yadav550@gmail.com | E3: 45 | F3: Male | G3: Coimbatore | H3: Salaried - IT/Tech | I3: Salaried | J3: 1816807 | K3: 1 | L3: N | M3: N | N3: Y | O3: N | P3: 596 | Q3: 1073974 | R3: 41306.71 | S3: Credit Card | T3: 219295 | U3: =IFERROR((R3*12)/J3,0) -> 0.27283059 | V3: 0 | W3: 65.4 | X3: 5.6 | Y3: =ROUND(0.4*((900-P3)/600*100)+0.3*MIN(U3*100,100)+0.2*MIN(V3*20,100)+0.1*W3,1) -> 35 | Z3: =IF(Y3<=30,"Low",IF(Y3<=60,"Medium","High")) -> Medium | AA3: =IF(AND(P3>=650,U3<=0.4,V3<=2,Y3<=50),"Eligible",IF(AND(P3>=550,V3<=4,Y3<=75),"Review","Not Eligible")) -> Review | AB3: Married | AC3: 0 | AD3: Owned | AE3: 22.5 | AF3: 0 | AG3: =J3+AF3 -> 1816807 | AH3: 1 | AI3: N | AJ3: 18 | AK3: =(IF(S3="Credit Card",0.36,IF(S3="Personal Loan",0.14,IF(S3="Car Loan",0.09,0.085))))+IF(Z3="Low",0,IF(Z3="Medium",0.015,0.03)) -> 0.375 | AL3: =-PMT(AK3/12,AJ3,T3) -> 16113.634 | AM3: =IFERROR(T3/J3,0) -> 0.12070352 | AN3: =R3+AL3 -> 57420.344 | AO3: =IFERROR((AN3*12)/J3,0) -> 0.37926105 | AP3: 0 | AQ3: =IF(AP3>0,T3/AP3,"N/A") -> N/A | AR3: 45978 | AS3: Verified
A4: CUST00003 | B4: Vikram Khanna | D4: vikram.khanna705@rediffmail.com | E4: 35 | F4: Female | G4: Delhi | H4: Self Employed - Professional | I4: Self-Employed | J4: 434638 | K4: 1 | L4: N | M4: N | N4: Y | O4: N | P4: 880 | Q4: 228541.6 | R4: 7141.93 | S4: Personal Loan | T4: 737277 | U4: =IFERROR((R4*12)/J4,0) -> 0.19718285 | V4: 1 | W4: 89 | X4: 9.7 | Y4: =ROUND(0.4*((900-P4)/600*100)+0.3*MIN(U4*100,100)+0.2*MIN(V4*20,100)+0.1*W4,1) -> 20.1 | Z4: =IF(Y4<=30,"Low",IF(Y4<=60,"Medium","High")) -> Low | AA4: =IF(AND(P4>=650,U4<=0.4,V4<=2,Y4<=50),"Eligible",IF(AND(P4>=550,V4<=4,Y4<=75),"Review","Not Eligible")) -> Eligible | AB4: Married | AC4: 0 | AD4: Rented | AE4: 7.7 | AF4: 0 | AG4: =J4+AF4 -> 434638 | AH4: 0 | AI4: N | AJ4: 36 | AK4: =(IF(S4="Credit Card",0.36,IF(S4="Personal Loan",0.14,IF(S4="Car Loan",0.09,0.085))))+IF(Z4="Low",0,IF(Z4="Medium",0.015,0.03)) -> 0.14 | AL4: =-PMT(AK4/12,AJ4,T4) -> 25198.38 | AM4: =IFERROR(T4/J4,0) -> 1.6963013 | AN4: =R4+AL4 -> 32340.31 | AO4: =IFERROR((AN4*12)/J4,0) -> 0.89288954 | AP4: 0 | AQ4: =IF(AP4>0,T4/AP4,"N/A") -> N/A | AR4: 46007 | AS4: Pending
A5: CUST00004 | B5: Krishna Desai | C5: 9629908599 | D5: krishna.desai94@gmail.com | E5: 28 | F5: Male | G5: Kolkata | H5: Salaried - Education | I5: Salaried | J5: 566454 | K5: 1 | L5: Y | M5: N | N5: N | O5: N | P5: 866 | Q5: 292555 | R5: 24379.6 | S5: Credit Card | U5: =IFERROR((R5*12)/J5,0) -> 0.51646771 | V5: 4 | W5: 76.3 | X5: 11.6 | Y5: =ROUND(0.4*((900-P5)/600*100)+0.3*MIN(U5*100,100)+0.2*MIN(V5*20,100)+0.1*W5,1) -> 41.4 | Z5: =IF(Y5<=30,"Low",IF(Y5<=60,"Medium","High")) -> Medium | AA5: =IF(AND(P5>=650,U5<=0.4,V5<=2,Y5<=50),"Eligible",IF(AND(P5>=550,V5<=4,Y5<=75),"Review","Not Eligible")) -> Review | AB5: Married | AC5: 1 | AD5: Owned | AE5: 0.3 | AF5: 0 | AG5: =J5+AF5 -> 566454 | AH5: 1 | AI5: Y | AJ5: 18 | AK5: =(IF(S5="Credit Card",0.36,IF(S5="Personal Loan",0.14,IF(S5="Car Loan",0.09,0.085))))+IF(Z5="Low",0,IF(Z5="Medium",0.015,0.03)) -> 0.375 | AL5: =-PMT(AK5/12,AJ5,T5) -> 0 | AM5: =IFERROR(T5/J5,0) -> 0 | AN5: =R5+AL5 -> 24379.6 | AO5: =IFERROR((AN5*12)/J5,0) -> 0.51646771 | AP5: 0 | AQ5: =IF(AP5>0,T5/AP5,"N/A") -> N/A | AR5: 46154 | AS5: Verified
A6: CUST00005 | B6: Usha Mishra | C6: 9420452650 | D6: usha.mishra862@rediffmail.com | E6: 59 | F6: Male | G6: Chennai | H6: Salaried - Healthcare | I6: Salaried | J6: 977585 | K6: 2 | L6: Y | M6: N | N6: N | O6: Y | P6: 631 | Q6: 286592 | R6: 15083.8 | S6: Car Loan | T6: 944903 | U6: =IFERROR((R6*12)/J6,0) -> 0.18515587 | V6: 0 | W6: 27.9 | X6: 8.6 | Y6: =ROUND(0.4*((900-P6)/600*100)+0.3*MIN(U6*100,100)+0.2*MIN(V6*20,100)+0.1*W6,1) -> 26.3 | Z6: =IF(Y6<=30,"Low",IF(Y6<=60,"Medium","High")) -> Low | AA6: =IF(AND(P6>=650,U6<=0.4,V6<=2,Y6<=50),"Eligible",IF(AND(P6>=550,V6<=4,Y6<=75),"Review","Not Eligible")) -> Review | AB6: Married | AC6: 2 | AD6: Rented | AE6: 29.3 | AF6: 0 | AG6: =J6+AF6 -> 977585 | AH6: 0 | AI6: N | AJ6: 72 | AK6: =(IF(S6="Credit Card",0.36,IF(S6="Personal Loan",0.14,IF(S6="Car Loan",0.09,0.085))))+IF(Z6="Low",0,IF(Z6="Medium",0.015,0.03)) -> 0.09 | AL6: =-PMT(AK6/12,AJ6,T6) -> 17032.384 | AM6: =IFERROR(T6/J6,0) -> 0.96656864 | AN6: =R6+AL6 -> 32116.184 | AO6: =IFERROR((AN6*12)/J6,0) -> 0.3942309 | AP6: 1023354 | AQ6: =IF(AP6>0,T6/AP6,"N/A") -> 0.92333933 | AR6: 46165 | AS6: Verified
A7: CUST00006 | B7: Saanvi Reddy | E7: 40 | F7: Female | G7: Kanpur | H7: Business Owner | I7: Self-Employed | J7: 2470870 | K7: 4 | L7: Y | M7: Y | N7: Y | O7: Y | P7: 867 | R7: 13121.16 | S7: Credit Card | T7: 57220 | U7: =IFERROR((R7*12)/J7,0) -> 0.063724081 | V7: 2 | W7: 10.6 | X7: 1.2 | Y7: =ROUND(0.4*((900-P7)/600*100)+0.3*MIN(U7*100,100)+0.2*MIN(V7*20,100)+0.1*W7,1) -> 13.2 | Z7: =IF(Y7<=30,"Low",IF(Y7<=60,"Medium","High")) -> Low | AA7: =IF(AND(P7>=650,U7<=0.4,V7<=2,Y7<=50),"Eligible",IF(AND(P7>=550,V7<=4,Y7<=75),"Review","Not Eligible")) -> Eligible | AB7: Married | AC7: 1 | AD7: Rented | AE7: 5.5 | AF7: 0 | AG7: =J7+AF7 -> 2470870 | AH7: 0 | AI7: N | AJ7: 36 | AK7: =(IF(S7="Credit Card",0.36,IF(S7="Personal Loan",0.14,IF(S7="Car Loan",0.09,0.085))))+IF(Z7="Low",0,IF(Z7="Medium",0.015,0.03)) -> 0.36 | AL7: =-PMT(AK7/12,AJ7,T7) -> 2620.8931 | AM7: =IFERROR(T7/J7,0) -> 0.023157835 | AN7: =R7+AL7 -> 15742.053 | AO7: =IFERROR((AN7*12)/J7,0) -> 0.076452682 | AP7: 0 | AQ7: =IF(AP7>0,T7/AP7,"N/A") -> N/A | AR7: 46019 | AS7: Verified
A8: CUST00007 | B8: Preeti Malhotra | C8: 9304451095 | D8: preeti.malhotra97@gmail.com | E8: 63 | F8: Female | G8: Kanpur | H8: Salaried - Education | I8: Salaried | J8: 2024287 | K8: 1 | L8: Y | M8: N | N8: N | O8: N | P8: 400 | Q8: 73618 | R8: 1269.28 | S8: Car Loan | U8: =IFERROR((R8*12)/J8,0) -> 0.0075243086 | V8: 0 | W8: 23.1 | X8: 6.8 | Y8: =ROUND(0.4*((900-P8)/600*100)+0.3*MIN(U8*100,100)+0.2*MIN(V8*20,100)+0.1*W8,1) -> 35.9 | Z8: =IF(Y8<=30,"Low",IF(Y8<=60,"Medium","High")) -> Medium | AA8: =IF(AND(P8>=650,U8<=0.4,V8<=2,Y8<=50),"Eligible",IF(AND(P8>=550,V8<=4,Y8<=75),"Review","Not Eligible")) -> Not Eligible | AB8: Married | AC8: 1 | AD8: Owned | AE8: 27.7 | AF8: 0 | AG8: =J8+AF8 -> 2024287 | AH8: 2 | AI8: N | AJ8: 24 | AK8: =(IF(S8="Credit Card",0.36,IF(S8="Personal Loan",0.14,IF(S8="Car Loan",0.09,0.085))))+IF(Z8="Low",0,IF(Z8="Medium",0.015,0.03)) -> 0.105 | AL8: =-PMT(AK8/12,AJ8,T8) -> 0 | AM8: =IFERROR(T8/J8,0) -> 0 | AN8: =R8+AL8 -> 1269.28 | AO8: =IFERROR((AN8*12)/J8,0) -> 0.0075243086 | AP8: 624628 | AQ8: =IF(AP8>0,T8/AP8,"N/A") -> 0 | AR8: 46171 | AS8: Verified
A9: CUST00008 | B9: Sai Khanna | C9: 9909134796 | D9: sai.khanna870@yahoo.com | E9: 31 | F9: Female | G9: Chandigarh | H9: Business Owner | I9: Self-Employed | J9: 1196521 | K9: 2 | L9: N | M9: N | N9: Y | O9: Y | P9: 699 | Q9: 190393 | R9: 4643.72 | S9: Car Loan | T9: 1187110 | U9: =IFERROR((R9*12)/J9,0) -> 0.046572221 | V9: 2 | W9: 74.4 | X9: 11.8 | Y9: =ROUND(0.4*((900-P9)/600*100)+0.3*MIN(U9*100,100)+0.2*MIN(V9*20,100)+0.1*W9,1) -> 30.2 | Z9: =IF(Y9<=30,"Low",IF(Y9<=60,"Medium","High")) -> Medium | AA9: =IF(AND(P9>=650,U9<=0.4,V9<=2,Y9<=50),"Eligible",IF(AND(P9>=550,V9<=4,Y9<=75),"Review","Not Eligible")) -> Eligible | AB9: Single | AC9: 1 | AD9: Owned | AE9: 2.4 | AF9: 701803 | AG9: =J9+AF9 -> 1898324 | AH9: 0 | AI9: N | AJ9: 24 | AK9: =(IF(S9="Credit Card",0.36,IF(S9="Personal Loan",0.14,IF(S9="Car Loan",0.09,0.085))))+IF(Z9="Low",0,IF(Z9="Medium",0.015,0.03)) -> 0.105 | AL9: =-PMT(AK9/12,AJ9,T9) -> 55053.463 | AM9: =IFERROR(T9/J9,0) -> 0.9921347 | AN9: =R9+AL9 -> 59697.183 | AO9: =IFERROR((AN9*12)/J9,0) -> 0.59870758 | AP9: 1385162 | AQ9: =IF(AP9>0,T9/AP9,"N/A") -> 0.85701889 | AR9: 46152 | AS9: Verified
A10: CUST00009 | B10: Divya Patel | C10: 9161073976 | D10: divya.patel984@rediffmail.com | E10: 26 | F10: Male | G10: Bengaluru | H10: Salaried - Government | I10: Salaried | J10: 1286516 | K10: 1 | L10: Y | M10: N | N10: N | O10: N | P10: 340 | Q10: 478106.53 | R10: 12581.75 | S10: Car Loan | T10: 846865 | U10: =IFERROR((R10*12)/J10,0) -> 0.11735649 | V10: 0 | W10: 73 | X10: 3.7 | Y10: =ROUND(0.4*((900-P10)/600*100)+0.3*MIN(U10*100,100)+0.2*MIN(V10*20,100)+0.1*W10,1) -> 48.2 | Z10: =IF(Y10<=30,"Low",IF(Y10<=60,"Medium","High")) -> Medium | AA10: =IF(AND(P10>=650,U10<=0.4,V10<=2,Y10<=50),"Eligible",IF(AND(P10>=550,V10<=4,Y10<=75),"Review","Not Eligible")) -> Not Eligible | AB10: Married | AC10: 2 | AD10: Owned | AE10: 1.8 | AF10: 0 | AG10: =J10+AF10 -> 1286516 | AH10: 0 | AI10: N | AJ10: 72 | AK10: =(IF(S10="Credit Card",0.36,IF(S10="Personal Loan",0.14,IF(S10="Car Loan",0.09,0.085))))+IF(Z10="Low",0,IF(Z10="Medium",0.015,0.03)) -> 0.105 | AL10: =-PMT(AK10/12,AJ10,T10) -> 15903.252 | AM10: =IFERROR(T10/J10,0) -> 0.65826231 | AN10: =R10+AL10 -> 28485.002 | AO10: =IFERROR((AN10*12)/J10,0) -> 0.26569435 | AP10: 1057920 | AQ10: =IF(AP10>0,T10/AP10,"N/A") -> 0.80050004 | AR10: 45932 | AS10: Verified
A11: CUST00010 | B11: Sneha Nair | C11: 9242224154 | E11: 25 | F11: Male | G11: Kanpur | H11: Salaried - IT/Tech | I11: Salaried | J11: 961638 | K11: 1 | L11: Y | M11: N | N11: N | O11: N | P11: 841 | Q11: 4513.8 | R11: 96.04 | S11: Car Loan | T11: 517236 | U11: =IFERROR((R11*12)/J11,0) -> 0.0011984551 | V11: 5 | W11: 17.8 | X11: 1.9 | Y11: =ROUND(0.4*((900-P11)/600*100)+0.3*MIN(U11*100,100)+0.2*MIN(V11*20,100)+0.1*W11,1) -> 25.7 | Z11: =IF(Y11<=30,"Low",IF(Y11<=60,"Medium","High")) -> Low | AA11: =IF(AND(P11>=650,U11<=0.4,V11<=2,Y11<=50),"Eligible",IF(AND(P11>=550,V11<=4,Y11<=75),"Review","Not Eligible")) -> Not Eligible | AB11: Married | AC11: 2 | AD11: Owned | AE11: 2.5 | AF11: 0 | AG11: =J11+AF11 -> 961638 | AH11: 0 | AI11: N | AJ11: 48 | AK11: =(IF(S11="Credit Card",0.36,IF(S11="Personal Loan",0.14,IF(S11="Car Loan",0.09,0.085))))+IF(Z11="Low",0,IF(Z11="Medium",0.015,0.03)) -> 0.09 | AL11: =-PMT(AK11/12,AJ11,T11) -> 12871.44 | AM11: =IFERROR(T11/J11,0) -> 0.53786976 | AN11: =R11+AL11 -> 12967.48 | AO11: =IFERROR((AN11*12)/J11,0) -> 0.1618174 | AP11: 595381 | AQ11: =IF(AP11>0,T11/AP11,"N/A") -> 0.86874791 | AR11: 46023 | AS11: Verified
A12: CUST00011 | B12: Rekha Verma | C12: 9199104722 | D12: rekha.verma650@hotmail.com | E12: 38 | F12: Male | G12: Mumbai | H12: Salaried - Healthcare | I12: Salaried | J12: 848697 | K12: 1 | L12: N | M12: Y | N12: N | O12: N | P12: 737 | Q12: 285623.98 | R12: 15032.84 | S12: Credit Card | U12: =IFERROR((R12*12)/J12,0) -> 0.21255416 | V12: 2 | W12: 19.2 | X12: 0.7 | Y12: =ROUND(0.4*((900-P12)/600*100)+0.3*MIN(U12*100,100)+0.2*MIN(V12*20,100)+0.1*W12,1) -> 27.2 | Z12: =IF(Y12<=30,"Low",IF(Y12<=60,"Medium","High")) -> Low | AA12: =IF(AND(P12>=650,U12<=0.4,V12<=2,Y12<=50),"Eligible",IF(AND(P12>=550,V12<=4,Y12<=75),"Review","Not Eligible")) -> Eligible | AB12: Married | AC12: 2 | AD12: Owned | AE12: 1 | AF12: 0 | AG12: =J12+AF12 -> 848697 | AH12: 3 | AI12: Y | AJ12: 12 | AK12: =(IF(S12="Credit Card",0.36,IF(S12="Personal Loan",0.14,IF(S12="Car Loan",0.09,0.085))))+IF(Z12="Low",0,IF(Z12="Medium",0.015,0.03)) -> 0.36 | AL12: =-PMT(AK12/12,AJ12,T12) -> 0 | AM12: =IFERROR(T12/J12,0) -> 0 | AN12: =R12+AL12 -> 15032.84 | AO12: =IFERROR((AN12*12)/J12,0) -> 0.21255416 | AP12: 0 | AQ12: =IF(AP12>0,T12/AP12,"N/A") -> N/A | AR12: 46078 | AS12: Verified
A13: CUST00012 | B13: Rahul Pandey | D13: rahul.pandey363@rediffmail.com | E13: 47 | F13: Male | G13: Ahmedabad | H13: Self Employed - Business | I13: Self-Employed | J13: 1042611 | K13: 1 | L13: N | M13: Y | N13: N | O13: N | P13: 721 | Q13: 501851.51 | R13: 8505.96 | S13: Personal Loan | T13: 329766 | U13: =IFERROR((R13*12)/J13,0) -> 0.097899907 | V13: 0 | W13: 71.6 | X13: 5.9 | Y13: =ROUND(0.4*((900-P13)/600*100)+0.3*MIN(U13*100,100)+0.2*MIN(V13*20,100)+0.1*W13,1) -> 22 | Z13: =IF(Y13<=30,"Low",IF(Y13<=60,"Medium","High")) -> Low | AA13: =IF(AND(P13>=650,U13<=0.4,V13<=2,Y13<=50),"Eligible",IF(AND(P13>=550,V13<=4,Y13<=75),"Review","Not Eligible")) -> Eligible | AB13: Married | AC13: 1 | AD13: Owned | AE13: 23.9 | AF13: 765402 | AG13: =J13+AF13 -> 1808013 | AH13: 2 | AI13: N | AJ13: 24 | AK13: =(IF(S13="Credit Card",0.36,IF(S13="Personal Loan",0.14,IF(S13="Car Loan",0.09,0.085))))+IF(Z13="Low",0,IF(Z13="Medium",0.015,0.03)) -> 0.14 | AL13: =-PMT(AK13/12,AJ13,T13) -> 15833.016 | AM13: =IFERROR(T13/J13,0) -> 0.31628863 | AN13: =R13+AL13 -> 24338.976 | AO13: =IFERROR((AN13*12)/J13,0) -> 0.28013105 | AP13: 0 | AQ13: =IF(AP13>0,T13/AP13,"N/A") -> N/A | AR13: 46099 | AS13: Verified
A14: CUST00013 | B14: Usha Gupta | C14: 9930353157 | D14: usha.gupta286@outlook.com | E14: 62 | F14: Female | G14: Coimbatore | H14: Salaried - Healthcare | I14: Salaried | J14: 415765 | K14: 2 | L14: Y | M14: N | N14: Y | O14: N | P14: 571 | Q14: 9543.6 | R14: 190.87 | S14: Home Loan | T14: 4399833 | U14: =IFERROR((R14*12)/J14,0) -> 0.0055089774 | V14: 2 | W14: 34.8 | X14: 9.2 | Y14: =ROUND(0.4*((900-P14)/600*100)+0.3*MIN(U14*100,100)+0.2*MIN(V14*20,100)+0.1*W14,1) -> 33.6 | Z14: =IF(Y14<=30,"Low",IF(Y14<=60,"Medium","High")) -> Medium | AA14: =IF(AND(P14>=650,U14<=0.4,V14<=2,Y14<=50),"Eligible",IF(AND(P14>=550,V14<=4,Y14<=75),"Review","Not Eligible")) -> Review | AB14: Married | AC14: 1 | AD14: Rented | AE14: 7.9 | AF14: 0 | AG14: =J14+AF14 -> 415765 | AH14: 0 | AI14: Y | AJ14: 360 | AK14: =(IF(S14="Credit Card",0.36,IF(S14="Personal Loan",0.14,IF(S14="Car Loan",0.09,0.085))))+IF(Z14="Low",0,IF(Z14="Medium",0.015,0.03)) -> 0.1 | AL14: =-PMT(AK14/12,AJ14,T14) -> 38611.684 | AM14: =IFERROR(T14/J14,0) -> 10.5825 | AN14: =R14+AL14 -> 38802.554 | AO14: =IFERROR((AN14*12)/J14,0) -> 1.1199371 | AP14: 5815322 | AQ14: =IF(AP14>0,T14/AP14,"N/A") -> 0.75659319 | AR14: 46238 | AS14: Verified
A15: CUST00014 | B15: Saanvi Gupta | C15: 9813219781 | D15: saanvi.gupta943@outlook.com | E15: 60 | F15: Female | G15: Hyderabad | H15: Salaried - IT/Tech | I15: Salaried | J15: 2427025 | K15: 1 | L15: Y | M15: N | N15: N | O15: N | P15: 430 | R15: 5173.34 | S15: Home Loan | T15: 7181754 | U15: =IFERROR((R15*12)/J15,0) -> 0.025578673 | V15: 2 | W15: 21.5 | X15: 8.6 | Y15: =ROUND(0.4*((900-P15)/600*100)+0.3*MIN(U15*100,100)+0.2*MIN(V15*20,100)+0.1*W15,1) -> 42.3 | Z15: =IF(Y15<=30,"Low",IF(Y15<=60,"Medium","High")) -> Medium | AA15: =IF(AND(P15>=650,U15<=0.4,V15<=2,Y15<=50),"Eligible",IF(AND(P15>=550,V15<=4,Y15<=75),"Review","Not Eligible")) -> Not Eligible | AB15: Married | AC15: 3 | AD15: Owned | AE15: 6.5 | AF15: 0 | AG15: =J15+AF15 -> 2427025 | AH15: 1 | AI15: N | AJ15: 300 | AK15: =(IF(S15="Credit Card",0.36,IF(S15="Personal Loan",0.14,IF(S15="Car Loan",0.09,0.085))))+IF(Z15="Low",0,IF(Z15="Medium",0.015,0.03)) -> 0.1 | AL15: =-PMT(AK15/12,AJ15,T15) -> 65260.652 | AM15: =IFERROR(T15/J15,0) -> 2.9590771 | AN15: =R15+AL15 -> 70433.992 | AO15: =IFERROR((AN15*12)/J15,0) -> 0.34824854 | AP15: 9052888 | AQ15: =IF(AP15>0,T15/AP15,"N/A") -> 0.79331082 | AR15: 46004 | AS15: Verified
A16: CUST00015 | B16: Kiran Sethi | C16: 9954725078 | D16: kiran.sethi754@yahoo.com | E16: 63 | F16: Male | G16: Surat | H16: Freelancer | I16: Self-Employed | J16: 1705881 | K16: 2 | L16: Y | M16: N | N16: Y | O16: N | P16: 503 | Q16: 150821 | R16: 10772.93 | S16: Personal Loan | T16: 548216 | U16: =IFERROR((R16*12)/J16,0) -> 0.07578205 | V16: 1 | W16: 78 | X16: 6.9 | Y16: =ROUND(0.4*((900-P16)/600*100)+0.3*MIN(U16*100,100)+0.2*MIN(V16*20,100)+0.1*W16,1) -> 40.5 | Z16: =IF(Y16<=30,"Low",IF(Y16<=60,"Medium","High")) -> Medium | AA16: =IF(AND(P16>=650,U16<=0.4,V16<=2,Y16<=50),"Eligible",IF(AND(P16>=550,V16<=4,Y16<=75),"Review","Not Eligible")) -> Not Eligible | AB16: Single | AC16: 2 | AD16: Rented | AE16: 11.7 | AF16: 0 | AG16: =J16+AF16 -> 1705881 | AH16: 0 | AI16: N | AJ16: 12 | AK16: =(IF(S16="Credit Card",0.36,IF(S16="Personal Loan",0.14,IF(S16="Car Loan",0.09,0.085))))+IF(Z16="Low",0,IF(Z16="Medium",0.015,0.03)) -> 0.155 | AL16: =-PMT(AK16/12,AJ16,T16) -> 49610.487 | AM16: =IFERROR(T16/J16,0) -> 0.32136825 | AN16: =R16+AL16 -> 60383.417 | AO16: =IFERROR((AN16*12)/J16,0) -> 0.42476644 | AP16: 0 | AQ16: =IF(AP16>0,T16/AP16,"N/A") -> N/A | AR16: 46112 | AS16: Verified
A17: CUST00016 | B17: Preeti Tiwari | C17: 9656152900 | D17: preeti.tiwari476@gmail.com | E17: 56 | F17: Male | G17: Hyderabad | H17: Business Owner | I17: Self-Employed | J17: 859264 | K17: 0 | L17: N | M17: N | N17: N | O17: N | P17: 753 | Q17: 52643.01 | R17: 907.64 | S17: Home Loan | U17: =IFERROR((R17*12)/J17,0) -> 0.012675592 | V17: 0 | W17: 20.1 | X17: 13 | Y17: =ROUND(0.4*((900-P17)/600*100)+0.3*MIN(U17*100,100)+0.2*MIN(V17*20,100)+0.1*W17,1) -> 12.2 | Z17: =IF(Y17<=30,"Low",IF(Y17<=60,"Medium","High")) -> Low | AA17: =IF(AND(P17>=650,U17<=0.4,V17<=2,Y17<=50),"Eligible",IF(AND(P17>=550,V17<=4,Y17<=75),"Review","Not Eligible")) -> Eligible | AB17: Married | AC17: 2 | AD17: Rented | AE17: 8.5 | AF17: 0 | AG17: =J17+AF17 -> 859264 | AH17: 0 | AI17: N | AJ17: 300 | AK17: =(IF(S17="Credit Card",0.36,IF(S17="Personal Loan",0.14,IF(S17="Car Loan",0.09,0.085))))+IF(Z17="Low",0,IF(Z17="Medium",0.015,0.03)) -> 0.085 | AL17: =-PMT(AK17/12,AJ17,T17) -> 0 | AM17: =IFERROR(T17/J17,0) -> 0 | AN17: =R17+AL17 -> 907.64 | AO17: =IFERROR((AN17*12)/J17,0) -> 0.012675592 | AP17: 7128348 | AQ17: =IF(AP17>0,T17/AP17,"N/A") -> 0 | AR17: 46041 | AS17: Verified
A18: CUST00017 | B18: Diya Mehta | C18: 9679984033 | D18: diya.mehta83@yahoo.com | E18: 30 | F18: Male | G18: Nagpur | H18: Self Employed - Business | I18: Self-Employed | J18: 1197383 | K18: 1 | L18: Y | M18: N | N18: N | O18: N | P18: 511 | Q18: 598374 | R18: 16621.5 | S18: Credit Card | U18: =IFERROR((R18*12)/J18,0) -> 0.16657828 | V18: 4 | W18: 59.7 | X18: 7.3 | Y18: =ROUND(0.4*((900-P18)/600*100)+0.3*MIN(U18*100,100)+0.2*MIN(V18*20,100)+0.1*W18,1) -> 52.9 | Z18: =IF(Y18<=30,"Low",IF(Y18<=60,"Medium","High")) -> Medium | AA18: =IF(AND(P18>=650,U18<=0.4,V18<=2,Y18<=50),"Eligible",IF(AND(P18>=550,V18<=4,Y18<=75),"Review","Not Eligible")) -> Not Eligible | AB18: Single | AC18: 1 | AD18: Owned | AE18: 8.1 | AF18: 0 | AG18: =J18+AF18 -> 1197383 | AH18: 0 | AI18: N | AJ18: 18 | AK18: =(IF(S18="Credit Card",0.36,IF(S18="Personal Loan",0.14,IF(S18="Car Loan",0.09,0.085))))+IF(Z18="Low",0,IF(Z18="Medium",0.015,0.03)) -> 0.375 | AL18: =-PMT(AK18/12,AJ18,T18) -> 0 | AM18: =IFERROR(T18/J18,0) -> 0 | AN18: =R18+AL18 -> 16621.5 | AO18: =IFERROR((AN18*12)/J18,0) -> 0.16657828 | AP18: 0 | AQ18: =IF(AP18>0,T18/AP18,"N/A") -> N/A | AR18: 46144 | AS18: Verified
A19: CUST00018 | B19: Saanvi Joshi | C19: 9131165166 | D19: saanvi.joshi399@outlook.com | E19: 63 | F19: Female | G19: Kolkata | H19: Business Owner | I19: Self-Employed | J19: 835309 | K19: 0 | L19: N | M19: N | N19: N | O19: N | P19: 327 | Q19: 7012 | R19: 179.8 | S19: Personal Loan | T19: 958959 | U19: =IFERROR((R19*12)/J19,0) -> 0.0025829962 | V19: 1 | W19: 9.8 | X19: 5.8 | Y19: =ROUND(0.4*((900-P19)/600*100)+0.3*MIN(U19*100,100)+0.2*MIN(V19*20,100)+0.1*W19,1) -> 43.3 | Z19: =IF(Y19<=30,"Low",IF(Y19<=60,"Medium","High")) -> Medium | AA19: =IF(AND(P19>=650,U19<=0.4,V19<=2,Y19<=50),"Eligible",IF(AND(P19>=550,V19<=4,Y19<=75),"Review","Not Eligible")) -> Not Eligible | AB19: Married | AC19: 1 | AD19: Rented | AE19: 11.6 | AF19: 0 | AG19: =J19+AF19 -> 835309 | AH19: 2 | AI19: N | AJ19: 12 | AK19: =(IF(S19="Credit Card",0.36,IF(S19="Personal Loan",0.14,IF(S19="Car Loan",0.09,0.085))))+IF(Z19="Low",0,IF(Z19="Medium",0.015,0.03)) -> 0.155 | AL19: =-PMT(AK19/12,AJ19,T19) -> 86780.435 | AM19: =IFERROR(T19/J19,0) -> 1.1480291 | AN19: =R19+AL19 -> 86960.235 | AO19: =IFERROR((AN19*12)/J19,0) -> 1.2492656 | AP19: 0 | AQ19: =IF(AP19>0,T19/AP19,"N/A") -> N/A | AR19: 46135 | AS19: Verified
A20: CUST00019 | B20: Shreya Verma | C20: 9475767056 | D20: shreya.verma230@gmail.com | E20: 62 | F20: Male | G20: Mumbai | H20: Self Employed - Professional | I20: Self-Employed | J20: 1136179 | K20: 1 | L20: N | M20: N | N20: Y | O20: N | P20: 417 | Q20: 384462.24 | R20: 15378.49 | S20: Home Loan | T20: 7367537 | U20: =IFERROR((R20*12)/J20,0) -> 0.16242324 | V20: 0 | W20: 40 | X20: 9.2 | Y20: =ROUND(0.4*((900-P20)/600*100)+0.3*MIN(U20*100,100)+0.2*MIN(V20*20,100)+0.1*W20,1) -> 41.1 | Z20: =IF(Y20<=30,"Low",IF(Y20<=60,"Medium","High")) -> Medium | AA20: =IF(AND(P20>=650,U20<=0.4,V20<=2,Y20<=50),"Eligible",IF(AND(P20>=550,V20<=4,Y20<=75),"Review","Not Eligible")) -> Not Eligible | AB20: Divorced | AC20: 2 | AD20: Rented | AE20: 5.2 | AF20: 584014 | AG20: =J20+AF20 -> 1720193 | AH20: 2 | AI20: N | AJ20: 300 | AK20: =(IF(S20="Credit Card",0.36,IF(S20="Personal Loan",0.14,IF(S20="Car Loan",0.09,0.085))))+IF(Z20="Low",0,IF(Z20="Medium",0.015,0.03)) -> 0.1 | AL20: =-PMT(AK20/12,AJ20,T20) -> 66948.864 | AM20: =IFERROR(T20/J20,0) -> 6.4844862 | AN20: =R20+AL20 -> 82327.354 | AO20: =IFERROR((AN20*12)/J20,0) -> 0.86951813 | AP20: 9203259 | AQ20: =IF(AP20>0,T20/AP20,"N/A") -> 0.80053566 | AR20: 45996 | AS20: Verified
A21: CUST00020 | B21: Deepak Saxena | C21: 9773496394 | D21: deepak.saxena249@gmail.com | E21: 65 | F21: Female | G21: Hyderabad | H21: Salaried - Private | I21: Salaried | J21: 1756278 | K21: 2 | L21: Y | M21: N | N21: Y | O21: N | P21: 312 | R21: 20819.87 | S21: Credit Card | T21: 247291 | U21: =IFERROR((R21*12)/J21,0) -> 0.1422545 | V21: 6 | W21: 65.4 | X21: 12.5 | Y21: =ROUND(0.4*((900-P21)/600*100)+0.3*MIN(U21*100,100)+0.2*MIN(V21*20,100)+0.1*W21,1) -> 70 | Z21: =IF(Y21<=30,"Low",IF(Y21<=60,"Medium","High")) -> High | AA21: =IF(AND(P21>=650,U21<=0.4,V21<=2,Y21<=50),"Eligible",IF(AND(P21>=550,V21<=4,Y21<=75),"Review","Not Eligible")) -> Not Eligible | AB21: Single | AC21: 1 | AD21: Rented | AE21: 29 | AF21: 756149 | AG21: =J21+AF21 -> 2512427 | AH21: 0 | AI21: N | AJ21: 36 | AK21: =(IF(S21="Credit Card",0.36,IF(S21="Personal Loan",0.14,IF(S21="Car Loan",0.09,0.085))))+IF(Z21="Low",0,IF(Z21="Medium",0.015,0.03)) -> 0.39 | AL21: =-PMT(AK21/12,AJ21,T21) -> 11753.324 | AM21: =IFERROR(T21/J21,0) -> 0.14080402 | AN21: =R21+AL21 -> 32573.194 | AO21: =IFERROR((AN21*12)/J21,0) -> 0.22256062 | AP21: 0 | AQ21: =IF(AP21>0,T21/AP21,"N/A") -> N/A | AR21: 46198 | AS21: Verified
A22: CUST00021 | B22: Rekha Rao | C22: 9991990632 | D22: rekha.rao958@gmail.com | E22: 38 | F22: Female | G22: Ahmedabad | H22: Business Owner | I22: Self-Employed | J22: 1889596 | K22: 1 | L22: Y | M22: N | N22: N | O22: N | P22: 663 | Q22: 904548 | R22: 27410.56 | S22: Car Loan | U22: =IFERROR((R22*12)/J22,0) -> 0.17407251 | V22: 1 | W22: 54.1 | X22: 3 | Y22: =ROUND(0.4*((900-P22)/600*100)+0.3*MIN(U22*100,100)+0.2*MIN(V22*20,100)+0.1*W22,1) -> 30.4 | Z22: =IF(Y22<=30,"Low",IF(Y22<=60,"Medium","High")) -> Medium | AA22: =IF(AND(P22>=650,U22<=0.4,V22<=2,Y22<=50),"Eligible",IF(AND(P22>=550,V22<=4,Y22<=75),"Review","Not Eligible")) -> Eligible | AB22: Married | AC22: 1 | AD22: Rented | AE22: 4.3 | AF22: 0 | AG22: =J22+AF22 -> 1889596 | AH22: 1 | AI22: N | AJ22: 24 | AK22: =(IF(S22="Credit Card",0.36,IF(S22="Personal Loan",0.14,IF(S22="Car Loan",0.09,0.085))))+IF(Z22="Low",0,IF(Z22="Medium",0.015,0.03)) -> 0.105 | AL22: =-PMT(AK22/12,AJ22,T22) -> 0 | AM22: =IFERROR(T22/J22,0) -> 0 | AN22: =R22+AL22 -> 27410.56 | AO22: =IFERROR((AN22*12)/J22,0) -> 0.17407251 | AP22: 939712 | AQ22: =IF(AP22>0,T22/AP22,"N/A") -> 0 | AR22: 46008 | AS22: Verified
A23: CUST00022 | B23: Rahul Iyer | C23: 9812921644 | D23: rahul.iyer596@outlook.com | E23: 51 | F23: Female | G23: Indore | H23: Freelancer | I23: Self-Employed | J23: 1687439 | K23: 1 | L23: Y | M23: N | N23: N | O23: N | P23: 497 | Q23: 319480.74 | R23: 5414.93 | S23: Personal Loan | T23: 250845 | U23: =IFERROR((R23*12)/J23,0) -> 0.038507561 | V23: 0 | W23: 51 | X23: 10.9 | Y23: =ROUND(0.4*((900-P23)/600*100)+0.3*MIN(U23*100,100)+0.2*MIN(V23*20,100)+0.1*W23,1) -> 33.1 | Z23: =IF(Y23<=30,"Low",IF(Y23<=60,"Medium","High")) -> Medium | AA23: =IF(AND(P23>=650,U23<=0.4,V23<=2,Y23<=50),"Eligible",IF(AND(P23>=550,V23<=4,Y23<=75),"Review","Not Eligible")) -> Not Eligible | AB23: Divorced | AC23: 2 | AD23: Owned | AE23: 3.3 | AF23: 320612 | AG23: =J23+AF23 -> 2008051 | AH23: 0 | AI23: N | AJ23: 60 | AK23: =(IF(S23="Credit Card",0.36,IF(S23="Personal Loan",0.14,IF(S23="Car Loan",0.09,0.085))))+IF(Z23="Low",0,IF(Z23="Medium",0.015,0.03)) -> 0.155 | AL23: =-PMT(AK23/12,AJ23,T23) -> 6033.6227 | AM23: =IFERROR(T23/J23,0) -> 0.14865426 | AN23: =R23+AL23 -> 11448.553 | AO23: =IFERROR((AN23*12)/J23,0) -> 0.081414873 | AP23: 0 | AQ23: =IF(AP23>0,T23/AP23,"N/A") -> N/A | AR23: 45959 | AS23: Verified
A24: CUST00023 | B24: Vihaan Bhatt | C24: 9413679331 | D24: vihaan.bhatt715@yahoo.com | E24: 61 | F24: Female | G24: Hyderabad | H24: Salaried - Private | I24: Salaried | J24: 1492605 | K24: 3 | L24: Y | M24: N | N24: Y | O24: Y | P24: 789 | Q24: 102172 | R24: 6385.76 | S24: Home Loan | T24: 5625069 | U24: =IFERROR((R24*12)/J24,0) -> 0.051339182 | V24: 0 | W24: 64.8 | X24: 1 | Y24: =ROUND(0.4*((900-P24)/600*100)+0.3*MIN(U24*100,100)+0.2*MIN(V24*20,100)+0.1*W24,1) -> 15.4 | Z24: =IF(Y24<=30,"Low",IF(Y24<=60,"Medium","High")) -> Low | AA24: =IF(AND(P24>=650,U24<=0.4,V24<=2,Y24<=50),"Eligible",IF(AND(P24>=550,V24<=4,Y24<=75),"Review","Not Eligible")) -> Eligible | AB24: Married | AC24: 2 | AD24: Owned | AE24: 29.8 | AF24: 723333 | AG24: =J24+AF24 -> 2215938 | AH24: 1 | AI24: N | AJ24: 180 | AK24: =(IF(S24="Credit Card",0.36,IF(S24="Personal Loan",0.14,IF(S24="Car Loan",0.09,0.085))))+IF(Z24="Low",0,IF(Z24="Medium",0.015,0.03)) -> 0.085 | AL24: =-PMT(AK24/12,AJ24,T24) -> 55392.28 | AM24: =IFERROR(T24/J24,0) -> 3.7686253 | AN24: =R24+AL24 -> 61778.04 | AO24: =IFERROR((AN24*12)/J24,0) -> 0.49667291 | AP24: 7559662 | AQ24: =IF(AP24>0,T24/AP24,"N/A") -> 0.74409001 | AR24: 46089 | AS24: Verified
A25: CUST00024 | B25: Tanya Iyer | C25: 9731924051 | D25: tanya.iyer440@outlook.com | E25: 57 | F25: Male | G25: Hyderabad | H25: Self Employed - Professional | I25: Self-Employed | J25: 1185103 | K25: 3 | L25: Y | M25: Y | N25: Y | O25: N | P25: 460 | Q25: 1902.6 | R25: 47.56 | S25: Home Loan | T25: 3943260 | U25: =IFERROR((R25*12)/J25,0) -> 0.00048157839 | V25: 0 | W25: 32.4 | X25: 4.4 | Y25: =ROUND(0.4*((900-P25)/600*100)+0.3*MIN(U25*100,100)+0.2*MIN(V25*20,100)+0.1*W25,1) -> 32.6 | Z25: =IF(Y25<=30,"Low",IF(Y25<=60,"Medium","High")) -> Medium | AA25: =IF(AND(P25>=650,U25<=0.4,V25<=2,Y25<=50),"Eligible",IF(AND(P25>=550,V25<=4,Y25<=75),"Review","Not Eligible")) -> Not Eligible | AB25: Single | AC25: 0 | AD25: Owned | AE25: 8.2 | AF25: 0 | AG25: =J25+AF25 -> 1185103 | AH25: 1 | AI25: N | AJ25: 180 | AK25: =(IF(S25="Credit Card",0.36,IF(S25="Personal Loan",0.14,IF(S25="Car Loan",0.09,0.085))))+IF(Z25="Low",0,IF(Z25="Medium",0.015,0.03)) -> 0.1 | AL25: =-PMT(AK25/12,AJ25,T25) -> 42374.474 | AM25: =IFERROR(T25/J25,0) -> 3.3273564 | AN25: =R25+AL25 -> 42422.034 | AO25: =IFERROR((AN25*12)/J25,0) -> 0.42955288 | AP25: 4953857 | AQ25: =IF(AP25>0,T25/AP25,"N/A") -> 0.79599795 | AR25: 46173 | AS25: Verified
A26: CUST00025 | B26: Ishaan Khanna | D26: ishaan.khanna847@yahoo.com | E26: 25 | F26: Male | G26: Kolkata | H26: Salaried - IT/Tech | I26: Salaried | J26: 1510520 | K26: 1 | L26: Y | M26: N | N26: N | O26: N | P26: 578 | R26: 10548.46 | S26: Home Loan | T26: 2174795 | U26: =IFERROR((R26*12)/J26,0) -> 0.083799963 | V26: 1 | W26: 89.5 | X26: 11.1 | Y26: =ROUND(0.4*((900-P26)/600*100)+0.3*MIN(U26*100,100)+0.2*MIN(V26*20,100)+0.1*W26,1) -> 36.9 | Z26: =IF(Y26<=30,"Low",IF(Y26<=60,"Medium","High")) -> Medium | AA26: =IF(AND(P26>=650,U26<=0.4,V26<=2,Y26<=50),"Eligible",IF(AND(P26>=550,V26<=4,Y26<=75),"Review","Not Eligible")) -> Review | AB26: Single | AC26: 0 | AD26: Owned | AE26: 2.8 | AF26: 0 | AG26: =J26+AF26 -> 1510520 | AH26: 1 | AI26: N | AJ26: 240 | AK26: =(IF(S26="Credit Card",0.36,IF(S26="Personal Loan",0.14,IF(S26="Car Loan",0.09,0.085))))+IF(Z26="Low",0,IF(Z26="Medium",0.015,0.03)) -> 0.1 | AL26: =-PMT(AK26/12,AJ26,T26) -> 20987.242 | AM26: =IFERROR(T26/J26,0) -> 1.4397658 | AN26: =R26+AL26 -> 31535.702 | AO26: =IFERROR((AN26*12)/J26,0) -> 0.25052858 | AP26: 2814319 | AQ26: =IF(AP26>0,T26/AP26,"N/A") -> 0.77276066 | AR26: 45984 | AS26: Verified
A27: CUST00026 | B27: Suresh Kapoor | C27: 9398668350 | D27: suresh.kapoor186@rediffmail.com | E27: 48 | F27: Female | G27: Bengaluru | H27: Business Owner | I27: Self-Employed | J27: 1759454 | K27: 3 | L27: Y | M27: N | N27: Y | O27: Y | P27: 721 | R27: 24409.74 | S27: Home Loan | U27: =IFERROR((R27*12)/J27,0) -> 0.16648169 | V27: 1 | W27: 48.2 | X27: 4.9 | Y27: =ROUND(0.4*((900-P27)/600*100)+0.3*MIN(U27*100,100)+0.2*MIN(V27*20,100)+0.1*W27,1) -> 25.7 | Z27: =IF(Y27<=30,"Low",IF(Y27<=60,"Medium","High")) -> Low | AA27: =IF(AND(P27>=650,U27<=0.4,V27<=2,Y27<=50),"Eligible",IF(AND(P27>=550,V27<=4,Y27<=75),"Review","Not Eligible")) -> Eligible | AB27: Married | AC27: 4 | AD27: Owned | AE27: 14 | AF27: 0 | AG27: =J27+AF27 -> 1759454 | AH27: 1 | AI27: N | AJ27: 300 | AK27: =(IF(S27="Credit Card",0.36,IF(S27="Personal Loan",0.14,IF(S27="Car Loan",0.09,0.085))))+IF(Z27="Low",0,IF(Z27="Medium",0.015,0.03)) -> 0.085 | AL27: =-PMT(AK27/12,AJ27,T27) -> 0 | AM27: =IFERROR(T27/J27,0) -> 0 | AN27: =R27+AL27 -> 24409.74 | AO27: =IFERROR((AN27*12)/J27,0) -> 0.16648169 | AP27: 9168240 | AQ27: =IF(AP27>0,T27/AP27,"N/A") -> 0 | AR27: 46160 | AS27: Verified
A28: CUST00027 | B28: Anil Joshi | C28: 9771527524 | D28: anil.joshi453@gmail.com | E28: 34 | F28: Female | G28: Coimbatore | H28: Self Employed - Business | I28: Self-Employed | J28: 1508081 | K28: 2 | L28: Y | M28: N | N28: Y | O28: N | P28: 545 | Q28: 642246 | R28: 20717.61 | S28: Credit Card | T28: 309538 | U28: =IFERROR((R28*12)/J28,0) -> 0.16485276 | V28: 0 | W28: 26.3 | X28: 12.7 | Y28: =ROUND(0.4*((900-P28)/600*100)+0.3*MIN(U28*100,100)+0.2*MIN(V28*20,100)+0.1*W28,1) -> 31.2 | Z28: =IF(Y28<=30,"Low",IF(Y28<=60,"Medium","High")) -> Medium | AA28: =IF(AND(P28>=650,U28<=0.4,V28<=2,Y28<=50),"Eligible",IF(AND(P28>=550,V28<=4,Y28<=75),"Review","Not Eligible")) -> Not Eligible | AB28: Married | AC28: 3 | AD28: Rented | AE28: 2.3 | AF28: 0 | AG28: =J28+AF28 -> 1508081 | AH28: 0 | AI28: N | AJ28: 36 | AK28: =(IF(S28="Credit Card",0.36,IF(S28="Personal Loan",0.14,IF(S28="Car Loan",0.09,0.085))))+IF(Z28="Low",0,IF(Z28="Medium",0.015,0.03)) -> 0.375 | AL28: =-PMT(AK28/12,AJ28,T28) -> 14443.691 | AM28: =IFERROR(T28/J28,0) -> 0.2052529 | AN28: =R28+AL28 -> 35161.301 | AO28: =IFERROR((AN28*12)/J28,0) -> 0.27978312 | AP28: 0 | AQ28: =IF(AP28>0,T28/AP28,"N/A") -> N/A | AR28: 46142 | AS28: Pending
A29: CUST00028 | B29: Rahul Kapoor | C29: 9691916368 | E29: 33 | F29: Male | G29: Bengaluru | H29: Salaried - IT/Tech | I29: Salaried | J29: 2040394 | K29: 2 | L29: Y | M29: N | N29: N | O29: Y | P29: 605 | Q29: 1025268.5 | R29: 20923.85 | S29: Home Loan | U29: =IFERROR((R29*12)/J29,0) -> 0.1230577 | V29: 0 | W29: 51 | X29: 5.1 | Y29: =ROUND(0.4*((900-P29)/600*100)+0.3*MIN(U29*100,100)+0.2*MIN(V29*20,100)+0.1*W29,1) -> 28.5 | Z29: =IF(Y29<=30,"Low",IF(Y29<=60,"Medium","High")) -> Low | AA29: =IF(AND(P29>=650,U29<=0.4,V29<=2,Y29<=50),"Eligible",IF(AND(P29>=550,V29<=4,Y29<=75),"Review","Not Eligible")) -> Review | AB29: Single | AC29: 1 | AD29: Company Provided | AE29: 10.5 | AF29: 0 | AG29: =J29+AF29 -> 2040394 | AH29: 0 | AI29: N | AJ29: 300 | AK29: =(IF(S29="Credit Card",0.36,IF(S29="Personal Loan",0.14,IF(S29="Car Loan",0.09,0.085))))+IF(Z29="Low",0,IF(Z29="Medium",0.015,0.03)) -> 0.085 | AL29: =-PMT(AK29/12,AJ29,T29) -> 0 | AM29: =IFERROR(T29/J29,0) -> 0 | AN29: =R29+AL29 -> 20923.85 | AO29: =IFERROR((AN29*12)/J29,0) -> 0.1230577 | AP29: 3188454 | AQ29: =IF(AP29>0,T29/AP29,"N/A") -> 0 | AR29: 46137 | AS29: Verified
A30: CUST00029 | B30: Preeti Chopra | C30: 9514548900 | D30: preeti.chopra680@yahoo.com | E30: 52 | F30: Male | G30: Chennai | H30: Freelancer | I30: Self-Employed | J30: 1692486 | K30: 0 | L30: N | M30: N | N30: N | O30: N | P30: 767 | Q30: 2597.56 | R30: 123.69 | S30: Home Loan | T30: 6992703 | U30: =IFERROR((R30*12)/J30,0) -> 0.00087698214 | V30: 6 | W30: 12.1 | X30: 11.8 | Y30: =ROUND(0.4*((900-P30)/600*100)+0.3*MIN(U30*100,100)+0.2*MIN(V30*20,100)+0.1*W30,1) -> 30.1 | Z30: =IF(Y30<=30,"Low",IF(Y30<=60,"Medium","High")) -> Medium | AA30: =IF(AND(P30>=650,U30<=0.4,V30<=2,Y30<=50),"Eligible",IF(AND(P30>=550,V30<=4,Y30<=75),"Review","Not Eligible")) -> Not Eligible | AB30: Married | AC30: 2 | AD30: Owned | AE30: 2.7 | AF30: 655768 | AG30: =J30+AF30 -> 2348254 | AH30: 0 | AI30: Y | AJ30: 300 | AK30: =(IF(S30="Credit Card",0.36,IF(S30="Personal Loan",0.14,IF(S30="Car Loan",0.09,0.085))))+IF(Z30="Low",0,IF(Z30="Medium",0.015,0.03)) -> 0.1 | AL30: =-PMT(AK30/12,AJ30,T30) -> 63542.744 | AM30: =IFERROR(T30/J30,0) -> 4.1316165 | AN30: =R30+AL30 -> 63666.434 | AO30: =IFERROR((AN30*12)/J30,0) -> 0.45140534 | AP30: 9566687 | AQ30: =IF(AP30>0,T30/AP30,"N/A") -> 0.73094301 | AR30: 45913 | AS30: Verified
A31: CUST00030 | B31: Rahul Mishra | D31: rahul.mishra944@outlook.com | E31: 35 | F31: Male | G31: Indore | H31: Salaried - Government | I31: Salaried | J31: 721557 | K31: 2 | L31: Y | M31: N | N31: N | O31: Y | P31: 357 | R31: 3628.83 | S31: Home Loan | T31: 2721127 | U31: =IFERROR((R31*12)/J31,0) -> 0.060349993 | V31: 0 | W31: 44.1 | X31: 10.3 | Y31: =ROUND(0.4*((900-P31)/600*100)+0.3*MIN(U31*100,100)+0.2*MIN(V31*20,100)+0.1*W31,1) -> 42.4 | Z31: =IF(Y31<=30,"Low",IF(Y31<=60,"Medium","High")) -> Medium | AA31: =IF(AND(P31>=650,U31<=0.4,V31<=2,Y31<=50),"Eligible",IF(AND(P31>=550,V31<=4,Y31<=75),"Review","Not Eligible")) -> Not Eligible | AB31: Married | AC31: 0 | AD31: Rented | AE31: 5.5 | AF31: 0 | AG31: =J31+AF31 -> 721557 | AH31: 0 | AI31: N | AJ31: 180 | AK31: =(IF(S31="Credit Card",0.36,IF(S31="Personal Loan",0.14,IF(S31="Car Loan",0.09,0.085))))+IF(Z31="Low",0,IF(Z31="Medium",0.015,0.03)) -> 0.1 | AL31: =-PMT(AK31/12,AJ31,T31) -> 29241.37 | AM31: =IFERROR(T31/J31,0) -> 3.7711879 | AN31: =R31+AL31 -> 32870.2 | AO31: =IFERROR((AN31*12)/J31,0) -> 0.54665453 | AP31: 3443008 | AQ31: =IF(AP31>0,T31/AP31,"N/A") -> 0.79033421 | AR31: 46025 | AS31: Verified
A32: CUST00031 | B32: Mahesh Sharma | C32: 9963968184 | E32: 64 | F32: Male | G32: Bengaluru | H32: Business Owner | I32: Self-Employed | J32: 1749407 | K32: 1 | L32: N | M32: Y | N32: N | O32: N | P32: 767 | Q32: 887268.36 | R32: 36969.51 | S32: Home Loan | U32: =IFERROR((R32*12)/J32,0) -> 0.25359114 | V32: 0 | W32: 41.2 | X32: 5.5 | Y32: =ROUND(0.4*((900-P32)/600*100)+0.3*MIN(U32*100,100)+0.2*MIN(V32*20,100)+0.1*W32,1) -> 20.6 | Z32: =IF(Y32<=30,"Low",IF(Y32<=60,"Medium","High")) -> Low | AA32: =IF(AND(P32>=650,U32<=0.4,V32<=2,Y32<=50),"Eligible",IF(AND(P32>=550,V32<=4,Y32<=75),"Review","Not Eligible")) -> Eligible | AB32: Married | AC32: 2 | AD32: Owned | AE32: 25 | AF32: 0 | AG32: =J32+AF32 -> 1749407 | AH32: 0 | AI32: N | AJ32: 120 | AK32: =(IF(S32="Credit Card",0.36,IF(S32="Personal Loan",0.14,IF(S32="Car Loan",0.09,0.085))))+IF(Z32="Low",0,IF(Z32="Medium",0.015,0.03)) -> 0.085 | AL32: =-PMT(AK32/12,AJ32,T32) -> 0 | AM32: =IFERROR(T32/J32,0) -> 0 | AN32: =R32+AL32 -> 36969.51 | AO32: =IFERROR((AN32*12)/J32,0) -> 0.25359114 | AP32: 7650724 | AQ32: =IF(AP32>0,T32/AP32,"N/A") -> 0 | AR32: 46149 | AS32: Verified
A33: CUST00032 | B33: Lata Iyer | C33: 9932945529 | D33: lata.iyer819@yahoo.com | E33: 59 | F33: Female | G33: Ahmedabad | H33: Self Employed - Professional | I33: Self-Employed | J33: 1351204 | K33: 0 | L33: N | M33: N | N33: N | O33: N | P33: 399 | Q33: 122068 | R33: 2303.17 | S33: Credit Card | T33: 181969 | U33: =IFERROR((R33*12)/J33,0) -> 0.02045438 | V33: 3 | W33: 8.2 | X33: 5.6 | Y33: =ROUND(0.4*((900-P33)/600*100)+0.3*MIN(U33*100,100)+0.2*MIN(V33*20,100)+0.1*W33,1) -> 46.8 | Z33: =IF(Y33<=30,"Low",IF(Y33<=60,"Medium","High")) -> Medium | AA33: =IF(AND(P33>=650,U33<=0.4,V33<=2,Y33<=50),"Eligible",IF(AND(P33>=550,V33<=4,Y33<=75),"Review","Not Eligible")) -> Not Eligible | AB33: Married | AC33: 3 | AD33: Owned | AE33: 12.6 | AF33: 739885 | AG33: =J33+AF33 -> 2091089 | AH33: 2 | AI33: N | AJ33: 24 | AK33: =(IF(S33="Credit Card",0.36,IF(S33="Personal Loan",0.14,IF(S33="Car Loan",0.09,0.085))))+IF(Z33="Low",0,IF(Z33="Medium",0.015,0.03)) -> 0.375 | AL33: =-PMT(AK33/12,AJ33,T33) -> 10889.997 | AM33: =IFERROR(T33/J33,0) -> 0.13467174 | AN33: =R33+AL33 -> 13193.167 | AO33: =IFERROR((AN33*12)/J33,0) -> 0.1171681 | AP33: 0 | AQ33: =IF(AP33>0,T33/AP33,"N/A") -> N/A | AR33: 45979 | AS33: Verified
A34: CUST00033 | B34: Geeta Joshi | C34: 9965960427 | D34: geeta.joshi303@outlook.com | E34: 28 | F34: Female | G34: Bengaluru | H34: Self Employed - Business | I34: Self-Employed | J34: 1246296 | K34: 0 | L34: N | M34: N | N34: N | O34: N | P34: 870 | Q34: 45586.4 | R34: 1232.06 | S34: Credit Card | T34: 158652 | U34: =IFERROR((R34*12)/J34,0) -> 0.011862928 | V34: 1 | W34: 48.2 | X34: 10.2 | Y34: =ROUND(0.4*((900-P34)/600*100)+0.3*MIN(U34*100,100)+0.2*MIN(V34*20,100)+0.1*W34,1) -> 11.2 | Z34: =IF(Y34<=30,"Low",IF(Y34<=60,"Medium","High")) -> Low | AA34: =IF(AND(P34>=650,U34<=0.4,V34<=2,Y34<=50),"Eligible",IF(AND(P34>=550,V34<=4,Y34<=75),"Review","Not Eligible")) -> Eligible | AB34: Single | AC34: 2 | AD34: Rented | AE34: 6.6 | AF34: 325366 | AG34: =J34+AF34 -> 1571662 | AH34: 0 | AI34: Y | AJ34: 24 | AK34: =(IF(S34="Credit Card",0.36,IF(S34="Personal Loan",0.14,IF(S34="Car Loan",0.09,0.085))))+IF(Z34="Low",0,IF(Z34="Medium",0.015,0.03)) -> 0.36 | AL34: =-PMT(AK34/12,AJ34,T34) -> 9367.9906 | AM34: =IFERROR(T34/J34,0) -> 0.12729881 | AN34: =R34+AL34 -> 10600.051 | AO34: =IFERROR((AN34*12)/J34,0) -> 0.10206292 | AP34: 0 | AQ34: =IF(AP34>0,T34/AP34,"N/A") -> N/A | AR34: 46207 | AS34: Verified
A35: CUST00034 | B35: Arjun Mishra | D35: arjun.mishra476@outlook.com | E35: 62 | F35: Female | G35: Hyderabad | H35: Self Employed - Business | I35: Self-Employed | J35: 490198 | K35: 1 | L35: N | M35: N | N35: N | O35: Y | P35: 850 | Q35: 39901 | R35: 973.2 | S35: Car Loan | T35: 1432865 | U35: =IFERROR((R35*12)/J35,0) -> 0.023823843 | V35: 0 | W35: 75.5 | X35: 2.5 | Y35: =ROUND(0.4*((900-P35)/600*100)+0.3*MIN(U35*100,100)+0.2*MIN(V35*20,100)+0.1*W35,1) -> 11.6 | Z35: =IF(Y35<=30,"Low",IF(Y35<=60,"Medium","High")) -> Low | AA35: =IF(AND(P35>=650,U35<=0.4,V35<=2,Y35<=50),"Eligible",IF(AND(P35>=550,V35<=4,Y35<=75),"Review","Not Eligible")) -> Eligible | AB35: Married | AC35: 0 | AD35: Rented | AE35: 12.4 | AF35: 0 | AG35: =J35+AF35 -> 490198 | AH35: 0 | AI35: N | AJ35: 60 | AK35: =(IF(S35="Credit Card",0.36,IF(S35="Personal Loan",0.14,IF(S35="Car Loan",0.09,0.085))))+IF(Z35="Low",0,IF(Z35="Medium",0.015,0.03)) -> 0.09 | AL35: =-PMT(AK35/12,AJ35,T35) -> 29743.921 | AM35: =IFERROR(T35/J35,0) -> 2.9230331 | AN35: =R35+AL35 -> 30717.121 | AO35: =IFERROR((AN35*12)/J35,0) -> 0.75195217 | AP35: 1631946 | AQ35: =IF(AP35>0,T35/AP35,"N/A") -> 0.87801006 | AR35: 46015 | AS35: Verified
A36: CUST00035 | B36: Reyansh Pandey | E36: 24 | F36: Female | G36: Jaipur | H36: Self Employed - Professional | I36: Self-Employed | J36: 812374 | K36: 1 | L36: N | M36: N | N36: Y | O36: N | P36: 321 | Q36: 24653.2 | R36: 747.07 | S36: Personal Loan | T36: 182040 | U36: =IFERROR((R36*12)/J36,0) -> 0.011035361 | V36: 3 | W36: 24.5 | X36: 12.5 | Y36: =ROUND(0.4*((900-P36)/600*100)+0.3*MIN(U36*100,100)+0.2*MIN(V36*20,100)+0.1*W36,1) -> 53.4 | Z36: =IF(Y36<=30,"Low",IF(Y36<=60,"Medium","High")) -> Medium | AA36: =IF(AND(P36>=650,U36<=0.4,V36<=2,Y36<=50),"Eligible",IF(AND(P36>=550,V36<=4,Y36<=75),"Review","Not Eligible")) -> Not Eligible | AB36: Married | AC36: 2 | AD36: Rented | AE36: 0.9 | AF36: 0 | AG36: =J36+AF36 -> 812374 | AH36: 1 | AI36: N | AJ36: 36 | AK36: =(IF(S36="Credit Card",0.36,IF(S36="Personal Loan",0.14,IF(S36="Car Loan",0.09,0.085))))+IF(Z36="Low",0,IF(Z36="Medium",0.015,0.03)) -> 0.155 | AL36: =-PMT(AK36/12,AJ36,T36) -> 6355.1404 | AM36: =IFERROR(T36/J36,0) -> 0.22408398 | AN36: =R36+AL36 -> 7102.2104 | AO36: =IFERROR((AN36*12)/J36,0) -> 0.10491045 | AP36: 0 | AQ36: =IF(AP36>0,T36/AP36,"N/A") -> N/A | AR36: 45969 | AS36: Pending
A37: CUST00036 | B37: Shreya Nair | C37: 9957397689 | D37: shreya.nair179@gmail.com | E37: 63 | F37: Male | G37: Chennai | H37: Salaried - Private | I37: Salaried | J37: 1802577 | K37: 2 | L37: N | M37: Y | N37: N | O37: Y | P37: 353 | R37: 3607.77 | S37: Credit Card | U37: =IFERROR((R37*12)/J37,0) -> 0.024017415 | V37: 0 | W37: 47.6 | X37: 5.6 | Y37: =ROUND(0.4*((900-P37)/600*100)+0.3*MIN(U37*100,100)+0.2*MIN(V37*20,100)+0.1*W37,1) -> 41.9 | Z37: =IF(Y37<=30,"Low",IF(Y37<=60,"Medium","High")) -> Medium | AA37: =IF(AND(P37>=650,U37<=0.4,V37<=2,Y37<=50),"Eligible",IF(AND(P37>=550,V37<=4,Y37<=75),"Review","Not Eligible")) -> Not Eligible | AB37: Married | AC37: 1 | AD37: Owned | AE37: 18.6 | AF37: 0 | AG37: =J37+AF37 -> 1802577 | AH37: 2 | AI37: N | AJ37: 24 | AK37: =(IF(S37="Credit Card",0.36,IF(S37="Personal Loan",0.14,IF(S37="Car Loan",0.09,0.085))))+IF(Z37="Low",0,IF(Z37="Medium",0.015,0.03)) -> 0.375 | AL37: =-PMT(AK37/12,AJ37,T37) -> 0 | AM37: =IFERROR(T37/J37,0) -> 0 | AN37: =R37+AL37 -> 3607.77 | AO37: =IFERROR((AN37*12)/J37,0) -> 0.024017415 | AP37: 0 | AQ37: =IF(AP37>0,T37/AP37,"N/A") -> N/A | AR37: 46129 | AS37: Verified
A38: CUST00037 | B38: Vivaan Verma | C38: 9614302907 | D38: vivaan.verma868@hotmail.com | E38: 48 | F38: Male | G38: Chandigarh | H38: Business Owner | I38: Self-Employed | J38: 608242 | K38: 2 | L38: N | M38: N | N38: Y | O38: Y | P38: 899 | Q38: 200120 | R38: 6253.75 | S38: Home Loan | U38: =IFERROR((R38*12)/J38,0) -> 0.12338017 | V38: 1 | W38: 48.1 | X38: 9.2 | Y38: =ROUND(0.4*((900-P38)/600*100)+0.3*MIN(U38*100,100)+0.2*MIN(V38*20,100)+0.1*W38,1) -> 12.6 | Z38: =IF(Y38<=30,"Low",IF(Y38<=60,"Medium","High")) -> Low | AA38: =IF(AND(P38>=650,U38<=0.4,V38<=2,Y38<=50),"Eligible",IF(AND(P38>=550,V38<=4,Y38<=75),"Review","Not Eligible")) -> Eligible | AB38: Married | AC38: 2 | AD38: Rented | AE38: 17.7 | AF38: 0 | AG38: =J38+AF38 -> 608242 | AH38: 1 | AI38: N | AJ38: 300 | AK38: =(IF(S38="Credit Card",0.36,IF(S38="Personal Loan",0.14,IF(S38="Car Loan",0.09,0.085))))+IF(Z38="Low",0,IF(Z38="Medium",0.015,0.03)) -> 0.085 | AL38: =-PMT(AK38/12,AJ38,T38) -> 0 | AM38: =IFERROR(T38/J38,0) -> 0 | AN38: =R38+AL38 -> 6253.75 | AO38: =IFERROR((AN38*12)/J38,0) -> 0.12338017 | AP38: 8933633 | AQ38: =IF(AP38>0,T38/AP38,"N/A") -> 0 | AR38: 46106 | AS38: Verified
A39: CUST00038 | B39: Neha Chopra | C39: 9546665485 | D39: neha.chopra748@gmail.com | E39: 41 | F39: Female | G39: Lucknow | H39: Salaried - IT/Tech | I39: Salaried | J39: 1869932 | K39: 1 | L39: N | M39: N | N39: N | O39: Y | P39: 387 | Q39: 104600 | R39: 5811.13 | S39: Car Loan | T39: 572871 | U39: =IFERROR((R39*12)/J39,0) -> 0.03729203 | V39: 1 | W39: 60.7 | X39: 8.5 | Y39: =ROUND(0.4*((900-P39)/600*100)+0.3*MIN(U39*100,100)+0.2*MIN(V39*20,100)+0.1*W39,1) -> 45.4 | Z39: =IF(Y39<=30,"Low",IF(Y39<=60,"Medium","High")) -> Medium | AA39: =IF(AND(P39>=650,U39<=0.4,V39<=2,Y39<=50),"Eligible",IF(AND(P39>=550,V39<=4,Y39<=75),"Review","Not Eligible")) -> Not Eligible | AB39: Married | AC39: 0 | AD39: Owned | AE39: 13.4 | AF39: 0 | AG39: =J39+AF39 -> 1869932 | AH39: 2 | AI39: N | AJ39: 48 | AK39: =(IF(S39="Credit Card",0.36,IF(S39="Personal Loan",0.14,IF(S39="Car Loan",0.09,0.085))))+IF(Z39="Low",0,IF(Z39="Medium",0.015,0.03)) -> 0.105 | AL39: =-PMT(AK39/12,AJ39,T39) -> 14667.434 | AM39: =IFERROR(T39/J39,0) -> 0.30635927 | AN39: =R39+AL39 -> 20478.564 | AO39: =IFERROR((AN39*12)/J39,0) -> 0.13141802 | AP39: 670306 | AQ39: =IF(AP39>0,T39/AP39,"N/A") -> 0.85464101 | AR39: 46075 | AS39: Verified
A40: CUST00039 | B40: Sneha Reddy | C40: 9266140258 | E40: 35 | F40: Male | G40: Kanpur | H40: Freelancer | I40: Self-Employed | J40: 1841662 | K40: 3 | L40: Y | M40: Y | N40: Y | O40: N | P40: 874 | R40: 21115.12 | S40: Credit Card | T40: 339288 | U40: =IFERROR((R40*12)/J40,0) -> 0.13758303 | V40: 5 | W40: 83.8 | X40: 4.2 | Y40: =ROUND(0.4*((900-P40)/600*100)+0.3*MIN(U40*100,100)+0.2*MIN(V40*20,100)+0.1*W40,1) -> 34.2 | Z40: =IF(Y40<=30,"Low",IF(Y40<=60,"Medium","High")) -> Medium | AA40: =IF(AND(P40>=650,U40<=0.4,V40<=2,Y40<=50),"Eligible",IF(AND(P40>=550,V40<=4,Y40<=75),"Review","Not Eligible")) -> Not Eligible | AB40: Married | AC40: 2 | AD40: Owned | AE40: 5 | AF40: 802397 | AG40: =J40+AF40 -> 2644059 | AH40: 1 | AI40: N | AJ40: 18 | AK40: =(IF(S40="Credit Card",0.36,IF(S40="Personal Loan",0.14,IF(S40="Car Loan",0.09,0.085))))+IF(Z40="Low",0,IF(Z40="Medium",0.015,0.03)) -> 0.375 | AL40: =-PMT(AK40/12,AJ40,T40) -> 24930.631 | AM40: =IFERROR(T40/J40,0) -> 0.18422925 | AN40: =R40+AL40 -> 46045.751 | AO40: =IFERROR((AN40*12)/J40,0) -> 0.30002737 | AP40: 0 | AQ40: =IF(AP40>0,T40/AP40,"N/A") -> N/A | AR40: 46219 | AS40: Pending
A41: CUST00040 | B41: Sai Yadav | C41: 9669601448 | D41: sai.yadav221@hotmail.com | E41: 47 | F41: Female | G41: Lucknow | H41: Self Employed - Business | I41: Self-Employed | J41: 1852115 | K41: 1 | L41: Y | M41: N | N41: N | O41: N | P41: 353 | Q41: 172891 | R41: 2881.52 | S41: Credit Card | T41: 373353 | U41: =IFERROR((R41*12)/J41,0) -> 0.018669597 | V41: 0 | W41: 47.1 | X41: 6.5 | Y41: =ROUND(0.4*((900-P41)/600*100)+0.3*MIN(U41*100,100)+0.2*MIN(V41*20,100)+0.1*W41,1) -> 41.7 | Z41: =IF(Y41<=30,"Low",IF(Y41<=60,"Medium","High")) -> Medium | AA41: =IF(AND(P41>=650,U41<=0.4,V41<=2,Y41<=50),"Eligible",IF(AND(P41>=550,V41<=4,Y41<=75),"Review","Not Eligible")) -> Not Eligible | AB41: Single | AC41: 1 | AD41: Owned | AE41: 13.5 | AF41: 233167 | AG41: =J41+AF41 -> 2085282 | AH41: 1 | AI41: N | AJ41: 24 | AK41: =(IF(S41="Credit Card",0.36,IF(S41="Personal Loan",0.14,IF(S41="Car Loan",0.09,0.085))))+IF(Z41="Low",0,IF(Z41="Medium",0.015,0.03)) -> 0.375 | AL41: =-PMT(AK41/12,AJ41,T41) -> 22343.437 | AM41: =IFERROR(T41/J41,0) -> 0.20158198 | AN41: =R41+AL41 -> 25224.957 | AO41: =IFERROR((AN41*12)/J41,0) -> 0.1634345 | AP41: 0 | AQ41: =IF(AP41>0,T41/AP41,"N/A") -> N/A | AR41: 45918 | AS41: Verified
A42: CUST00041 | B42: Simran Verma | D42: simran.verma210@outlook.com | E42: 34 | F42: Male | G42: Jaipur | H42: Salaried - IT/Tech | I42: Salaried | J42: 1676244 | K42: 2 | L42: Y | M42: N | N42: N | O42: Y | P42: 845 | R42: 16084.43 | S42: Car Loan | U42: =IFERROR((R42*12)/J42,0) -> 0.11514622 | V42: 0 | W42: 75.5 | X42: 6.7 | Y42: =ROUND(0.4*((900-P42)/600*100)+0.3*MIN(U42*100,100)+0.2*MIN(V42*20,100)+0.1*W42,1) -> 14.7 | Z42: =IF(Y42<=30,"Low",IF(Y42<=60,"Medium","High")) -> Low | AA42: =IF(AND(P42>=650,U42<=0.4,V42<=2,Y42<=50),"Eligible",IF(AND(P42>=550,V42<=4,Y42<=75),"Review","Not Eligible")) -> Eligible | AB42: Married | AC42: 0 | AD42: Owned | AE42: 5.8 | AF42: 0 | AG42: =J42+AF42 -> 1676244 | AH42: 1 | AI42: N | AJ42: 60 | AK42: =(IF(S42="Credit Card",0.36,IF(S42="Personal Loan",0.14,IF(S42="Car Loan",0.09,0.085))))+IF(Z42="Low",0,IF(Z42="Medium",0.015,0.03)) -> 0.09 | AL42: =-PMT(AK42/12,AJ42,T42) -> 0 | AM42: =IFERROR(T42/J42,0) -> 0 | AN42: =R42+AL42 -> 16084.43 | AO42: =IFERROR((AN42*12)/J42,0) -> 0.11514622 | AP42: 475593 | AQ42: =IF(AP42>0,T42/AP42,"N/A") -> 0 | AR42: 46061 | AS42: Verified
A43: CUST00042 | B43: Swati Kapoor | D43: swati.kapoor707@outlook.com | E43: 26 | F43: Female | G43: Hyderabad | H43: Self Employed - Professional | I43: Self-Employed | J43: 2127359 | K43: 0 | L43: N | M43: N | N43: N | O43: N | P43: 647 | Q43: 47136 | R43: 2142.56 | S43: Credit Card | T43: 287640 | U43: =IFERROR((R43*12)/J43,0) -> 0.012085746 | V43: 1 | W43: 55.4 | X43: 3.1 | Y43: =ROUND(0.4*((900-P43)/600*100)+0.3*MIN(U43*100,100)+0.2*MIN(V43*20,100)+0.1*W43,1) -> 26.8 | Z43: =IF(Y43<=30,"Low",IF(Y43<=60,"Medium","High")) -> Low | AA43: =IF(AND(P43>=650,U43<=0.4,V43<=2,Y43<=50),"Eligible",IF(AND(P43>=550,V43<=4,Y43<=75),"Review","Not Eligible")) -> Review | AB43: Single | AC43: 1 | AD43: Company Provided | AE43: 3.3 | AF43: 227103 | AG43: =J43+AF43 -> 2354462 | AH43: 0 | AI43: N | AJ43: 18 | AK43: =(IF(S43="Credit Card",0.36,IF(S43="Personal Loan",0.14,IF(S43="Car Loan",0.09,0.085))))+IF(Z43="Low",0,IF(Z43="Medium",0.015,0.03)) -> 0.36 | AL43: =-PMT(AK43/12,AJ43,T43) -> 20913.929 | AM43: =IFERROR(T43/J43,0) -> 0.1352099 | AN43: =R43+AL43 -> 23056.489 | AO43: =IFERROR((AN43*12)/J43,0) -> 0.13005697 | AP43: 0 | AQ43: =IF(AP43>0,T43/AP43,"N/A") -> N/A | AR43: 46230 | AS43: Verified
A44: CUST00043 | B44: Sunil Mishra | C44: 9630554118 | E44: 58 | F44: Female | G44: Lucknow | H44: Salaried - Healthcare | I44: Salaried | J44: 933161 | K44: 1 | L44: Y | M44: N | N44: N | O44: N | P44: 357 | R44: 12315.7 | S44: Car Loan | T44: 1268344 | U44: =IFERROR((R44*12)/J44,0) -> 0.15837396 | V44: 1 | W44: 10.4 | X44: 12.5 | Y44: =ROUND(0.4*((900-P44)/600*100)+0.3*MIN(U44*100,100)+0.2*MIN(V44*20,100)+0.1*W44,1) -> 46 | Z44: =IF(Y44<=30,"Low",IF(Y44<=60,"Medium","High")) -> Medium | AA44: =IF(AND(P44>=650,U44<=0.4,V44<=2,Y44<=50),"Eligible",IF(AND(P44>=550,V44<=4,Y44<=75),"Review","Not Eligible")) -> Not Eligible | AB44: Married | AC44: 3 | AD44: Rented | AE44: 18.6 | AF44: 0 | AG44: =J44+AF44 -> 933161 | AH44: 0 | AI44: N | AJ44: 84 | AK44: =(IF(S44="Credit Card",0.36,IF(S44="Personal Loan",0.14,IF(S44="Car Loan",0.09,0.085))))+IF(Z44="Low",0,IF(Z44="Medium",0.015,0.03)) -> 0.105 | AL44: =-PMT(AK44/12,AJ44,T44) -> 21385.134 | AM44: =IFERROR(T44/J44,0) -> 1.359191 | AN44: =R44+AL44 -> 33700.834 | AO44: =IFERROR((AN44*12)/J44,0) -> 0.43337645 | AP44: 1559017 | AQ44: =IF(AP44>0,T44/AP44,"N/A") -> 0.81355367 | AR44: 46125 | AS44: Verified
A45: CUST00044 | B45: Nisha Mishra | C45: 9302120588 | D45: nisha.mishra330@rediffmail.com | E45: 51 | F45: Male | G45: Delhi | H45: Business Owner | I45: Self-Employed | J45: 734118 | K45: 1 | L45: N | M45: N | N45: N | O45: Y | P45: 476 | R45: 302.47 | S45: Home Loan | T45: 5186137 | U45: =IFERROR((R45*12)/J45,0) -> 0.0049442188 | V45: 1 | W45: 62.9 | X45: 5.6 | Y45: =ROUND(0.4*((900-P45)/600*100)+0.3*MIN(U45*100,100)+0.2*MIN(V45*20,100)+0.1*W45,1) -> 38.7 | Z45: =IF(Y45<=30,"Low",IF(Y45<=60,"Medium","High")) -> Medium | AA45: =IF(AND(P45>=650,U45<=0.4,V45<=2,Y45<=50),"Eligible",IF(AND(P45>=550,V45<=4,Y45<=75),"Review","Not Eligible")) -> Not Eligible | AB45: Single | AC45: 1 | AD45: Rented | AE45: 20.5 | AF45: 623165 | AG45: =J45+AF45 -> 1357283 | AH45: 0 | AI45: N | AJ45: 360 | AK45: =(IF(S45="Credit Card",0.36,IF(S45="Personal Loan",0.14,IF(S45="Car Loan",0.09,0.085))))+IF(Z45="Low",0,IF(Z45="Medium",0.015,0.03)) -> 0.1 | AL45: =-PMT(AK45/12,AJ45,T45) -> 45512.064 | AM45: =IFERROR(T45/J45,0) -> 7.064446 | AN45: =R45+AL45 -> 45814.534 | AO45: =IFERROR((AN45*12)/J45,0) -> 0.74889106 | AP45: 6843600 | AQ45: =IF(AP45>0,T45/AP45,"N/A") -> 0.75780832 | AR45: 46040 | AS45: Verified
A46: CUST00045 | B46: Rekha Pandey | C46: 9747145068 | D46: rekha.pandey895@yahoo.com | E46: 42 | F46: Male | G46: Chennai | H46: Salaried - Healthcare | I46: Salaried | J46: 1601206 | K46: 0 | L46: N | M46: N | N46: N | O46: N | P46: 386 | Q46: 49570.44 | R46: 1376.96 | S46: Car Loan | T46: 568002 | U46: =IFERROR((R46*12)/J46,0) -> 0.010319422 | V46: 2 | W46: 83.8 | X46: 11.1 | Y46: =ROUND(0.4*((900-P46)/600*100)+0.3*MIN(U46*100,100)+0.2*MIN(V46*20,100)+0.1*W46,1) -> 51 | Z46: =IF(Y46<=30,"Low",IF(Y46<=60,"Medium","High")) -> Medium | AA46: =IF(AND(P46>=650,U46<=0.4,V46<=2,Y46<=50),"Eligible",IF(AND(P46>=550,V46<=4,Y46<=75),"Review","Not Eligible")) -> Not Eligible | AB46: Single | AC46: 2 | AD46: Rented | AE46: 9.1 | AF46: 0 | AG46: =J46+AF46 -> 1601206 | AH46: 0 | AI46: N | AJ46: 36 | AK46: =(IF(S46="Credit Card",0.36,IF(S46="Personal Loan",0.14,IF(S46="Car Loan",0.09,0.085))))+IF(Z46="Low",0,IF(Z46="Medium",0.015,0.03)) -> 0.105 | AL46: =-PMT(AK46/12,AJ46,T46) -> 18461.453 | AM46: =IFERROR(T46/J46,0) -> 0.35473387 | AN46: =R46+AL46 -> 19838.413 | AO46: =IFERROR((AN46*12)/J46,0) -> 0.14867603 | AP46: 635223 | AQ46: =IF(AP46>0,T46/AP46,"N/A") -> 0.89417732 | AR46: 46143 | AS46: Verified
A47: CUST00046 | B47: Krishna Singh | C47: 9182855381 | E47: 53 | F47: Male | G47: Lucknow | H47: Self Employed - Business | I47: Self-Employed | J47: 1880077 | K47: 2 | L47: Y | M47: Y | N47: N | O47: N | P47: 469 | Q47: 813527.74 | R47: 58109.12 | S47: Home Loan | U47: =IFERROR((R47*12)/J47,0) -> 0.37089409 | V47: 2 | W47: 27.6 | X47: 6.8 | Y47: =ROUND(0.4*((900-P47)/600*100)+0.3*MIN(U47*100,100)+0.2*MIN(V47*20,100)+0.1*W47,1) -> 50.6 | Z47: =IF(Y47<=30,"Low",IF(Y47<=60,"Medium","High")) -> Medium | AA47: =IF(AND(P47>=650,U47<=0.4,V47<=2,Y47<=50),"Eligible",IF(AND(P47>=550,V47<=4,Y47<=75),"Review","Not Eligible")) -> Not Eligible | AB47: Married | AC47: 2 | AD47: Owned | AE47: 16.2 | AF47: 756468 | AG47: =J47+AF47 -> 2636545 | AH47: 0 | AI47: N | AJ47: 240 | AK47: =(IF(S47="Credit Card",0.36,IF(S47="Personal Loan",0.14,IF(S47="Car Loan",0.09,0.085))))+IF(Z47="Low",0,IF(Z47="Medium",0.015,0.03)) -> 0.1 | AL47: =-PMT(AK47/12,AJ47,T47) -> 0 | AM47: =IFERROR(T47/J47,0) -> 0 | AN47: =R47+AL47 -> 58109.12 | AO47: =IFERROR((AN47*12)/J47,0) -> 0.37089409 | AP47: 6011944 | AQ47: =IF(AP47>0,T47/AP47,"N/A") -> 0 | AR47: 46187 | AS47: Pending
A48: CUST00047 | B48: Neha Chauhan | D48: neha.chauhan797@hotmail.com | E48: 53 | F48: Female | G48: Kolkata | H48: Self Employed - Professional | I48: Self-Employed | J48: 880485 | K48: 1 | L48: N | M48: Y | N48: N | O48: N | P48: 405 | Q48: 375827 | R48: 8351.71 | S48: Credit Card | U48: =IFERROR((R48*12)/J48,0) -> 0.11382422 | V48: 0 | W48: 20.2 | X48: 6.8 | Y48: =ROUND(0.4*((900-P48)/600*100)+0.3*MIN(U48*100,100)+0.2*MIN(V48*20,100)+0.1*W48,1) -> 38.4 | Z48: =IF(Y48<=30,"Low",IF(Y48<=60,"Medium","High")) -> Medium | AA48: =IF(AND(P48>=650,U48<=0.4,V48<=2,Y48<=50),"Eligible",IF(AND(P48>=550,V48<=4,Y48<=75),"Review","Not Eligible")) -> Not Eligible | AB48: Married | AC48: 3 | AD48: Owned | AE48: 27.3 | AF48: 0 | AG48: =J48+AF48 -> 880485 | AH48: 2 | AI48: Y | AJ48: 36 | AK48: =(IF(S48="Credit Card",0.36,IF(S48="Personal Loan",0.14,IF(S48="Car Loan",0.09,0.085))))+IF(Z48="Low",0,IF(Z48="Medium",0.015,0.03)) -> 0.375 | AL48: =-PMT(AK48/12,AJ48,T48) -> 0 | AM48: =IFERROR(T48/J48,0) -> 0 | AN48: =R48+AL48 -> 8351.71 | AO48: =IFERROR((AN48*12)/J48,0) -> 0.11382422 | AP48: 0 | AQ48: =IF(AP48>0,T48/AP48,"N/A") -> N/A | AR48: 45922 | AS48: Verified
A49: CUST00048 | B49: Kavya Rao | C49: 9514642708 | D49: kavya.rao84@outlook.com | E49: 35 | F49: Male | G49: Lucknow | H49: Salaried - Government | I49: Salaried | J49: 1706309 | K49: 1 | L49: N | M49: Y | N49: N | O49: N | P49: 442 | Q49: 776890 | R49: 18497.39 | S49: Home Loan | U49: =IFERROR((R49*12)/J49,0) -> 0.13008704 | V49: 0 | W49: 12.5 | X49: 4 | Y49: =ROUND(0.4*((900-P49)/600*100)+0.3*MIN(U49*100,100)+0.2*MIN(V49*20,100)+0.1*W49,1) -> 35.7 | Z49: =IF(Y49<=30,"Low",IF(Y49<=60,"Medium","High")) -> Medium | AA49: =IF(AND(P49>=650,U49<=0.4,V49<=2,Y49<=50),"Eligible",IF(AND(P49>=550,V49<=4,Y49<=75),"Review","Not Eligible")) -> Not Eligible | AB49: Single | AC49: 2 | AD49: Rented | AE49: 7.5 | AF49: 366076 | AG49: =J49+AF49 -> 2072385 | AH49: 0 | AI49: N | AJ49: 300 | AK49: =(IF(S49="Credit Card",0.36,IF(S49="Personal Loan",0.14,IF(S49="Car Loan",0.09,0.085))))+IF(Z49="Low",0,IF(Z49="Medium",0.015,0.03)) -> 0.1 | AL49: =-PMT(AK49/12,AJ49,T49) -> 0 | AM49: =IFERROR(T49/J49,0) -> 0 | AN49: =R49+AL49 -> 18497.39 | AO49: =IFERROR((AN49*12)/J49,0) -> 0.13008704 | AP49: 8725363 | AQ49: =IF(AP49>0,T49/AP49,"N/A") -> 0 | AR49: 46213 | AS49: Verified
A50: CUST00049 | B50: Ayaan Saxena | C50: 9636687537 | D50: ayaan.saxena612@rediffmail.com | E50: 22 | F50: Male | G50: Chennai | H50: Salaried - IT/Tech | I50: Salaried | J50: 2100358 | K50: 1 | L50: Y | M50: N | N50: N | O50: N | P50: 387 | Q50: 659703 | R50: 18848.66 | S50: Credit Card | T50: 295806 | U50: =IFERROR((R50*12)/J50,0) -> 0.10768827 | V50: 1 | W50: 79.7 | X50: 7.7 | Y50: =ROUND(0.4*((900-P50)/600*100)+0.3*MIN(U50*100,100)+0.2*MIN(V50*20,100)+0.1*W50,1) -> 49.4 | Z50: =IF(Y50<=30,"Low",IF(Y50<=60,"Medium","High")) -> Medium | AA50: =IF(AND(P50>=650,U50<=0.4,V50<=2,Y50<=50),"Eligible",IF(AND(P50>=550,V50<=4,Y50<=75),"Review","Not Eligible")) -> Not Eligible | AB50: Married | AC50: 3 | AD50: Owned | AE50: 0.6 | AF50: 0 | AG50: =J50+AF50 -> 2100358 | AH50: 1 | AI50: N | AJ50: 12 | AK50: =(IF(S50="Credit Card",0.36,IF(S50="Personal Loan",0.14,IF(S50="Car Loan",0.09,0.085))))+IF(Z50="Low",0,IF(Z50="Medium",0.015,0.03)) -> 0.375 | AL50: =-PMT(AK50/12,AJ50,T50) -> 29939.464 | AM50: =IFERROR(T50/J50,0) -> 0.14083599 | AN50: =R50+AL50 -> 48788.124 | AO50: =IFERROR((AN50*12)/J50,0) -> 0.27874176 | AP50: 0 | AQ50: =IF(AP50>0,T50/AP50,"N/A") -> N/A | AR50: 46071 | AS50: Verified
A51: CUST00050 | B51: Mahesh Mishra | D51: mahesh.mishra791@rediffmail.com | E51: 42 | F51: Male | G51: Delhi | H51: Salaried - Healthcare | I51: Salaried | J51: 1719970 | K51: 1 | L51: N | M51: Y | N51: N | O51: N | P51: 790 | R51: 32597 | S51: Credit Card | U51: =IFERROR((R51*12)/J51,0) -> 0.2274249 | V51: 3 | W51: 48.5 | X51: 4.5 | Y51: =ROUND(0.4*((900-P51)/600*100)+0.3*MIN(U51*100,100)+0.2*MIN(V51*20,100)+0.1*W51,1) -> 31 | Z51: =IF(Y51<=30,"Low",IF(Y51<=60,"Medium","High")) -> Medium | AA51: =IF(AND(P51>=650,U51<=0.4,V51<=2,Y51<=50),"Eligible",IF(AND(P51>=550,V51<=4,Y51<=75),"Review","Not Eligible")) -> Review | AB51: Married | AC51: 0 | AD51: Owned | AE51: 19.6 | AF51: 0 | AG51: =J51+AF51 -> 1719970 | AH51: 3 | AI51: N | AJ51: 24 | AK51: =(IF(S51="Credit Card",0.36,IF(S51="Personal Loan",0.14,IF(S51="Car Loan",0.09,0.085))))+IF(Z51="Low",0,IF(Z51="Medium",0.015,0.03)) -> 0.375 | AL51: =-PMT(AK51/12,AJ51,T51) -> 0 | AM51: =IFERROR(T51/J51,0) -> 0 | AN51: =R51+AL51 -> 32597 | AO51: =IFERROR((AN51*12)/J51,0) -> 0.2274249 | AP51: 0 | AQ51: =IF(AP51>0,T51/AP51,"N/A") -> N/A | AR51: 45913 | AS51: Verified
A52: CUST00051 | B52: Aryan Iyer | C52: 9483298103 | D52: aryan.iyer883@gmail.com | E52: 62 | F52: Female | G52: Jaipur | H52: Salaried - Government | I52: Salaried | J52: 1843584 | K52: 1 | L52: Y | M52: N | N52: N | O52: N | P52: 647 | R52: 25048.48 | S52: Home Loan | T52: 4581529 | U52: =IFERROR((R52*12)/J52,0) -> 0.16304207 | V52: 5 | W52: 54.3 | X52: 12.1 | Y52: =ROUND(0.4*((900-P52)/600*100)+0.3*MIN(U52*100,100)+0.2*MIN(V52*20,100)+0.1*W52,1) -> 47.2 | Z52: =IF(Y52<=30,"Low",IF(Y52<=60,"Medium","High")) -> Medium | AA52: =IF(AND(P52>=650,U52<=0.4,V52<=2,Y52<=50),"Eligible",IF(AND(P52>=550,V52<=4,Y52<=75),"Review","Not Eligible")) -> Not Eligible | AB52: Single | AC52: 0 | AD52: Rented | AE52: 24.7 | AF52: 0 | AG52: =J52+AF52 -> 1843584 | AH52: 0 | AI52: N | AJ52: 240 | AK52: =(IF(S52="Credit Card",0.36,IF(S52="Personal Loan",0.14,IF(S52="Car Loan",0.09,0.085))))+IF(Z52="Low",0,IF(Z52="Medium",0.015,0.03)) -> 0.1 | AL52: =-PMT(AK52/12,AJ52,T52) -> 44212.747 | AM52: =IFERROR(T52/J52,0) -> 2.4851208 | AN52: =R52+AL52 -> 69261.227 | AO52: =IFERROR((AN52*12)/J52,0) -> 0.45082552 | AP52: 5619813 | AQ52: =IF(AP52>0,T52/AP52,"N/A") -> 0.81524581 | AR52: 46203 | AS52: Verified
A53: CUST00052 | B53: Rohan Tiwari | C53: 9576642996 | D53: rohan.tiwari360@hotmail.com | E53: 23 | F53: Female | G53: Indore | H53: Salaried - IT/Tech | I53: Salaried | J53: 540577 | K53: 1 | L53: Y | M53: N | N53: N | O53: N | P53: 463 | R53: 14715.89 | S53: Home Loan | U53: =IFERROR((R53*12)/J53,0) -> 0.32667072 | V53: 0 | W53: 27.4 | X53: 9.7 | Y53: =ROUND(0.4*((900-P53)/600*100)+0.3*MIN(U53*100,100)+0.2*MIN(V53*20,100)+0.1*W53,1) -> 41.7 | Z53: =IF(Y53<=30,"Low",IF(Y53<=60,"Medium","High")) -> Medium | AA53: =IF(AND(P53>=650,U53<=0.4,V53<=2,Y53<=50),"Eligible",IF(AND(P53>=550,V53<=4,Y53<=75),"Review","Not Eligible")) -> Not Eligible | AB53: Married | AC53: 3 | AD53: Owned | AE53: 0.6 | AF53: 0 | AG53: =J53+AF53 -> 540577 | AH53: 0 | AI53: N | AJ53: 120 | AK53: =(IF(S53="Credit Card",0.36,IF(S53="Personal Loan",0.14,IF(S53="Car Loan",0.09,0.085))))+IF(Z53="Low",0,IF(Z53="Medium",0.015,0.03)) -> 0.1 | AL53: =-PMT(AK53/12,AJ53,T53) -> 0 | AM53: =IFERROR(T53/J53,0) -> 0 | AN53: =R53+AL53 -> 14715.89 | AO53: =IFERROR((AN53*12)/J53,0) -> 0.32667072 | AP53: 2317806 | AQ53: =IF(AP53>0,T53/AP53,"N/A") -> 0 | AR53: 46166 | AS53: Verified
A54: CUST00053 | B54: Ananya Mishra | C54: 9399240862 | D54: ananya.mishra256@gmail.com | E54: 22 | F54: Male | G54: Chandigarh | H54: Freelancer | I54: Self-Employed | J54: 1923142 | K54: 1 | L54: N | M54: Y | N54: N | O54: N | P54: 519 | Q54: 1149691 | R54: 38323.03 | S54: Home Loan | U54: =IFERROR((R54*12)/J54,0) -> 0.23912762 | V54: 0 | W54: 86 | X54: 6.9 | Y54: =ROUND(0.4*((900-P54)/600*100)+0.3*MIN(U54*100,100)+0.2*MIN(V54*20,100)+0.1*W54,1) -> 41.2 | Z54: =IF(Y54<=30,"Low",IF(Y54<=60,"Medium","High")) -> Medium | AA54: =IF(AND(P54>=650,U54<=0.4,V54<=2,Y54<=50),"Eligible",IF(AND(P54>=550,V54<=4,Y54<=75),"Review","Not Eligible")) -> Not Eligible | AB54: Single | AC54: 1 | AD54: Owned | AE54: 0.8 | AF54: 0 | AG54: =J54+AF54 -> 1923142 | AH54: 0 | AI54: N | AJ54: 120 | AK54: =(IF(S54="Credit Card",0.36,IF(S54="Personal Loan",0.14,IF(S54="Car Loan",0.09,0.085))))+IF(Z54="Low",0,IF(Z54="Medium",0.015,0.03)) -> 0.1 | AL54: =-PMT(AK54/12,AJ54,T54) -> 0 | AM54: =IFERROR(T54/J54,0) -> 0 | AN54: =R54+AL54 -> 38323.03 | AO54: =IFERROR((AN54*12)/J54,0) -> 0.23912762 | AP54: 4093240 | AQ54: =IF(AP54>0,T54/AP54,"N/A") -> 0 | AR54: 46043 | AS54: Verified
A55: CUST00054 | B55: Rekha Patel | D55: rekha.patel727@yahoo.com | E55: 44 | F55: Male | G55: Hyderabad | H55: Self Employed - Professional | I55: Self-Employed | J55: 882491 | K55: 1 | L55: Y | M55: N | N55: N | O55: N | P55: 778 | Q55: 425535 | R55: 9053.93 | S55: Personal Loan | T55: 691674 | U55: =IFERROR((R55*12)/J55,0) -> 0.12311418 | V55: 4 | W55: 11.2 | X55: 6.1 | Y55: =ROUND(0.4*((900-P55)/600*100)+0.3*MIN(U55*100,100)+0.2*MIN(V55*20,100)+0.1*W55,1) -> 28.9 | Z55: =IF(Y55<=30,"Low",IF(Y55<=60,"Medium","High")) -> Low | AA55: =IF(AND(P55>=650,U55<=0.4,V55<=2,Y55<=50),"Eligible",IF(AND(P55>=550,V55<=4,Y55<=75),"Review","Not Eligible")) -> Review | AB55: Single | AC55: 1 | AD55: Owned | AE55: 9.6 | AF55: 0 | AG55: =J55+AF55 -> 882491 | AH55: 0 | AI55: N | AJ55: 12 | AK55: =(IF(S55="Credit Card",0.36,IF(S55="Personal Loan",0.14,IF(S55="Car Loan",0.09,0.085))))+IF(Z55="Low",0,IF(Z55="Medium",0.015,0.03)) -> 0.14 | AL55: =-PMT(AK55/12,AJ55,T55) -> 62103.415 | AM55: =IFERROR(T55/J55,0) -> 0.78377457 | AN55: =R55+AL55 -> 71157.345 | AO55: =IFERROR((AN55*12)/J55,0) -> 0.96758849 | AP55: 0 | AQ55: =IF(AP55>0,T55/AP55,"N/A") -> N/A | AR55: 46125 | AS55: Verified
A56: CUST00055 | B56: Divya Shah | C56: 9237798236 | D56: divya.shah900@rediffmail.com | E56: 61 | F56: Male | G56: Chennai | H56: Salaried - Education | I56: Salaried | J56: 2409163 | K56: 3 | L56: N | M56: Y | N56: Y | O56: Y | P56: 468 | Q56: 234122.88 | R56: 4107.42 | S56: Personal Loan | T56: 412831 | U56: =IFERROR((R56*12)/J56,0) -> 0.020458989 | V56: 5 | W56: 54.3 | X56: 4.4 | Y56: =ROUND(0.4*((900-P56)/600*100)+0.3*MIN(U56*100,100)+0.2*MIN(V56*20,100)+0.1*W56,1) -> 54.8 | Z56: =IF(Y56<=30,"Low",IF(Y56<=60,"Medium","High")) -> Medium | AA56: =IF(AND(P56>=650,U56<=0.4,V56<=2,Y56<=50),"Eligible",IF(AND(P56>=550,V56<=4,Y56<=75),"Review","Not Eligible")) -> Not Eligible | AB56: Married | AC56: 0 | AD56: Company Provided | AE56: 8.5 | AF56: 0 | AG56: =J56+AF56 -> 2409163 | AH56: 1 | AI56: N | AJ56: 24 | AK56: =(IF(S56="Credit Card",0.36,IF(S56="Personal Loan",0.14,IF(S56="Car Loan",0.09,0.085))))+IF(Z56="Low",0,IF(Z56="Medium",0.015,0.03)) -> 0.155 | AL56: =-PMT(AK56/12,AJ56,T56) -> 20115.002 | AM56: =IFERROR(T56/J56,0) -> 0.17135868 | AN56: =R56+AL56 -> 24222.422 | AO56: =IFERROR((AN56*12)/J56,0) -> 0.12065147 | AP56: 0 | AQ56: =IF(AP56>0,T56/AP56,"N/A") -> N/A | AR56: 46198 | AS56: Pending
A57: CUST00056 | B57: Ishaan Patel | D57: ishaan.patel640@rediffmail.com | E57: 42 | F57: Male | G57: Mumbai | H57: Salaried - Government | I57: Salaried | J57: 490680 | K57: 0 | L57: N | M57: N | N57: N | O57: N | P57: 885 | Q57: 20441 | R57: 393.1 | S57: Credit Card | T57: 281115 | U57: =IFERROR((R57*12)/J57,0) -> 0.0096135975 | V57: 4 | W57: 56.8 | X57: 9.7 | Y57: =ROUND(0.4*((900-P57)/600*100)+0.3*MIN(U57*100,100)+0.2*MIN(V57*20,100)+0.1*W57,1) -> 23 | Z57: =IF(Y57<=30,"Low",IF(Y57<=60,"Medium","High")) -> Low | AA57: =IF(AND(P57>=650,U57<=0.4,V57<=2,Y57<=50),"Eligible",IF(AND(P57>=550,V57<=4,Y57<=75),"Review","Not Eligible")) -> Review | AB57: Married | AC57: 0 | AD57: Rented | AE57: 8.7 | AF57: 0 | AG57: =J57+AF57 -> 490680 | AH57: 1 | AI57: N | AJ57: 36 | AK57: =(IF(S57="Credit Card",0.36,IF(S57="Personal Loan",0.14,IF(S57="Car Loan",0.09,0.085))))+IF(Z57="Low",0,IF(Z57="Medium",0.015,0.03)) -> 0.36 | AL57: =-PMT(AK57/12,AJ57,T57) -> 12876.134 | AM57: =IFERROR(T57/J57,0) -> 0.57290902 | AN57: =R57+AL57 -> 13269.234 | AO57: =IFERROR((AN57*12)/J57,0) -> 0.32451048 | AP57: 0 | AQ57: =IF(AP57>0,T57/AP57,"N/A") -> N/A | AR57: 46142 | AS57: Verified
A58: CUST00057 | B58: Diya Bansal | C58: 9254263081 | D58: diya.bansal321@outlook.com | E58: 43 | F58: Female | G58: Chennai | H58: Salaried - Healthcare | I58: Salaried | J58: 2459983 | K58: 0 | L58: N | M58: N | N58: N | O58: N | P58: 553 | Q58: 34655.66 | R58: 2310.38 | S58: Car Loan | T58: 1105620 | U58: =IFERROR((R58*12)/J58,0) -> 0.011270224 | V58: 4 | W58: 44.7 | X58: 14.4 | Y58: =ROUND(0.4*((900-P58)/600*100)+0.3*MIN(U58*100,100)+0.2*MIN(V58*20,100)+0.1*W58,1) -> 43.9 | Z58: =IF(Y58<=30,"Low",IF(Y58<=60,"Medium","High")) -> Medium | AA58: =IF(AND(P58>=650,U58<=0.4,V58<=2,Y58<=50),"Eligible",IF(AND(P58>=550,V58<=4,Y58<=75),"Review","Not Eligible")) -> Review | AB58: Single | AC58: 3 | AD58: Company Provided | AE58: 15.9 | AF58: 269507 | AG58: =J58+AF58 -> 2729490 | AH58: 3 | AI58: N | AJ58: 48 | AK58: =(IF(S58="Credit Card",0.36,IF(S58="Personal Loan",0.14,IF(S58="Car Loan",0.09,0.085))))+IF(Z58="Low",0,IF(Z58="Medium",0.015,0.03)) -> 0.105 | AL58: =-PMT(AK58/12,AJ58,T58) -> 28307.609 | AM58: =IFERROR(T58/J58,0) -> 0.44944213 | AN58: =R58+AL58 -> 30617.989 | AO58: =IFERROR((AN58*12)/J58,0) -> 0.14935707 | AP58: 1270882 | AQ58: =IF(AP58>0,T58/AP58,"N/A") -> 0.86996275 | AR58: 45941 | AS58: Pending
A59: CUST00058 | B59: Sneha Kapoor | D59: sneha.kapoor221@rediffmail.com | E59: 43 | F59: Male | G59: Delhi | H59: Salaried - IT/Tech | I59: Salaried | J59: 2375736 | K59: 0 | L59: N | M59: N | N59: N | O59: N | P59: 308 | Q59: 201265.79 | R59: 5160.66 | S59: Personal Loan | T59: 975321 | U59: =IFERROR((R59*12)/J59,0) -> 0.026066836 | V59: 0 | W59: 39.7 | X59: 6.2 | Y59: =ROUND(0.4*((900-P59)/600*100)+0.3*MIN(U59*100,100)+0.2*MIN(V59*20,100)+0.1*W59,1) -> 44.2 | Z59: =IF(Y59<=30,"Low",IF(Y59<=60,"Medium","High")) -> Medium | AA59: =IF(AND(P59>=650,U59<=0.4,V59<=2,Y59<=50),"Eligible",IF(AND(P59>=550,V59<=4,Y59<=75),"Review","Not Eligible")) -> Not Eligible | AB59: Married | AC59: 0 | AD59: Rented | AE59: 8.2 | AF59: 439762 | AG59: =J59+AF59 -> 2815498 | AH59: 0 | AI59: N | AJ59: 60 | AK59: =(IF(S59="Credit Card",0.36,IF(S59="Personal Loan",0.14,IF(S59="Car Loan",0.09,0.085))))+IF(Z59="Low",0,IF(Z59="Medium",0.015,0.03)) -> 0.155 | AL59: =-PMT(AK59/12,AJ59,T59) -> 23459.582 | AM59: =IFERROR(T59/J59,0) -> 0.41053425 | AN59: =R59+AL59 -> 28620.242 | AO59: =IFERROR((AN59*12)/J59,0) -> 0.14456274 | AP59: 0 | AQ59: =IF(AP59>0,T59/AP59,"N/A") -> N/A | AR59: 46243 | AS59: Verified
A60: CUST00059 | B60: Krishna Kumar | C60: 9522950895 | D60: krishna.kumar383@outlook.com | E60: 56 | F60: Female | G60: Chennai | H60: Self Employed - Professional | I60: Self-Employed | J60: 2435414 | K60: 3 | L60: Y | M60: Y | N60: Y | O60: N | P60: 785 | Q60: 758874 | R60: 36136.86 | S60: Personal Loan | T60: 393897 | U60: =IFERROR((R60*12)/J60,0) -> 0.17805692 | V60: 5 | W60: 35.3 | X60: 6 | Y60: =ROUND(0.4*((900-P60)/600*100)+0.3*MIN(U60*100,100)+0.2*MIN(V60*20,100)+0.1*W60,1) -> 36.5 | Z60: =IF(Y60<=30,"Low",IF(Y60<=60,"Medium","High")) -> Medium | AA60: =IF(AND(P60>=650,U60<=0.4,V60<=2,Y60<=50),"Eligible",IF(AND(P60>=550,V60<=4,Y60<=75),"Review","Not Eligible")) -> Not Eligible | AB60: Single | AC60: 3 | AD60: Rented | AE60: 15.4 | AF60: 0 | AG60: =J60+AF60 -> 2435414 | AH60: 0 | AI60: N | AJ60: 48 | AK60: =(IF(S60="Credit Card",0.36,IF(S60="Personal Loan",0.14,IF(S60="Car Loan",0.09,0.085))))+IF(Z60="Low",0,IF(Z60="Medium",0.015,0.03)) -> 0.155 | AL60: =-PMT(AK60/12,AJ60,T60) -> 11062.542 | AM60: =IFERROR(T60/J60,0) -> 0.16173718 | AN60: =R60+AL60 -> 47199.402 | AO60: =IFERROR((AN60*12)/J60,0) -> 0.23256531 | AP60: 0 | AQ60: =IF(AP60>0,T60/AP60,"N/A") -> N/A | AR60: 45903 | AS60: Verified
A61: CUST00060 | B61: Ramesh Kumar | C61: 9547256709 | E61: 65 | F61: Male | G61: Chandigarh | H61: Salaried - IT/Tech | I61: Salaried | J61: 1254385 | K61: 1 | L61: N | M61: N | N61: Y | O61: N | P61: 689 | R61: 2022.19 | S61: Personal Loan | T61: 83104 | U61: =IFERROR((R61*12)/J61,0) -> 0.019345161 | V61: 1 | W61: 71.5 | X61: 3 | Y61: =ROUND(0.4*((900-P61)/600*100)+0.3*MIN(U61*100,100)+0.2*MIN(V61*20,100)+0.1*W61,1) -> 25.8 | Z61: =IF(Y61<=30,"Low",IF(Y61<=60,"Medium","High")) -> Low | AA61: =IF(AND(P61>=650,U61<=0.4,V61<=2,Y61<=50),"Eligible",IF(AND(P61>=550,V61<=4,Y61<=75),"Review","Not Eligible")) -> Eligible | AB61: Married | AC61: 1 | AD61: Owned | AE61: 6.4 | AF61: 0 | AG61: =J61+AF61 -> 1254385 | AH61: 1 | AI61: N | AJ61: 12 | AK61: =(IF(S61="Credit Card",0.36,IF(S61="Personal Loan",0.14,IF(S61="Car Loan",0.09,0.085))))+IF(Z61="Low",0,IF(Z61="Medium",0.015,0.03)) -> 0.14 | AL61: =-PMT(AK61/12,AJ61,T61) -> 7461.6686 | AM61: =IFERROR(T61/J61,0) -> 0.066250792 | AN61: =R61+AL61 -> 9483.8586 | AO61: =IFERROR((AN61*12)/J61,0) -> 0.090726773 | AP61: 0 | AQ61: =IF(AP61>0,T61/AP61,"N/A") -> N/A | AR61: 46256 | AS61: Verified
A62: CUST00061 | B62: Dhruv Bhatt | C62: 9449019278 | D62: dhruv.bhatt679@hotmail.com | E62: 54 | F62: Female | G62: Lucknow | H62: Self Employed - Business | I62: Self-Employed | J62: 2227968 | K62: 0 | L62: N | M62: N | N62: N | O62: N | P62: 570 | Q62: 135923 | R62: 5663.46 | S62: Personal Loan | U62: =IFERROR((R62*12)/J62,0) -> 0.030503813 | V62: 1 | W62: 26.4 | X62: 14.6 | Y62: =ROUND(0.4*((900-P62)/600*100)+0.3*MIN(U62*100,100)+0.2*MIN(V62*20,100)+0.1*W62,1) -> 29.6 | Z62: =IF(Y62<=30,"Low",IF(Y62<=60,"Medium","High")) -> Low | AA62: =IF(AND(P62>=650,U62<=0.4,V62<=2,Y62<=50),"Eligible",IF(AND(P62>=550,V62<=4,Y62<=75),"Review","Not Eligible")) -> Review | AB62: Married | AC62: 1 | AD62: Owned | AE62: 21.2 | AF62: 411602 | AG62: =J62+AF62 -> 2639570 | AH62: 3 | AI62: N | AJ62: 36 | AK62: =(IF(S62="Credit Card",0.36,IF(S62="Personal Loan",0.14,IF(S62="Car Loan",0.09,0.085))))+IF(Z62="Low",0,IF(Z62="Medium",0.015,0.03)) -> 0.14 | AL62: =-PMT(AK62/12,AJ62,T62) -> 0 | AM62: =IFERROR(T62/J62,0) -> 0 | AN62: =R62+AL62 -> 5663.46 | AO62: =IFERROR((AN62*12)/J62,0) -> 0.030503813 | AP62: 0 | AQ62: =IF(AP62>0,T62/AP62,"N/A") -> N/A | AR62: 46042 | AS62: Verified
A63: CUST00062 | B63: Ramesh Bhatt | C63: 9507693523 | D63: ramesh.bhatt918@hotmail.com | E63: 43 | F63: Male | G63: Surat | H63: Salaried - Private | I63: Salaried | J63: 1506409 | K63: 1 | L63: N | M63: Y | N63: N | O63: N | P63: 790 | Q63: 193411 | R63: 4204.59 | S63: Car Loan | T63: 1478637 | U63: =IFERROR((R63*12)/J63,0) -> 0.033493613 | V63: 2 | W63: 18 | X63: 9.3 | Y63: =ROUND(0.4*((900-P63)/600*100)+0.3*MIN(U63*100,100)+0.2*MIN(V63*20,100)+0.1*W63,1) -> 18.1 | Z63: =IF(Y63<=30,"Low",IF(Y63<=60,"Medium","High")) -> Low | AA63: =IF(AND(P63>=650,U63<=0.4,V63<=2,Y63<=50),"Eligible",IF(AND(P63>=550,V63<=4,Y63<=75),"Review","Not Eligible")) -> Eligible | AB63: Married | AC63: 0 | AD63: Rented | AE63: 11.8 | AF63: 0 | AG63: =J63+AF63 -> 1506409 | AH63: 0 | AI63: N | AJ63: 84 | AK63: =(IF(S63="Credit Card",0.36,IF(S63="Personal Loan",0.14,IF(S63="Car Loan",0.09,0.085))))+IF(Z63="Low",0,IF(Z63="Medium",0.015,0.03)) -> 0.09 | AL63: =-PMT(AK63/12,AJ63,T63) -> 23789.906 | AM63: =IFERROR(T63/J63,0) -> 0.9815641 | AN63: =R63+AL63 -> 27994.496 | AO63: =IFERROR((AN63*12)/J63,0) -> 0.22300315 | AP63: 1692272 | AQ63: =IF(AP63>0,T63/AP63,"N/A") -> 0.87375847 | AR63: 46243 | AS63: Verified
A64: CUST00063 | B64: Aarav Bhatt | C64: 9269587940 | D64: aarav.bhatt417@hotmail.com | E64: 51 | F64: Male | G64: Surat | H64: Salaried - Healthcare | I64: Salaried | J64: 1497118 | K64: 1 | L64: N | M64: N | N64: Y | O64: N | P64: 847 | Q64: 663541 | R64: 47395.75 | S64: Personal Loan | T64: 488184 | U64: =IFERROR((R64*12)/J64,0) -> 0.37989591 | V64: 4 | W64: 21.7 | X64: 13.8 | Y64: =ROUND(0.4*((900-P64)/600*100)+0.3*MIN(U64*100,100)+0.2*MIN(V64*20,100)+0.1*W64,1) -> 33.1 | Z64: =IF(Y64<=30,"Low",IF(Y64<=60,"Medium","High")) -> Medium | AA64: =IF(AND(P64>=650,U64<=0.4,V64<=2,Y64<=50),"Eligible",IF(AND(P64>=550,V64<=4,Y64<=75),"Review","Not Eligible")) -> Review | AB64: Divorced | AC64: 1 | AD64: Rented | AE64: 28.1 | AF64: 0 | AG64: =J64+AF64 -> 1497118 | AH64: 2 | AI64: N | AJ64: 12 | AK64: =(IF(S64="Credit Card",0.36,IF(S64="Personal Loan",0.14,IF(S64="Car Loan",0.09,0.085))))+IF(Z64="Low",0,IF(Z64="Medium",0.015,0.03)) -> 0.155 | AL64: =-PMT(AK64/12,AJ64,T64) -> 44177.926 | AM64: =IFERROR(T64/J64,0) -> 0.32608251 | AN64: =R64+AL64 -> 91573.676 | AO64: =IFERROR((AN64*12)/J64,0) -> 0.73399967 | AP64: 0 | AQ64: =IF(AP64>0,T64/AP64,"N/A") -> N/A | AR64: 46047 | AS64: Verified
A65: CUST00064 | B65: Reyansh Khanna | D65: reyansh.khanna292@hotmail.com | E65: 62 | F65: Female | G65: Chennai | H65: Freelancer | I65: Self-Employed | J65: 2263021 | K65: 1 | L65: Y | M65: N | N65: N | O65: N | P65: 563 | Q65: 975722 | R65: 81310.14 | S65: Car Loan | T65: 918710 | U65: =IFERROR((R65*12)/J65,0) -> 0.43115892 | V65: 1 | W65: 76.9 | X65: 2.8 | Y65: =ROUND(0.4*((900-P65)/600*100)+0.3*MIN(U65*100,100)+0.2*MIN(V65*20,100)+0.1*W65,1) -> 47.1 | Z65: =IF(Y65<=30,"Low",IF(Y65<=60,"Medium","High")) -> Medium | AA65: =IF(AND(P65>=650,U65<=0.4,V65<=2,Y65<=50),"Eligible",IF(AND(P65>=550,V65<=4,Y65<=75),"Review","Not Eligible")) -> Review | AB65: Single | AC65: 3 | AD65: Rented | AE65: 15.6 | AF65: 651942 | AG65: =J65+AF65 -> 2914963 | AH65: 0 | AI65: N | AJ65: 48 | AK65: =(IF(S65="Credit Card",0.36,IF(S65="Personal Loan",0.14,IF(S65="Car Loan",0.09,0.085))))+IF(Z65="Low",0,IF(Z65="Medium",0.015,0.03)) -> 0.105 | AL65: =-PMT(AK65/12,AJ65,T65) -> 23522.081 | AM65: =IFERROR(T65/J65,0) -> 0.40596618 | AN65: =R65+AL65 -> 104832.22 | AO65: =IFERROR((AN65*12)/J65,0) -> 0.55588819 | AP65: 1136596 | AQ65: =IF(AP65>0,T65/AP65,"N/A") -> 0.80829952 | AR65: 45898 | AS65: Verified
A66: CUST00065 | B66: Rahul Kapoor | C66: 9909340042 | D66: rahul.kapoor274@outlook.com | E66: 40 | F66: Male | G66: Jaipur | H66: Salaried - Healthcare | I66: Salaried | J66: 1291124 | K66: 2 | L66: Y | M66: Y | N66: N | O66: N | P66: 814 | Q66: 715107 | R66: 12545.73 | S66: Car Loan | T66: 546238 | U66: =IFERROR((R66*12)/J66,0) -> 0.11660287 | V66: 1 | W66: 94.4 | X66: 5.6 | Y66: =ROUND(0.4*((900-P66)/600*100)+0.3*MIN(U66*100,100)+0.2*MIN(V66*20,100)+0.1*W66,1) -> 22.7 | Z66: =IF(Y66<=30,"Low",IF(Y66<=60,"Medium","High")) -> Low | AA66: =IF(AND(P66>=650,U66<=0.4,V66<=2,Y66<=50),"Eligible",IF(AND(P66>=550,V66<=4,Y66<=75),"Review","Not Eligible")) -> Eligible | AB66: Married | AC66: 4 | AD66: Rented | AE66: 8.8 | AF66: 0 | AG66: =J66+AF66 -> 1291124 | AH66: 0 | AI66: N | AJ66: 60 | AK66: =(IF(S66="Credit Card",0.36,IF(S66="Personal Loan",0.14,IF(S66="Car Loan",0.09,0.085))))+IF(Z66="Low",0,IF(Z66="Medium",0.015,0.03)) -> 0.09 | AL66: =-PMT(AK66/12,AJ66,T66) -> 11339.002 | AM66: =IFERROR(T66/J66,0) -> 0.42307168 | AN66: =R66+AL66 -> 23884.732 | AO66: =IFERROR((AN66*12)/J66,0) -> 0.22199013 | AP66: 656289 | AQ66: =IF(AP66>0,T66/AP66,"N/A") -> 0.8323132 | AR66: 46235 | AS66: Verified
A67: CUST00066 | B67: Anil Rao | D67: anil.rao773@rediffmail.com | E67: 26 | F67: Female | G67: Kochi | H67: Salaried - Healthcare | I67: Salaried | J67: 627586 | K67: 1 | L67: N | M67: Y | N67: N | O67: N | P67: 507 | R67: 10269.13 | S67: Personal Loan | T67: 394056 | U67: =IFERROR((R67*12)/J67,0) -> 0.19635486 | V67: 4 | W67: 47 | X67: 10.3 | Y67: =ROUND(0.4*((900-P67)/600*100)+0.3*MIN(U67*100,100)+0.2*MIN(V67*20,100)+0.1*W67,1) -> 52.8 | Z67: =IF(Y67<=30,"Low",IF(Y67<=60,"Medium","High")) -> Medium | AA67: =IF(AND(P67>=650,U67<=0.4,V67<=2,Y67<=50),"Eligible",IF(AND(P67>=550,V67<=4,Y67<=75),"Review","Not Eligible")) -> Not Eligible | AB67: Single | AC67: 1 | AD67: Rented | AE67: 2.4 | AF67: 248958 | AG67: =J67+AF67 -> 876544 | AH67: 0 | AI67: N | AJ67: 60 | AK67: =(IF(S67="Credit Card",0.36,IF(S67="Personal Loan",0.14,IF(S67="Car Loan",0.09,0.085))))+IF(Z67="Low",0,IF(Z67="Medium",0.015,0.03)) -> 0.155 | AL67: =-PMT(AK67/12,AJ67,T67) -> 9478.3043 | AM67: =IFERROR(T67/J67,0) -> 0.62789164 | AN67: =R67+AL67 -> 19747.434 | AO67: =IFERROR((AN67*12)/J67,0) -> 0.37758843 | AP67: 0 | AQ67: =IF(AP67>0,T67/AP67,"N/A") -> N/A | AR67: 46131 | AS67: Verified
A68: CUST00067 | B68: Manish Yadav | C68: 9123375849 | D68: manish.yadav406@outlook.com | E68: 21 | F68: Male | G68: Bengaluru | H68: Salaried - Private | I68: Salaried | J68: 2077115 | K68: 2 | L68: Y | M68: Y | N68: N | O68: N | P68: 370 | R68: 29261.72 | S68: Credit Card | U68: =IFERROR((R68*12)/J68,0) -> 0.16905209 | V68: 0 | W68: 78.1 | X68: 11.5 | Y68: =ROUND(0.4*((900-P68)/600*100)+0.3*MIN(U68*100,100)+0.2*MIN(V68*20,100)+0.1*W68,1) -> 48.2 | Z68: =IF(Y68<=30,"Low",IF(Y68<=60,"Medium","High")) -> Medium | AA68: =IF(AND(P68>=650,U68<=0.4,V68<=2,Y68<=50),"Eligible",IF(AND(P68>=550,V68<=4,Y68<=75),"Review","Not Eligible")) -> Not Eligible | AB68: Divorced | AC68: 2 | AD68: Owned | AE68: 0.3 | AF68: 0 | AG68: =J68+AF68 -> 2077115 | AH68: 0 | AI68: N | AJ68: 36 | AK68: =(IF(S68="Credit Card",0.36,IF(S68="Personal Loan",0.14,IF(S68="Car Loan",0.09,0.085))))+IF(Z68="Low",0,IF(Z68="Medium",0.015,0.03)) -> 0.375 | AL68: =-PMT(AK68/12,AJ68,T68) -> 0 | AM68: =IFERROR(T68/J68,0) -> 0 | AN68: =R68+AL68 -> 29261.72 | AO68: =IFERROR((AN68*12)/J68,0) -> 0.16905209 | AP68: 0 | AQ68: =IF(AP68>0,T68/AP68,"N/A") -> N/A | AR68: 46087 | AS68: Verified
A69: CUST00068 | B69: Mahesh Bhatia | C69: 9679069250 | D69: mahesh.bhatia137@outlook.com | E69: 28 | F69: Male | G69: Coimbatore | H69: Salaried - Education | I69: Salaried | J69: 834132 | K69: 3 | L69: N | M69: Y | N69: Y | O69: Y | P69: 605 | Q69: 231724 | R69: 3995.24 | S69: Home Loan | T69: 5962182 | U69: =IFERROR((R69*12)/J69,0) -> 0.057476371 | V69: 0 | W69: 26.8 | X69: 7 | Y69: =ROUND(0.4*((900-P69)/600*100)+0.3*MIN(U69*100,100)+0.2*MIN(V69*20,100)+0.1*W69,1) -> 24.1 | Z69: =IF(Y69<=30,"Low",IF(Y69<=60,"Medium","High")) -> Low | AA69: =IF(AND(P69>=650,U69<=0.4,V69<=2,Y69<=50),"Eligible",IF(AND(P69>=550,V69<=4,Y69<=75),"Review","Not Eligible")) -> Review | AB69: Married | AC69: 0 | AD69: Rented | AE69: 5.4 | AF69: 645148 | AG69: =J69+AF69 -> 1479280 | AH69: 1 | AI69: Y | AJ69: 120 | AK69: =(IF(S69="Credit Card",0.36,IF(S69="Personal Loan",0.14,IF(S69="Car Loan",0.09,0.085))))+IF(Z69="Low",0,IF(Z69="Medium",0.015,0.03)) -> 0.085 | AL69: =-PMT(AK69/12,AJ69,T69) -> 73922.524 | AM69: =IFERROR(T69/J69,0) -> 7.147768 | AN69: =R69+AL69 -> 77917.764 | AO69: =IFERROR((AN69*12)/J69,0) -> 1.1209415 | AP69: 7215233 | AQ69: =IF(AP69>0,T69/AP69,"N/A") -> 0.82633257 | AR69: 45929 | AS69: Verified
A70: CUST00069 | B70: Aditya Kapoor | D70: aditya.kapoor689@gmail.com | E70: 36 | F70: Male | G70: Nagpur | H70: Business Owner | I70: Self-Employed | J70: 1282890 | K70: 2 | L70: Y | M70: N | N70: N | O70: Y | P70: 596 | R70: 3107.62 | S70: Car Loan | T70: 972483 | U70: =IFERROR((R70*12)/J70,0) -> 0.029068307 | V70: 0 | W70: 88.2 | X70: 14.8 | Y70: =ROUND(0.4*((900-P70)/600*100)+0.3*MIN(U70*100,100)+0.2*MIN(V70*20,100)+0.1*W70,1) -> 30 | Z70: =IF(Y70<=30,"Low",IF(Y70<=60,"Medium","High")) -> Low | AA70: =IF(AND(P70>=650,U70<=0.4,V70<=2,Y70<=50),"Eligible",IF(AND(P70>=550,V70<=4,Y70<=75),"Review","Not Eligible")) -> Review | AB70: Married | AC70: 1 | AD70: Owned | AE70: 8.5 | AF70: 0 | AG70: =J70+AF70 -> 1282890 | AH70: 1 | AI70: N | AJ70: 84 | AK70: =(IF(S70="Credit Card",0.36,IF(S70="Personal Loan",0.14,IF(S70="Car Loan",0.09,0.085))))+IF(Z70="Low",0,IF(Z70="Medium",0.015,0.03)) -> 0.09 | AL70: =-PMT(AK70/12,AJ70,T70) -> 15646.355 | AM70: =IFERROR(T70/J70,0) -> 0.75804083 | AN70: =R70+AL70 -> 18753.975 | AO70: =IFERROR((AN70*12)/J70,0) -> 0.17542245 | AP70: 1104196 | AQ70: =IF(AP70>0,T70/AP70,"N/A") -> 0.88071592 | AR70: 46148 | AS70: Verified
A71: CUST00070 | B71: Isha Mishra | C71: 9820848547 | D71: isha.mishra391@rediffmail.com | E71: 41 | F71: Female | G71: Indore | H71: Self Employed - Business | I71: Self-Employed | J71: 1557823 | K71: 1 | L71: Y | M71: N | N71: N | O71: N | P71: 607 | Q71: 801538.48 | R71: 38168.5 | S71: Home Loan | T71: 1983384 | U71: =IFERROR((R71*12)/J71,0) -> 0.29401415 | V71: 1 | W71: 96.9 | X71: 8.4 | Y71: =ROUND(0.4*((900-P71)/600*100)+0.3*MIN(U71*100,100)+0.2*MIN(V71*20,100)+0.1*W71,1) -> 42 | Z71: =IF(Y71<=30,"Low",IF(Y71<=60,"Medium","High")) -> Medium | AA71: =IF(AND(P71>=650,U71<=0.4,V71<=2,Y71<=50),"Eligible",IF(AND(P71>=550,V71<=4,Y71<=75),"Review","Not Eligible")) -> Review | AB71: Married | AC71: 0 | AD71: Owned | AE71: 13 | AF71: 0 | AG71: =J71+AF71 -> 1557823 | AH71: 2 | AI71: N | AJ71: 180 | AK71: =(IF(S71="Credit Card",0.36,IF(S71="Personal Loan",0.14,IF(S71="Car Loan",0.09,0.085))))+IF(Z71="Low",0,IF(Z71="Medium",0.015,0.03)) -> 0.1 | AL71: =-PMT(AK71/12,AJ71,T71) -> 21313.546 | AM71: =IFERROR(T71/J71,0) -> 1.2731767 | AN71: =R71+AL71 -> 59482.046 | AO71: =IFERROR((AN71*12)/J71,0) -> 0.45819361 | AP71: 2306446 | AQ71: =IF(AP71>0,T71/AP71,"N/A") -> 0.85993082 | AR71: 46088 | AS71: Verified
A72: CUST00071 | B72: Simran Verma | C72: 9178151583 | D72: simran.verma193@rediffmail.com | E72: 63 | F72: Male | G72: Chandigarh | H72: Self Employed - Professional | I72: Self-Employed | J72: 1696553 | K72: 2 | L72: Y | M72: N | N72: Y | O72: N | P72: 420 | Q72: 760272 | R72: 12671.2 | S72: Home Loan | T72: 3535019 | U72: =IFERROR((R72*12)/J72,0) -> 0.089625494 | V72: 2 | W72: 71.9 | X72: 6.1 | Y72: =ROUND(0.4*((900-P72)/600*100)+0.3*MIN(U72*100,100)+0.2*MIN(V72*20,100)+0.1*W72,1) -> 49.9 | Z72: =IF(Y72<=30,"Low",IF(Y72<=60,"Medium","High")) -> Medium | AA72: =IF(AND(P72>=650,U72<=0.4,V72<=2,Y72<=50),"Eligible",IF(AND(P72>=550,V72<=4,Y72<=75),"Review","Not Eligible")) -> Not Eligible | AB72: Married | AC72: 1 | AD72: Owned | AE72: 14.1 | AF72: 0 | AG72: =J72+AF72 -> 1696553 | AH72: 0 | AI72: N | AJ72: 300 | AK72: =(IF(S72="Credit Card",0.36,IF(S72="Personal Loan",0.14,IF(S72="Car Loan",0.09,0.085))))+IF(Z72="Low",0,IF(Z72="Medium",0.015,0.03)) -> 0.1 | AL72: =-PMT(AK72/12,AJ72,T72) -> 32122.744 | AM72: =IFERROR(T72/J72,0) -> 2.0836478 | AN72: =R72+AL72 -> 44793.944 | AO72: =IFERROR((AN72*12)/J72,0) -> 0.31683498 | AP72: 4477105 | AQ72: =IF(AP72>0,T72/AP72,"N/A") -> 0.78957697 | AR72: 46135 | AS72: Verified
A73: CUST00072 | B73: Ananya Khanna | C73: 9318106480 | D73: ananya.khanna380@outlook.com | E73: 47 | F73: Male | G73: Ahmedabad | H73: Self Employed - Business | I73: Self-Employed | J73: 368031 | K73: 1 | L73: Y | M73: N | N73: N | O73: N | P73: 456 | Q73: 43323 | R73: 1666.26 | S73: Home Loan | T73: 6279740 | U73: =IFERROR((R73*12)/J73,0) -> 0.054329989 | V73: 3 | W73: 52.4 | X73: 9.9 | Y73: =ROUND(0.4*((900-P73)/600*100)+0.3*MIN(U73*100,100)+0.2*MIN(V73*20,100)+0.1*W73,1) -> 48.5 | Z73: =IF(Y73<=30,"Low",IF(Y73<=60,"Medium","High")) -> Medium | AA73: =IF(AND(P73>=650,U73<=0.4,V73<=2,Y73<=50),"Eligible",IF(AND(P73>=550,V73<=4,Y73<=75),"Review","Not Eligible")) -> Not Eligible | AB73: Single | AC73: 1 | AD73: Rented | AE73: 25.1 | AF73: 0 | AG73: =J73+AF73 -> 368031 | AH73: 0 | AI73: N | AJ73: 240 | AK73: =(IF(S73="Credit Card",0.36,IF(S73="Personal Loan",0.14,IF(S73="Car Loan",0.09,0.085))))+IF(Z73="Low",0,IF(Z73="Medium",0.015,0.03)) -> 0.1 | AL73: =-PMT(AK73/12,AJ73,T73) -> 60600.85 | AM73: =IFERROR(T73/J73,0) -> 17.063073 | AN73: =R73+AL73 -> 62267.11 | AO73: =IFERROR((AN73*12)/J73,0) -> 2.0302782 | AP73: 7487437 | AQ73: =IF(AP73>0,T73/AP73,"N/A") -> 0.83870355 | AR73: 46174 | AS73: Verified
A74: CUST00073 | B74: Seema Sethi | C74: 9682115008 | D74: seema.sethi658@gmail.com | E74: 54 | F74: Male | G74: Bengaluru | H74: Salaried - Private | I74: Salaried | J74: 326775 | K74: 2 | L74: Y | M74: N | N74: Y | O74: N | P74: 309 | Q74: 42883 | R74: 1045.93 | S74: Car Loan | T74: 426773 | U74: =IFERROR((R74*12)/J74,0) -> 0.038409181 | V74: 1 | W74: 68.3 | X74: 9.3 | Y74: =ROUND(0.4*((900-P74)/600*100)+0.3*MIN(U74*100,100)+0.2*MIN(V74*20,100)+0.1*W74,1) -> 51.4 | Z74: =IF(Y74<=30,"Low",IF(Y74<=60,"Medium","High")) -> Medium | AA74: =IF(AND(P74>=650,U74<=0.4,V74<=2,Y74<=50),"Eligible",IF(AND(P74>=550,V74<=4,Y74<=75),"Review","Not Eligible")) -> Not Eligible | AB74: Married | AC74: 1 | AD74: Owned | AE74: 16.7 | AF74: 547063 | AG74: =J74+AF74 -> 873838 | AH74: 0 | AI74: Y | AJ74: 24 | AK74: =(IF(S74="Credit Card",0.36,IF(S74="Personal Loan",0.14,IF(S74="Car Loan",0.09,0.085))))+IF(Z74="Low",0,IF(Z74="Medium",0.015,0.03)) -> 0.105 | AL74: =-PMT(AK74/12,AJ74,T74) -> 19792.042 | AM74: =IFERROR(T74/J74,0) -> 1.3060148 | AN74: =R74+AL74 -> 20837.972 | AO74: =IFERROR((AN74*12)/J74,0) -> 0.76522276 | AP74: 490978 | AQ74: =IF(AP74>0,T74/AP74,"N/A") -> 0.86923039 | AR74: 46252 | AS74: Verified
A75: CUST00074 | B75: Preeti Khanna | D75: preeti.khanna110@gmail.com | E75: 54 | F75: Male | G75: Ahmedabad | H75: Self Employed - Professional | I75: Self-Employed | J75: 1358718 | K75: 1 | L75: N | M75: Y | N75: N | O75: N | P75: 715 | Q75: 374189 | R75: 13858.86 | S75: Personal Loan | U75: =IFERROR((R75*12)/J75,0) -> 0.12239944 | V75: 2 | W75: 85.5 | X75: 9.9 | Y75: =ROUND(0.4*((900-P75)/600*100)+0.3*MIN(U75*100,100)+0.2*MIN(V75*20,100)+0.1*W75,1) -> 32.6 | Z75: =IF(Y75<=30,"Low",IF(Y75<=60,"Medium","High")) -> Medium | AA75: =IF(AND(P75>=650,U75<=0.4,V75<=2,Y75<=50),"Eligible",IF(AND(P75>=550,V75<=4,Y75<=75),"Review","Not Eligible")) -> Eligible | AB75: Single | AC75: 2 | AD75: Owned | AE75: 11.6 | AF75: 0 | AG75: =J75+AF75 -> 1358718 | AH75: 0 | AI75: N | AJ75: 24 | AK75: =(IF(S75="Credit Card",0.36,IF(S75="Personal Loan",0.14,IF(S75="Car Loan",0.09,0.085))))+IF(Z75="Low",0,IF(Z75="Medium",0.015,0.03)) -> 0.155 | AL75: =-PMT(AK75/12,AJ75,T75) -> 0 | AM75: =IFERROR(T75/J75,0) -> 0 | AN75: =R75+AL75 -> 13858.86 | AO75: =IFERROR((AN75*12)/J75,0) -> 0.12239944 | AP75: 0 | AQ75: =IF(AP75>0,T75/AP75,"N/A") -> N/A | AR75: 45937 | AS75: Verified
A76: CUST00075 | B76: Saanvi Mishra | C76: 9942217648 | D76: saanvi.mishra340@rediffmail.com | E76: 27 | F76: Male | G76: Ahmedabad | H76: Self Employed - Professional | I76: Self-Employed | J76: 2294392 | K76: 1 | L76: Y | M76: N | N76: N | O76: N | P76: 856 | Q76: 775748 | R76: 55410.54 | S76: Personal Loan | T76: 941737 | U76: =IFERROR((R76*12)/J76,0) -> 0.28980509 | V76: 0 | W76: 96.3 | X76: 8.9 | Y76: =ROUND(0.4*((900-P76)/600*100)+0.3*MIN(U76*100,100)+0.2*MIN(V76*20,100)+0.1*W76,1) -> 21.3 | Z76: =IF(Y76<=30,"Low",IF(Y76<=60,"Medium","High")) -> Low | AA76: =IF(AND(P76>=650,U76<=0.4,V76<=2,Y76<=50),"Eligible",IF(AND(P76>=550,V76<=4,Y76<=75),"Review","Not Eligible")) -> Eligible | AB76: Single | AC76: 2 | AD76: Owned | AE76: 0.7 | AF76: 330354 | AG76: =J76+AF76 -> 2624746 | AH76: 2 | AI76: N | AJ76: 60 | AK76: =(IF(S76="Credit Card",0.36,IF(S76="Personal Loan",0.14,IF(S76="Car Loan",0.09,0.085))))+IF(Z76="Low",0,IF(Z76="Medium",0.015,0.03)) -> 0.14 | AL76: =-PMT(AK76/12,AJ76,T76) -> 21912.573 | AM76: =IFERROR(T76/J76,0) -> 0.41045166 | AN76: =R76+AL76 -> 77323.113 | AO76: =IFERROR((AN76*12)/J76,0) -> 0.404411 | AP76: 0 | AQ76: =IF(AP76>0,T76/AP76,"N/A") -> N/A | AR76: 46064 | AS76: Verified
A77: CUST00076 | B77: Vinod Singh | C77: 9948790854 | D77: vinod.singh706@gmail.com | E77: 53 | F77: Female | G77: Delhi | H77: Salaried - Government | I77: Salaried | J77: 2133281 | K77: 2 | L77: Y | M77: Y | N77: N | O77: N | P77: 706 | Q77: 1240188 | R77: 38755.87 | S77: Credit Card | T77: 352463 | U77: =IFERROR((R77*12)/J77,0) -> 0.21800712 | V77: 0 | W77: 99.3 | X77: 7.5 | Y77: =ROUND(0.4*((900-P77)/600*100)+0.3*MIN(U77*100,100)+0.2*MIN(V77*20,100)+0.1*W77,1) -> 29.4 | Z77: =IF(Y77<=30,"Low",IF(Y77<=60,"Medium","High")) -> Low | AA77: =IF(AND(P77>=650,U77<=0.4,V77<=2,Y77<=50),"Eligible",IF(AND(P77>=550,V77<=4,Y77<=75),"Review","Not Eligible")) -> Eligible | AB77: Married | AC77: 3 | AD77: Owned | AE77: 20.5 | AF77: 0 | AG77: =J77+AF77 -> 2133281 | AH77: 0 | AI77: N | AJ77: 18 | AK77: =(IF(S77="Credit Card",0.36,IF(S77="Personal Loan",0.14,IF(S77="Car Loan",0.09,0.085))))+IF(Z77="Low",0,IF(Z77="Medium",0.015,0.03)) -> 0.36 | AL77: =-PMT(AK77/12,AJ77,T77) -> 25627.125 | AM77: =IFERROR(T77/J77,0) -> 0.16522108 | AN77: =R77+AL77 -> 64382.995 | AO77: =IFERROR((AN77*12)/J77,0) -> 0.36216323 | AP77: 0 | AQ77: =IF(AP77>0,T77/AP77,"N/A") -> N/A | AR77: 46260 | AS77: Verified
A78: CUST00077 | B78: Vikram Singh | C78: 9508021882 | D78: vikram.singh729@yahoo.com | E78: 45 | F78: Female | G78: Kanpur | H78: Salaried - Government | I78: Salaried | J78: 683864 | K78: 1 | L78: Y | M78: N | N78: N | O78: N | P78: 435 | R78: 918.45 | S78: Home Loan | U78: =IFERROR((R78*12)/J78,0) -> 0.016116362 | V78: 1 | W78: 43.8 | X78: 0.6 | Y78: =ROUND(0.4*((900-P78)/600*100)+0.3*MIN(U78*100,100)+0.2*MIN(V78*20,100)+0.1*W78,1) -> 39.9 | Z78: =IF(Y78<=30,"Low",IF(Y78<=60,"Medium","High")) -> Medium | AA78: =IF(AND(P78>=650,U78<=0.4,V78<=2,Y78<=50),"Eligible",IF(AND(P78>=550,V78<=4,Y78<=75),"Review","Not Eligible")) -> Not Eligible | AB78: Married | AC78: 0 | AD78: Rented | AE78: 8 | AF78: 0 | AG78: =J78+AF78 -> 683864 | AH78: 0 | AI78: N | AJ78: 120 | AK78: =(IF(S78="Credit Card",0.36,IF(S78="Personal Loan",0.14,IF(S78="Car Loan",0.09,0.085))))+IF(Z78="Low",0,IF(Z78="Medium",0.015,0.03)) -> 0.1 | AL78: =-PMT(AK78/12,AJ78,T78) -> 0 | AM78: =IFERROR(T78/J78,0) -> 0 | AN78: =R78+AL78 -> 918.45 | AO78: =IFERROR((AN78*12)/J78,0) -> 0.016116362 | AP78: 8216672 | AQ78: =IF(AP78>0,T78/AP78,"N/A") -> 0 | AR78: 46181 | AS78: Verified
A79: CUST00078 | B79: Rahul Agarwal | C79: 9659531734 | D79: rahul.agarwal174@hotmail.com | E79: 31 | F79: Male | G79: Jaipur | H79: Salaried - IT/Tech | I79: Salaried | J79: 1425779 | K79: 2 | L79: Y | M79: Y | N79: N | O79: N | P79: 795 | R79: 19129.88 | S79: Car Loan | T79: 817136 | U79: =IFERROR((R79*12)/J79,0) -> 0.16100571 | V79: 2 | W79: 52.1 | X79: 9.3 | Y79: =ROUND(0.4*((900-P79)/600*100)+0.3*MIN(U79*100,100)+0.2*MIN(V79*20,100)+0.1*W79,1) -> 25 | Z79: =IF(Y79<=30,"Low",IF(Y79<=60,"Medium","High")) -> Low | AA79: =IF(AND(P79>=650,U79<=0.4,V79<=2,Y79<=50),"Eligible",IF(AND(P79>=550,V79<=4,Y79<=75),"Review","Not Eligible")) -> Eligible | AB79: Married | AC79: 0 | AD79: Owned | AE79: 4.1 | AF79: 0 | AG79: =J79+AF79 -> 1425779 | AH79: 0 | AI79: N | AJ79: 60 | AK79: =(IF(S79="Credit Card",0.36,IF(S79="Personal Loan",0.14,IF(S79="Car Loan",0.09,0.085))))+IF(Z79="Low",0,IF(Z79="Medium",0.015,0.03)) -> 0.09 | AL79: =-PMT(AK79/12,AJ79,T79) -> 16962.399 | AM79: =IFERROR(T79/J79,0) -> 0.57311547 | AN79: =R79+AL79 -> 36092.279 | AO79: =IFERROR((AN79*12)/J79,0) -> 0.30376892 | AP79: 912698 | AQ79: =IF(AP79>0,T79/AP79,"N/A") -> 0.89529724 | AR79: 46228 | AS79: Pending
A80: CUST00079 | B80: Krishna Iyer | C80: 9444311586 | D80: krishna.iyer618@yahoo.com | E80: 51 | F80: Female | G80: Kolkata | H80: Salaried - Education | I80: Salaried | J80: 1638560 | K80: 1 | L80: Y | M80: N | N80: N | O80: N | P80: 548 | Q80: 320390.49 | R80: 11047.95 | S80: Home Loan | T80: 4561972 | U80: =IFERROR((R80*12)/J80,0) -> 0.080909701 | V80: 0 | W80: 58.6 | X80: 9 | Y80: =ROUND(0.4*((900-P80)/600*100)+0.3*MIN(U80*100,100)+0.2*MIN(V80*20,100)+0.1*W80,1) -> 31.8 | Z80: =IF(Y80<=30,"Low",IF(Y80<=60,"Medium","High")) -> Medium | AA80: =IF(AND(P80>=650,U80<=0.4,V80<=2,Y80<=50),"Eligible",IF(AND(P80>=550,V80<=4,Y80<=75),"Review","Not Eligible")) -> Not Eligible | AB80: Married | AC80: 2 | AD80: Rented | AE80: 28.6 | AF80: 0 | AG80: =J80+AF80 -> 1638560 | AH80: 1 | AI80: N | AJ80: 240 | AK80: =(IF(S80="Credit Card",0.36,IF(S80="Personal Loan",0.14,IF(S80="Car Loan",0.09,0.085))))+IF(Z80="Low",0,IF(Z80="Medium",0.015,0.03)) -> 0.1 | AL80: =-PMT(AK80/12,AJ80,T80) -> 44024.017 | AM80: =IFERROR(T80/J80,0) -> 2.7841349 | AN80: =R80+AL80 -> 55071.967 | AO80: =IFERROR((AN80*12)/J80,0) -> 0.40331975 | AP80: 6194339 | AQ80: =IF(AP80>0,T80/AP80,"N/A") -> 0.73647438 | AR80: 45930 | AS80: Verified
A81: CUST00080 | B81: Kiran Rathi | C81: 9539312437 | D81: kiran.rathi690@hotmail.com | E81: 29 | F81: Female | G81: Ahmedabad | H81: Salaried - IT/Tech | I81: Salaried | J81: 946523 | K81: 1 | L81: N | M81: N | N81: Y | O81: N | P81: 790 | Q81: 330664.41 | R81: 7188.36 | S81: Home Loan | T81: 6060426 | U81: =IFERROR((R81*12)/J81,0) -> 0.091133887 | V81: 0 | W81: 97 | X81: 10.6 | Y81: =ROUND(0.4*((900-P81)/600*100)+0.3*MIN(U81*100,100)+0.2*MIN(V81*20,100)+0.1*W81,1) -> 19.8 | Z81: =IF(Y81<=30,"Low",IF(Y81<=60,"Medium","High")) -> Low | AA81: =IF(AND(P81>=650,U81<=0.4,V81<=2,Y81<=50),"Eligible",IF(AND(P81>=550,V81<=4,Y81<=75),"Review","Not Eligible")) -> Eligible | AB81: Single | AC81: 2 | AD81: Company Provided | AE81: 1.1 | AF81: 648520 | AG81: =J81+AF81 -> 1595043 | AH81: 0 | AI81: N | AJ81: 360 | AK81: =(IF(S81="Credit Card",0.36,IF(S81="Personal Loan",0.14,IF(S81="Car Loan",0.09,0.085))))+IF(Z81="Low",0,IF(Z81="Medium",0.015,0.03)) -> 0.085 | AL81: =-PMT(AK81/12,AJ81,T81) -> 46599.433 | AM81: =IFERROR(T81/J81,0) -> 6.4028301 | AN81: =R81+AL81 -> 53787.793 | AO81: =IFERROR((AN81*12)/J81,0) -> 0.68192058 | AP81: 8459761 | AQ81: =IF(AP81>0,T81/AP81,"N/A") -> 0.71638265 | AR81: 46241 | AS81: Verified
A82: CUST00081 | B82: Anil Mehta | C82: 9954946593 | D82: anil.mehta441@gmail.com | E82: 21 | F82: Male | G82: Jaipur | H82: Self Employed - Professional | I82: Self-Employed | J82: 2441931 | K82: 0 | L82: N | M82: N | N82: N | O82: N | P82: 683 | Q82: 95512.27 | R82: 1736.59 | S82: Personal Loan | T82: 411724 | U82: =IFERROR((R82*12)/J82,0) -> 0.0085338529 | V82: 10 | W82: 50.9 | X82: 4.6 | Y82: =ROUND(0.4*((900-P82)/600*100)+0.3*MIN(U82*100,100)+0.2*MIN(V82*20,100)+0.1*W82,1) -> 39.8 | Z82: =IF(Y82<=30,"Low",IF(Y82<=60,"Medium","High")) -> Medium | AA82: =IF(AND(P82>=650,U82<=0.4,V82<=2,Y82<=50),"Eligible",IF(AND(P82>=550,V82<=4,Y82<=75),"Review","Not Eligible")) -> Not Eligible | AB82: Single | AC82: 0 | AD82: Rented | AE82: 0.3 | AF82: 0 | AG82: =J82+AF82 -> 2441931 | AH82: 0 | AI82: N | AJ82: 24 | AK82: =(IF(S82="Credit Card",0.36,IF(S82="Personal Loan",0.14,IF(S82="Car Loan",0.09,0.085))))+IF(Z82="Low",0,IF(Z82="Medium",0.015,0.03)) -> 0.155 | AL82: =-PMT(AK82/12,AJ82,T82) -> 20061.064 | AM82: =IFERROR(T82/J82,0) -> 0.16860591 | AN82: =R82+AL82 -> 21797.654 | AO82: =IFERROR((AN82*12)/J82,0) -> 0.1071168 | AP82: 0 | AQ82: =IF(AP82>0,T82/AP82,"N/A") -> N/A | AR82: 46161 | AS82: Verified
A83: CUST00082 | B83: Pooja Kumar | C83: 9570477095 | D83: pooja.kumar740@hotmail.com | E83: 41 | F83: Male | G83: Surat | H83: Salaried - Private | I83: Salaried | J83: 782702 | K83: 2 | L83: Y | M83: N | N83: Y | O83: N | P83: 549 | R83: 5155.78 | S83: Personal Loan | T83: 397067 | U83: =IFERROR((R83*12)/J83,0) -> 0.079045869 | V83: 1 | W83: 96.1 | X83: 3.6 | Y83: =ROUND(0.4*((900-P83)/600*100)+0.3*MIN(U83*100,100)+0.2*MIN(V83*20,100)+0.1*W83,1) -> 39.4 | Z83: =IF(Y83<=30,"Low",IF(Y83<=60,"Medium","High")) -> Medium | AA83: =IF(AND(P83>=650,U83<=0.4,V83<=2,Y83<=50),"Eligible",IF(AND(P83>=550,V83<=4,Y83<=75),"Review","Not Eligible")) -> Not Eligible | AB83: Married | AC83: 0 | AD83: Rented | AE83: 8.8 | AF83: 610580 | AG83: =J83+AF83 -> 1393282 | AH83: 0 | AI83: N | AJ83: 48 | AK83: =(IF(S83="Credit Card",0.36,IF(S83="Personal Loan",0.14,IF(S83="Car Loan",0.09,0.085))))+IF(Z83="Low",0,IF(Z83="Medium",0.015,0.03)) -> 0.155 | AL83: =-PMT(AK83/12,AJ83,T83) -> 11151.571 | AM83: =IFERROR(T83/J83,0) -> 0.50730291 | AN83: =R83+AL83 -> 16307.351 | AO83: =IFERROR((AN83*12)/J83,0) -> 0.25001624 | AP83: 0 | AQ83: =IF(AP83>0,T83/AP83,"N/A") -> N/A | AR83: 45897 | AS83: Verified
A84: CUST00083 | B84: Dhruv Nair | C84: 9907803348 | D84: dhruv.nair721@gmail.com | E84: 57 | F84: Male | G84: Coimbatore | H84: Self Employed - Business | I84: Self-Employed | J84: 1834247 | K84: 1 | L84: Y | M84: N | N84: N | O84: N | P84: 840 | Q84: 1063038 | R84: 33219.92 | S84: Home Loan | T84: 6628026 | U84: =IFERROR((R84*12)/J84,0) -> 0.21733117 | V84: 0 | W84: 15.9 | X84: 5.4 | Y84: =ROUND(0.4*((900-P84)/600*100)+0.3*MIN(U84*100,100)+0.2*MIN(V84*20,100)+0.1*W84,1) -> 12.1 | Z84: =IF(Y84<=30,"Low",IF(Y84<=60,"Medium","High")) -> Low | AA84: =IF(AND(P84>=650,U84<=0.4,V84<=2,Y84<=50),"Eligible",IF(AND(P84>=550,V84<=4,Y84<=75),"Review","Not Eligible")) -> Eligible | AB84: Married | AC84: 0 | AD84: Rented | AE84: 24.1 | AF84: 0 | AG84: =J84+AF84 -> 1834247 | AH84: 1 | AI84: N | AJ84: 240 | AK84: =(IF(S84="Credit Card",0.36,IF(S84="Personal Loan",0.14,IF(S84="Car Loan",0.09,0.085))))+IF(Z84="Low",0,IF(Z84="Medium",0.015,0.03)) -> 0.085 | AL84: =-PMT(AK84/12,AJ84,T84) -> 57519.55 | AM84: =IFERROR(T84/J84,0) -> 3.6134861 | AN84: =R84+AL84 -> 90739.47 | AO84: =IFERROR((AN84*12)/J84,0) -> 0.59363523 | AP84: 7817527 | AQ84: =IF(AP84>0,T84/AP84,"N/A") -> 0.84784178 | AR84: 46051 | AS84: Verified
A85: CUST00084 | B85: Kavya Tiwari | C85: 9251782582 | D85: kavya.tiwari524@hotmail.com | E85: 47 | F85: Male | G85: Nagpur | H85: Salaried - Education | I85: Salaried | J85: 1079107 | K85: 1 | L85: Y | M85: N | N85: N | O85: N | P85: 477 | Q85: 359286.03 | R85: 8355.49 | S85: Car Loan | U85: =IFERROR((R85*12)/J85,0) -> 0.092915605 | V85: 0 | W85: 85 | X85: 9.4 | Y85: =ROUND(0.4*((900-P85)/600*100)+0.3*MIN(U85*100,100)+0.2*MIN(V85*20,100)+0.1*W85,1) -> 39.5 | Z85: =IF(Y85<=30,"Low",IF(Y85<=60,"Medium","High")) -> Medium | AA85: =IF(AND(P85>=650,U85<=0.4,V85<=2,Y85<=50),"Eligible",IF(AND(P85>=550,V85<=4,Y85<=75),"Review","Not Eligible")) -> Not Eligible | AB85: Single | AC85: 4 | AD85: Rented | AE85: 5.3 | AF85: 0 | AG85: =J85+AF85 -> 1079107 | AH85: 1 | AI85: N | AJ85: 60 | AK85: =(IF(S85="Credit Card",0.36,IF(S85="Personal Loan",0.14,IF(S85="Car Loan",0.09,0.085))))+IF(Z85="Low",0,IF(Z85="Medium",0.015,0.03)) -> 0.105 | AL85: =-PMT(AK85/12,AJ85,T85) -> 0 | AM85: =IFERROR(T85/J85,0) -> 0 | AN85: =R85+AL85 -> 8355.49 | AO85: =IFERROR((AN85*12)/J85,0) -> 0.092915605 | AP85: 705307 | AQ85: =IF(AP85>0,T85/AP85,"N/A") -> 0 | AR85: 46107 | AS85: Verified
A86: CUST00085 | B86: Tanya Joshi | C86: 9279587066 | D86: tanya.joshi85@rediffmail.com | E86: 22 | F86: Male | G86: Surat | H86: Salaried - Private | I86: Salaried | J86: 1452816 | K86: 2 | L86: Y | M86: Y | N86: N | O86: N | P86: 807 | Q86: 479191 | R86: 25220.56 | S86: Credit Card | U86: =IFERROR((R86*12)/J86,0) -> 0.20831731 | V86: 3 | W86: 83.2 | X86: 5.6 | Y86: =ROUND(0.4*((900-P86)/600*100)+0.3*MIN(U86*100,100)+0.2*MIN(V86*20,100)+0.1*W86,1) -> 32.8 | Z86: =IF(Y86<=30,"Low",IF(Y86<=60,"Medium","High")) -> Medium | AA86: =IF(AND(P86>=650,U86<=0.4,V86<=2,Y86<=50),"Eligible",IF(AND(P86>=550,V86<=4,Y86<=75),"Review","Not Eligible")) -> Review | AB86: Single | AC86: 0 | AD86: Rented | AE86: 0.7 | AF86: 0 | AG86: =J86+AF86 -> 1452816 | AH86: 0 | AI86: N | AJ86: 18 | AK86: =(IF(S86="Credit Card",0.36,IF(S86="Personal Loan",0.14,IF(S86="Car Loan",0.09,0.085))))+IF(Z86="Low",0,IF(Z86="Medium",0.015,0.03)) -> 0.375 | AL86: =-PMT(AK86/12,AJ86,T86) -> 0 | AM86: =IFERROR(T86/J86,0) -> 0 | AN86: =R86+AL86 -> 25220.56 | AO86: =IFERROR((AN86*12)/J86,0) -> 0.20831731 | AP86: 0 | AQ86: =IF(AP86>0,T86/AP86,"N/A") -> N/A | AR86: 46047 | AS86: Verified
A87: CUST00086 | B87: Aditya Kapoor | C87: 9382195698 | D87: aditya.kapoor357@gmail.com | E87: 49 | F87: Male | G87: Ahmedabad | H87: Self Employed - Professional | I87: Self-Employed | J87: 1770652 | K87: 0 | L87: N | M87: N | N87: N | O87: N | P87: 511 | Q87: 144048 | R87: 9603.19 | S87: Car Loan | U87: =IFERROR((R87*12)/J87,0) -> 0.065082399 | V87: 0 | W87: 56.2 | X87: 5 | Y87: =ROUND(0.4*((900-P87)/600*100)+0.3*MIN(U87*100,100)+0.2*MIN(V87*20,100)+0.1*W87,1) -> 33.5 | Z87: =IF(Y87<=30,"Low",IF(Y87<=60,"Medium","High")) -> Medium | AA87: =IF(AND(P87>=650,U87<=0.4,V87<=2,Y87<=50),"Eligible",IF(AND(P87>=550,V87<=4,Y87<=75),"Review","Not Eligible")) -> Not Eligible | AB87: Single | AC87: 1 | AD87: Owned | AE87: 24.1 | AF87: 0 | AG87: =J87+AF87 -> 1770652 | AH87: 1 | AI87: N | AJ87: 60 | AK87: =(IF(S87="Credit Card",0.36,IF(S87="Personal Loan",0.14,IF(S87="Car Loan",0.09,0.085))))+IF(Z87="Low",0,IF(Z87="Medium",0.015,0.03)) -> 0.105 | AL87: =-PMT(AK87/12,AJ87,T87) -> 0 | AM87: =IFERROR(T87/J87,0) -> 0 | AN87: =R87+AL87 -> 9603.19 | AO87: =IFERROR((AN87*12)/J87,0) -> 0.065082399 | AP87: 1747332 | AQ87: =IF(AP87>0,T87/AP87,"N/A") -> 0 | AR87: 46036 | AS87: Verified
A88: CUST00087 | B88: Krishna Tiwari | C88: 9242475723 | E88: 41 | F88: Male | G88: Nagpur | H88: Business Owner | I88: Self-Employed | J88: 896311 | K88: 1 | L88: N | M88: Y | N88: N | O88: N | P88: 395 | Q88: 216647.75 | R88: 3672 | S88: Car Loan | T88: 1073998 | U88: =IFERROR((R88*12)/J88,0) -> 0.049161508 | V88: 1 | W88: 51.4 | X88: 8.8 | Y88: =ROUND(0.4*((900-P88)/600*100)+0.3*MIN(U88*100,100)+0.2*MIN(V88*20,100)+0.1*W88,1) -> 44.3 | Z88: =IF(Y88<=30,"Low",IF(Y88<=60,"Medium","High")) -> Medium | AA88: =IF(AND(P88>=650,U88<=0.4,V88<=2,Y88<=50),"Eligible",IF(AND(P88>=550,V88<=4,Y88<=75),"Review","Not Eligible")) -> Not Eligible | AB88: Single | AC88: 3 | AD88: Owned | AE88: 19.5 | AF88: 0 | AG88: =J88+AF88 -> 896311 | AH88: 1 | AI88: N | AJ88: 72 | AK88: =(IF(S88="Credit Card",0.36,IF(S88="Personal Loan",0.14,IF(S88="Car Loan",0.09,0.085))))+IF(Z88="Low",0,IF(Z88="Medium",0.015,0.03)) -> 0.105 | AL88: =-PMT(AK88/12,AJ88,T88) -> 20168.576 | AM88: =IFERROR(T88/J88,0) -> 1.1982426 | AN88: =R88+AL88 -> 23840.576 | AO88: =IFERROR((AN88*12)/J88,0) -> 0.31918264 | AP88: 1213127 | AQ88: =IF(AP88>0,T88/AP88,"N/A") -> 0.88531374 | AR88: 46114 | AS88: Verified
A89: CUST00088 | B89: Anjali Nair | C89: 9446673808 | D89: anjali.nair849@outlook.com | E89: 42 | F89: Male | G89: Chandigarh | H89: Salaried - Healthcare | I89: Salaried | J89: 503043 | K89: 2 | L89: Y | M89: N | N89: N | O89: Y | P89: 461 | Q89: 133191.48 | R89: 11099.29 | S89: Home Loan | T89: 3197168 | U89: =IFERROR((R89*12)/J89,0) -> 0.26477156 | V89: 10 | W89: 91.4 | X89: 13.3 | Y89: =ROUND(0.4*((900-P89)/600*100)+0.3*MIN(U89*100,100)+0.2*MIN(V89*20,100)+0.1*W89,1) -> 66.3 | Z89: =IF(Y89<=30,"Low",IF(Y89<=60,"Medium","High")) -> High | AA89: =IF(AND(P89>=650,U89<=0.4,V89<=2,Y89<=50),"Eligible",IF(AND(P89>=550,V89<=4,Y89<=75),"Review","Not Eligible")) -> Not Eligible | AB89: Married | AC89: 3 | AD89: Rented | AE89: 2.2 | AF89: 0 | AG89: =J89+AF89 -> 503043 | AH89: 0 | AI89: N | AJ89: 180 | AK89: =(IF(S89="Credit Card",0.36,IF(S89="Personal Loan",0.14,IF(S89="Car Loan",0.09,0.085))))+IF(Z89="Low",0,IF(Z89="Medium",0.015,0.03)) -> 0.115 | AL89: =-PMT(AK89/12,AJ89,T89) -> 37348.991 | AM89: =IFERROR(T89/J89,0) -> 6.3556555 | AN89: =R89+AL89 -> 48448.281 | AO89: =IFERROR((AN89*12)/J89,0) -> 1.155725 | AP89: 3718136 | AQ89: =IF(AP89>0,T89/AP89,"N/A") -> 0.85988463 | AR89: 46215 | AS89: Verified
A90: CUST00089 | B90: Deepak Chauhan | C90: 9351410032 | D90: deepak.chauhan440@gmail.com | E90: 27 | F90: Male | G90: Pune | H90: Business Owner | I90: Self-Employed | J90: 626898 | K90: 3 | L90: Y | M90: Y | N90: N | O90: Y | P90: 651 | R90: 7880.68 | S90: Personal Loan | T90: 550905 | U90: =IFERROR((R90*12)/J90,0) -> 0.15085095 | V90: 0 | W90: 41.4 | X90: 11 | Y90: =ROUND(0.4*((900-P90)/600*100)+0.3*MIN(U90*100,100)+0.2*MIN(V90*20,100)+0.1*W90,1) -> 25.3 | Z90: =IF(Y90<=30,"Low",IF(Y90<=60,"Medium","High")) -> Low | AA90: =IF(AND(P90>=650,U90<=0.4,V90<=2,Y90<=50),"Eligible",IF(AND(P90>=550,V90<=4,Y90<=75),"Review","Not Eligible")) -> Eligible | AB90: Married | AC90: 1 | AD90: Rented | AE90: 1.1 | AF90: 0 | AG90: =J90+AF90 -> 626898 | AH90: 1 | AI90: N | AJ90: 24 | AK90: =(IF(S90="Credit Card",0.36,IF(S90="Personal Loan",0.14,IF(S90="Car Loan",0.09,0.085))))+IF(Z90="Low",0,IF(Z90="Medium",0.015,0.03)) -> 0.14 | AL90: =-PMT(AK90/12,AJ90,T90) -> 26450.537 | AM90: =IFERROR(T90/J90,0) -> 0.87877932 | AN90: =R90+AL90 -> 34331.217 | AO90: =IFERROR((AN90*12)/J90,0) -> 0.6571637 | AP90: 0 | AQ90: =IF(AP90>0,T90/AP90,"N/A") -> N/A | AR90: 45930 | AS90: Verified
A91: CUST00090 | B91: Aarav Bansal | D91: aarav.bansal169@hotmail.com | E91: 43 | F91: Male | G91: Chennai | H91: Salaried - Education | I91: Salaried | J91: 2155492 | K91: 2 | L91: N | M91: Y | N91: Y | O91: N | P91: 693 | Q91: 454639.36 | R91: 11657.42 | S91: Car Loan | U91: =IFERROR((R91*12)/J91,0) -> 0.064898891 | V91: 0 | W91: 66.2 | X91: 3.9 | Y91: =ROUND(0.4*((900-P91)/600*100)+0.3*MIN(U91*100,100)+0.2*MIN(V91*20,100)+0.1*W91,1) -> 22.4 | Z91: =IF(Y91<=30,"Low",IF(Y91<=60,"Medium","High")) -> Low | AA91: =IF(AND(P91>=650,U91<=0.4,V91<=2,Y91<=50),"Eligible",IF(AND(P91>=550,V91<=4,Y91<=75),"Review","Not Eligible")) -> Eligible | AB91: Single | AC91: 2 | AD91: Owned | AE91: 20.7 | AF91: 785303 | AG91: =J91+AF91 -> 2940795 | AH91: 2 | AI91: N | AJ91: 72 | AK91: =(IF(S91="Credit Card",0.36,IF(S91="Personal Loan",0.14,IF(S91="Car Loan",0.09,0.085))))+IF(Z91="Low",0,IF(Z91="Medium",0.015,0.03)) -> 0.09 | AL91: =-PMT(AK91/12,AJ91,T91) -> 0 | AM91: =IFERROR(T91/J91,0) -> 0 | AN91: =R91+AL91 -> 11657.42 | AO91: =IFERROR((AN91*12)/J91,0) -> 0.064898891 | AP91: 683362 | AQ91: =IF(AP91>0,T91/AP91,"N/A") -> 0 | AR91: 46095 | AS91: Verified
A92: CUST00091 | B92: Vihaan Rathi | C92: 9952312670 | D92: vihaan.rathi978@yahoo.com | E92: 52 | F92: Female | G92: Hyderabad | H92: Self Employed - Professional | I92: Self-Employed | J92: 2395401 | K92: 2 | L92: N | M92: Y | N92: N | O92: Y | P92: 669 | R92: 67113.7 | S92: Home Loan | T92: 6267920 | U92: =IFERROR((R92*12)/J92,0) -> 0.33621277 | V92: 0 | W92: 56.9 | X92: 2.8 | Y92: =ROUND(0.4*((900-P92)/600*100)+0.3*MIN(U92*100,100)+0.2*MIN(V92*20,100)+0.1*W92,1) -> 31.2 | Z92: =IF(Y92<=30,"Low",IF(Y92<=60,"Medium","High")) -> Medium | AA92: =IF(AND(P92>=650,U92<=0.4,V92<=2,Y92<=50),"Eligible",IF(AND(P92>=550,V92<=4,Y92<=75),"Review","Not Eligible")) -> Eligible | AB92: Married | AC92: 4 | AD92: Owned | AE92: 17.7 | AF92: 311807 | AG92: =J92+AF92 -> 2707208 | AH92: 2 | AI92: Y | AJ92: 300 | AK92: =(IF(S92="Credit Card",0.36,IF(S92="Personal Loan",0.14,IF(S92="Car Loan",0.09,0.085))))+IF(Z92="Low",0,IF(Z92="Medium",0.015,0.03)) -> 0.1 | AL92: =-PMT(AK92/12,AJ92,T92) -> 56956.636 | AM92: =IFERROR(T92/J92,0) -> 2.6166475 | AN92: =R92+AL92 -> 124070.34 | AO92: =IFERROR((AN92*12)/J92,0) -> 0.62154271 | AP92: 8001957 | AQ92: =IF(AP92>0,T92/AP92,"N/A") -> 0.78329839 | AR92: 46216 | AS92: Verified
A93: CUST00092 | B93: Sunil Malhotra | C93: 9554810443 | D93: sunil.malhotra719@hotmail.com | E93: 26 | F93: Male | G93: Jaipur | H93: Salaried - Government | I93: Salaried | J93: 1599843 | K93: 2 | L93: Y | M93: N | N93: N | O93: Y | P93: 634 | Q93: 375065.44 | R93: 7212.8 | S93: Credit Card | U93: =IFERROR((R93*12)/J93,0) -> 0.054101309 | V93: 2 | W93: 74.3 | X93: 12.7 | Y93: =ROUND(0.4*((900-P93)/600*100)+0.3*MIN(U93*100,100)+0.2*MIN(V93*20,100)+0.1*W93,1) -> 34.8 | Z93: =IF(Y93<=30,"Low",IF(Y93<=60,"Medium","High")) -> Medium | AA93: =IF(AND(P93>=650,U93<=0.4,V93<=2,Y93<=50),"Eligible",IF(AND(P93>=550,V93<=4,Y93<=75),"Review","Not Eligible")) -> Review | AB93: Married | AC93: 0 | AD93: Owned | AE93: 2.4 | AF93: 0 | AG93: =J93+AF93 -> 1599843 | AH93: 0 | AI93: N | AJ93: 18 | AK93: =(IF(S93="Credit Card",0.36,IF(S93="Personal Loan",0.14,IF(S93="Car Loan",0.09,0.085))))+IF(Z93="Low",0,IF(Z93="Medium",0.015,0.03)) -> 0.375 | AL93: =-PMT(AK93/12,AJ93,T93) -> 0 | AM93: =IFERROR(T93/J93,0) -> 0 | AN93: =R93+AL93 -> 7212.8 | AO93: =IFERROR((AN93*12)/J93,0) -> 0.054101309 | AP93: 0 | AQ93: =IF(AP93>0,T93/AP93,"N/A") -> N/A | AR93: 45956 | AS93: Verified
A94: CUST00093 | B94: Krishna Tiwari | C94: 9112187618 | E94: 43 | F94: Female | G94: Kolkata | H94: Salaried - Healthcare | I94: Salaried | J94: 832385 | K94: 1 | L94: N | M94: N | N94: N | O94: Y | P94: 330 | Q94: 167314.89 | R94: 4290.13 | S94: Car Loan | U94: =IFERROR((R94*12)/J94,0) -> 0.061848255 | V94: 0 | W94: 72.7 | X94: 8.7 | Y94: =ROUND(0.4*((900-P94)/600*100)+0.3*MIN(U94*100,100)+0.2*MIN(V94*20,100)+0.1*W94,1) -> 47.1 | Z94: =IF(Y94<=30,"Low",IF(Y94<=60,"Medium","High")) -> Medium | AA94: =IF(AND(P94>=650,U94<=0.4,V94<=2,Y94<=50),"Eligible",IF(AND(P94>=550,V94<=4,Y94<=75),"Review","Not Eligible")) -> Not Eligible | AB94: Married | AC94: 1 | AD94: Owned | AE94: 11.1 | AF94: 0 | AG94: =J94+AF94 -> 832385 | AH94: 0 | AI94: N | AJ94: 24 | AK94: =(IF(S94="Credit Card",0.36,IF(S94="Personal Loan",0.14,IF(S94="Car Loan",0.09,0.085))))+IF(Z94="Low",0,IF(Z94="Medium",0.015,0.03)) -> 0.105 | AL94: =-PMT(AK94/12,AJ94,T94) -> 0 | AM94: =IFERROR(T94/J94,0) -> 0 | AN94: =R94+AL94 -> 4290.13 | AO94: =IFERROR((AN94*12)/J94,0) -> 0.061848255 | AP94: 1718676 | AQ94: =IF(AP94>0,T94/AP94,"N/A") -> 0 | AR94: 46240 | AS94: Verified
A95: CUST00094 | B95: Karan Yadav | C95: 9646346564 | D95: karan.yadav3@gmail.com | E95: 21 | F95: Male | G95: Delhi | H95: Business Owner | I95: Self-Employed | J95: 1826628 | K95: 2 | L95: Y | M95: Y | N95: N | O95: N | P95: 866 | Q95: 880195.94 | R95: 15442.03 | S95: Home Loan | U95: =IFERROR((R95*12)/J95,0) -> 0.10144614 | V95: 0 | W95: 44.5 | X95: 10.9 | Y95: =ROUND(0.4*((900-P95)/600*100)+0.3*MIN(U95*100,100)+0.2*MIN(V95*20,100)+0.1*W95,1) -> 9.8 | Z95: =IF(Y95<=30,"Low",IF(Y95<=60,"Medium","High")) -> Low | AA95: =IF(AND(P95>=650,U95<=0.4,V95<=2,Y95<=50),"Eligible",IF(AND(P95>=550,V95<=4,Y95<=75),"Review","Not Eligible")) -> Eligible | AB95: Married | AC95: 0 | AD95: Owned | AE95: 0.3 | AF95: 0 | AG95: =J95+AF95 -> 1826628 | AH95: 2 | AI95: N | AJ95: 360 | AK95: =(IF(S95="Credit Card",0.36,IF(S95="Personal Loan",0.14,IF(S95="Car Loan",0.09,0.085))))+IF(Z95="Low",0,IF(Z95="Medium",0.015,0.03)) -> 0.085 | AL95: =-PMT(AK95/12,AJ95,T95) -> 0 | AM95: =IFERROR(T95/J95,0) -> 0 | AN95: =R95+AL95 -> 15442.03 | AO95: =IFERROR((AN95*12)/J95,0) -> 0.10144614 | AP95: 4720997 | AQ95: =IF(AP95>0,T95/AP95,"N/A") -> 0 | AR95: 46100 | AS95: Verified
A96: CUST00095 | B96: Neha Bhatia | C96: 9403124688 | D96: neha.bhatia793@outlook.com | E96: 41 | F96: Male | G96: Coimbatore | H96: Business Owner | I96: Self-Employed | J96: 333425 | K96: 2 | L96: Y | M96: Y | N96: N | O96: N | P96: 548 | Q96: 92811 | R96: 1894.1 | S96: Home Loan | T96: 7981149 | U96: =IFERROR((R96*12)/J96,0) -> 0.068168854 | V96: 3 | W96: 74.6 | X96: 8.3 | Y96: =ROUND(0.4*((900-P96)/600*100)+0.3*MIN(U96*100,100)+0.2*MIN(V96*20,100)+0.1*W96,1) -> 45 | Z96: =IF(Y96<=30,"Low",IF(Y96<=60,"Medium","High")) -> Medium | AA96: =IF(AND(P96>=650,U96<=0.4,V96<=2,Y96<=50),"Eligible",IF(AND(P96>=550,V96<=4,Y96<=75),"Review","Not Eligible")) -> Not Eligible | AB96: Single | AC96: 0 | AD96: Company Provided | AE96: 0.8 | AF96: 0 | AG96: =J96+AF96 -> 333425 | AH96: 1 | AI96: N | AJ96: 120 | AK96: =(IF(S96="Credit Card",0.36,IF(S96="Personal Loan",0.14,IF(S96="Car Loan",0.09,0.085))))+IF(Z96="Low",0,IF(Z96="Medium",0.015,0.03)) -> 0.1 | AL96: =-PMT(AK96/12,AJ96,T96) -> 105471.47 | AM96: =IFERROR(T96/J96,0) -> 23.936864 | AN96: =R96+AL96 -> 107365.57 | AO96: =IFERROR((AN96*12)/J96,0) -> 3.864098 | AP96: 11075820 | AQ96: =IF(AP96>0,T96/AP96,"N/A") -> 0.72059215 | AR96: 45895 | AS96: Verified
A97: CUST00096 | B97: Meera Bhatia | C97: 9892510222 | D97: meera.bhatia745@outlook.com | E97: 27 | F97: Male | G97: Kochi | H97: Self Employed - Professional | I97: Self-Employed | J97: 2060835 | K97: 2 | L97: Y | M97: Y | N97: N | O97: N | P97: 395 | Q97: 54283 | R97: 2087.8 | S97: Home Loan | U97: =IFERROR((R97*12)/J97,0) -> 0.012157014 | V97: 4 | W97: 48.6 | X97: 11.3 | Y97: =ROUND(0.4*((900-P97)/600*100)+0.3*MIN(U97*100,100)+0.2*MIN(V97*20,100)+0.1*W97,1) -> 54.9 | Z97: =IF(Y97<=30,"Low",IF(Y97<=60,"Medium","High")) -> Medium | AA97: =IF(AND(P97>=650,U97<=0.4,V97<=2,Y97<=50),"Eligible",IF(AND(P97>=550,V97<=4,Y97<=75),"Review","Not Eligible")) -> Not Eligible | AB97: Married | AC97: 2 | AD97: Rented | AE97: 2.5 | AF97: 0 | AG97: =J97+AF97 -> 2060835 | AH97: 0 | AI97: N | AJ97: 180 | AK97: =(IF(S97="Credit Card",0.36,IF(S97="Personal Loan",0.14,IF(S97="Car Loan",0.09,0.085))))+IF(Z97="Low",0,IF(Z97="Medium",0.015,0.03)) -> 0.1 | AL97: =-PMT(AK97/12,AJ97,T97) -> 0 | AM97: =IFERROR(T97/J97,0) -> 0 | AN97: =R97+AL97 -> 2087.8 | AO97: =IFERROR((AN97*12)/J97,0) -> 0.012157014 | AP97: 8922791 | AQ97: =IF(AP97>0,T97/AP97,"N/A") -> 0 | AR97: 46028 | AS97: Verified
A98: CUST00097 | B98: Rita Rathi | D98: rita.rathi718@outlook.com | E98: 41 | F98: Female | G98: Jaipur | H98: Self Employed - Professional | I98: Self-Employed | J98: 613261 | K98: 2 | L98: N | M98: Y | N98: N | O98: Y | P98: 408 | Q98: 60482.86 | R98: 1475.19 | S98: Car Loan | U98: =IFERROR((R98*12)/J98,0) -> 0.028865817 | V98: 0 | W98: 39 | X98: 11.6 | Y98: =ROUND(0.4*((900-P98)/600*100)+0.3*MIN(U98*100,100)+0.2*MIN(V98*20,100)+0.1*W98,1) -> 37.6 | Z98: =IF(Y98<=30,"Low",IF(Y98<=60,"Medium","High")) -> Medium | AA98: =IF(AND(P98>=650,U98<=0.4,V98<=2,Y98<=50),"Eligible",IF(AND(P98>=550,V98<=4,Y98<=75),"Review","Not Eligible")) -> Not Eligible | AB98: Married | AC98: 1 | AD98: Rented | AE98: 2.1 | AF98: 0 | AG98: =J98+AF98 -> 613261 | AH98: 0 | AI98: N | AJ98: 72 | AK98: =(IF(S98="Credit Card",0.36,IF(S98="Personal Loan",0.14,IF(S98="Car Loan",0.09,0.085))))+IF(Z98="Low",0,IF(Z98="Medium",0.015,0.03)) -> 0.105 | AL98: =-PMT(AK98/12,AJ98,T98) -> 0 | AM98: =IFERROR(T98/J98,0) -> 0 | AN98: =R98+AL98 -> 1475.19 | AO98: =IFERROR((AN98*12)/J98,0) -> 0.028865817 | AP98: 1219440 | AQ98: =IF(AP98>0,T98/AP98,"N/A") -> 0 | AR98: 46062 | AS98: Verified
A99: CUST00098 | B99: Sanjay Rao | C99: 9481975879 | D99: sanjay.rao406@rediffmail.com | E99: 24 | F99: Female | G99: Jaipur | H99: Self Employed - Business | I99: Self-Employed | J99: 430367 | K99: 0 | L99: N | M99: N | N99: N | O99: N | P99: 396 | R99: 994.24 | S99: Credit Card | U99: =IFERROR((R99*12)/J99,0) -> 0.027722572 | V99: 0 | W99: 79.2 | X99: 3.5 | Y99: =ROUND(0.4*((900-P99)/600*100)+0.3*MIN(U99*100,100)+0.2*MIN(V99*20,100)+0.1*W99,1) -> 42.4 | Z99: =IF(Y99<=30,"Low",IF(Y99<=60,"Medium","High")) -> Medium | AA99: =IF(AND(P99>=650,U99<=0.4,V99<=2,Y99<=50),"Eligible",IF(AND(P99>=550,V99<=4,Y99<=75),"Review","Not Eligible")) -> Not Eligible | AB99: Married | AC99: 1 | AD99: Rented | AE99: 2.8 | AF99: 589589 | AG99: =J99+AF99 -> 1019956 | AH99: 2 | AI99: N | AJ99: 12 | AK99: =(IF(S99="Credit Card",0.36,IF(S99="Personal Loan",0.14,IF(S99="Car Loan",0.09,0.085))))+IF(Z99="Low",0,IF(Z99="Medium",0.015,0.03)) -> 0.375 | AL99: =-PMT(AK99/12,AJ99,T99) -> 0 | AM99: =IFERROR(T99/J99,0) -> 0 | AN99: =R99+AL99 -> 994.24 | AO99: =IFERROR((AN99*12)/J99,0) -> 0.027722572 | AP99: 0 | AQ99: =IF(AP99>0,T99/AP99,"N/A") -> N/A | AR99: 45996 | AS99: Verified
A100: CUST00099 | B100: Tanya Rathi | C100: 9238288872 | D100: tanya.rathi95@outlook.com | E100: 28 | F100: Male | G100: Bhopal | H100: Salaried - Private | I100: Salaried | J100: 1004597 | K100: 0 | L100: N | M100: N | N100: N | O100: N | P100: 691 | R100: 2984.15 | S100: Car Loan | T100: 750292 | U100: =IFERROR((R100*12)/J100,0) -> 0.035645936 | V100: 4 | W100: 31.1 | X100: 6.8 | Y100: =ROUND(0.4*((900-P100)/600*100)+0.3*MIN(U100*100,100)+0.2*MIN(V100*20,100)+0.1*W100,1) -> 34.1 | Z100: =IF(Y100<=30,"Low",IF(Y100<=60,"Medium","High")) -> Medium | AA100: =IF(AND(P100>=650,U100<=0.4,V100<=2,Y100<=50),"Eligible",IF(AND(P100>=550,V100<=4,Y100<=75),"Review","Not Eligible")) -> Review | AB100: Married | AC100: 2 | AD100: Rented | AE100: 4.6 | AF100: 0 | AG100: =J100+AF100 -> 1004597 | AH100: 2 | AI100: N | AJ100: 24 | AK100: =(IF(S100="Credit Card",0.36,IF(S100="Personal Loan",0.14,IF(S100="Car Loan",0.09,0.085))))+IF(Z100="Low",0,IF(Z100="Medium",0.015,0.03)) -> 0.105 | AL100: =-PMT(AK100/12,AJ100,T100) -> 34795.573 | AM100: =IFERROR(T100/J100,0) -> 0.74685869 | AN100: =R100+AL100 -> 37779.723 | AO100: =IFERROR((AN100*12)/J100,0) -> 0.45128213 | AP100: 829789 | AQ100: =IF(AP100>0,T100/AP100,"N/A") -> 0.90419613 | AR100: 45965 | AS100: Verified
...

Sheet Raw Data (Unclean)
A1: Customer ID | B1: Full Name | C1: Phone Number | D1: Email ID | E1: Age | F1: Gender | G1: City | H1: Occupation | I1: Employment Type | J1: Annual Income | K1: Existing Products Count | L1: Has Credit Card | M1: Has Personal Loan | N1: Has Car Loan | O1: Has Home Loan | P1: Credit Score | Q1: Existing Outstanding Debt | R1: Monthly EMI Outstanding | S1: Requested Loan Type | T1: Requested Amount | U1: Missed Payments (12M) | V1: Credit Utilization (%) | W1: Years with Bank | X1: Marital Status | Y1: Number of Dependents | Z1: Residence Type | AA1: Employment Tenure (Years) | AB1: Co-Applicant Income | AC1: Existing Loans (Other Banks) | AD1: Previous Default History | AE1: Requested Tenure (Months) | AF1: Collateral Value | AG1: Application Date | AH1: KYC Status
A2: CUST00001 | B2: Rajesh Kumar | D2: rajesh.kumar760@outlook.com | E2: 36 | F2: MALE | G2: Chennai | H2: SALARIED - GOVERNMENT | I2: Salaried | J2: 664,647 | K2: 2 | L2: 0 | M2: Y | N2: Yes | O2: false | P2: 327 | Q2: 223817.91 | R2: 3926.63 | S2: Home Loan | T2: ₹3,349,189 | U2: 0 | V2: 31.4 | W2: 13.1 | X2: Single | Y2: 0 | Z2: Owned | AA2: 4.4 | AB2: 722621.0 | AC2: 0 | AD2: NO | AE2: 240 | AF2: 4561172.0 | AG2: 2026/07/01 | AH2: Verified
A3: CUST00002 | B3: Aditya Yadav | C3: 95933037 | D3: aditya.yadav550@gmail.com | E3: 45 | F3: MALE | G3: Coimbatore | H3: Salaried - IT/Tech | I3: Salaried | J3: 1,816,807 | K3: 1 | L3: NO | M3: no | N3: 1 | O3: no | P3: 596 | Q3: ₹1,073,974 | R3: 41306.71 | S3: Credit Card | T3: 219295 | U3: 0 | V3: 65.4 | W3: 5.6 | X3: married | Y3: 0 | Z3: Owned | AA3: 22.5 | AC3: 1 | AD3: NO | AE3: 18 | AH3: Verified
A4: CUST00003 | B4: Vikram Khanna | D4: vikram.khanna705@rediffmail.com | E4: 35 | F4: Female | G4: delhi | H4: Self Employed - Professional | I4: Self-Employed | J4: 434638 | K4: 1 | L4: NO | M4: false | N4: YES | O4: 0 | P4: 880 | Q4: 228541.6 | R4: 7141.93 | S4: PERSONAL LOAN | T4: ₹737,277 | U4: 1 | V4: 89.0 | W4: 9.7 | X4: Married | Y4: 0 | Z4: Rented | AA4: 7.7 | AC4: 0 | AD4: NO | AE4: 36 | AG4: 16 Dec 2025 | AH4: Pending
A5: CUST00004 | B5: Krishna Desai | C5: 09629908599 | D5: krishna.desai94 at gmail.com | E5: 28 | F5: Male | G5: Calcutta | H5: Salaried - Education | I5: Salaried | J5: 566454 | K5: 1 | L5: yes | M5: no | N5: no | O5: N | P5: 866 | Q5: 292,555 | R5: 24379.6 | S5: Credit Card | U5: 4 | V5: 76.3 | W5: 11.6 | X5: Married | Y5: 1 | Z5: Owned | AA5: 0.3 | AC5: 1 | AD5: true | AE5: 18 | AG5: 2026/05/12 | AH5: Verified
A6: CUST00005 | B6: Usha Mishra | C6: +91-9420452650 | D6: USHA.MISHRA862@REDIFFMAIL.COM | E6: 59 | F6: M | G6: Chennai | H6: Salaried - Healthcare | I6: Salaried | J6: 977,585 | K6: 2 | L6: 1 | M6: 0 | N6: NO | O6: Yes | P6: 631 | Q6: 286,592 | R6: 15083.8 | S6: Car Loan | T6: -944903 | U6: 0 | V6: 27.9 | W6: 8.6 | X6: Married | Y6: 2 | Z6: Rented | AA6: 29.3 | AC6: 0 | AD6: false | AE6: 72 | AF6: 1023354.0 | AG6: 2026-05-23 | AH6: Verified
A7: CUST00006 | B7: Saanvi Reddy | E7: 40 | F7: FEMALE | G7: KANPUR | H7: Business Owner | I7: Self-Employed | K7: 4 | L7: YES | M7: 1 | N7: Y | O7: Y | P7: 867 | Q7: N/A | R7: 13121.16 | S7: credit card | T7: ₹57,220 | U7: 2 | V7: 10.6 | W7: 1.2 | X7: Married | Y7: 1 | Z7: Rented | AA7: 5.5 | AC7: 0 | AD7: no | AE7: 36 | AG7: 2025/12/28 | AH7: Verified
A8: CUST00007 | B8: Preeti Malhotra | C8: 9304451095 | D8: preeti.malhotra97@gmail,com | E8: 63 | F8: female | G8: Kanpur | H8: Salaried - Education | I8: Salaried | J8: 2024287 | K8: 1 | L8: 1 | M8: NO | N8: false | O8: N | P8: 400 | Q8: ₹73,618 | R8: 1269.28 | S8: Car Loan | U8: 0 | V8: 23.1 | W8: 6.8 | X8: Married | Y8: 1 | Z8: Owned | AA8: 27.7 | AC8: 2 | AD8: 0 | AE8: 24 | AF8: 624628.0 | AG8: 05/29/2026 | AH8: Verified
A9: CUST00008 | B9: Sai Khanna | C9: 09909134796 | D9: sai.khanna870@yahoo.com | E9: 31 | F9: Female | G9: Chandigarh | H9: BUSINESS OWNER | I9: Self-Employed | J9: ₹1,196,521 | K9: 2 | L9: NO | M9: No | N9: true | O9: 1 | P9: 699 | Q9: 190,393 | R9: 4643.72 | S9: Car Loan | T9: 1187110 | U9: 2 | V9: 74.4 | W9: 11.8 | X9: Single | Y9: 1 | Z9: Owned | AA9: 2.4 | AB9: 701803.0 | AC9: 0 | AD9: No | AE9: 24 | AF9: 1385162.0 | AG9: 10-05-2026 | AH9: Verified
A10: CUST00009 | B10: Divya Patel | C10: 9161073976 | D10: divya.patel984@rediffmail.com | E10: 26 | F10: Male | G10: BENGALURU | H10: Salaried - Government | I10: Salaried | J10: 1,286,516 | K10: 1 | L10: Yes | M10: no | N10: false | O10: NO | P10: 340 | Q10: 478106.53 | R10: 12581.75 | S10: Car Loan | T10: 846,865 | U10: 0 | V10: 73.0 | W10: 3.7 | X10: Married | Y10: 2 | Z10: OWNED | AA10: 1.8 | AC10: 0 | AD10: No | AE10: 72 | AF10: 1057920.0 | AG10: 02-10-2025 | AH10: Verified
A11: CUST00010 | B11: Sneha Nair | C11: 09242224154 | E11: 25 | F11: Male | G11: Kanpur | H11: Salaried - IT/Tech | I11: Salaried | J11: 961638 | K11: 1 | L11: Y | M11: 0 | N11: false | O11: No | P11: 841 | Q11: 4513.8 | R11: 96.04 | S11: Car Loan | T11: ₹517,236 | U11: 5 | V11: 17.8 | W11: 1.9 | X11: Married | Y11: 2 | Z11: Owned | AA11: 2.5 | AC11: 0 | AD11: No | AE11: 48 | AF11: 595381.0 | AG11: 2026-01-01 | AH11: Verified
A12: CUST00011 | B12: Rekha Verma | C12: 9199104722 | D12: rekha.verma650@hotmail.com | E12: 38 | F12: F | G12: Mumbai | H12: Salaried - Healthcare | I12: Salaried | K12: 1 | L12: 0 | M12: Y | N12: no | O12: No | P12: 737 | Q12: 285623.98 | R12: 15032.84 | S12: CREDIT CARD | T12: N/A | U12: 2 | V12: 19.2 | W12: 0.7 | X12: MARRIED | Y12: 2 | Z12: Owned | AA12: 1.0 | AC12: 3 | AD12: 1 | AE12: 12 | AG12: 2026/02/25 | AH12: Verified
A13: CUST00012 | B13: Rahul Pandey | D13: rahul.pandey363@rediffmail.com | E13: 47 | F13: F | G13: AHMEDABAD | H13: Self Employed - Business | I13: Self-Employed | J13: N/A | K13: 1 | L13: No | M13: true | N13: NO | O13: no | P13: 721 | Q13: 501851.51 | R13: 8505.96 | S13: Personal Loan | T13: ₹329,766 | U13: 0 | V13: 71.6 | W13: 5.9 | X13: Married | Y13: 1 | Z13: Owned | AA13: 23.9 | AB13: 765402.0 | AC13: 2 | AD13: NO | AE13: 24 | AG13: 2026-03-18 | AH13: Verified
A14: CUST00013 | B14: Usha Gupta | C14: +91-9930353157 | D14: usha.gupta286@outlook.com | E14: 62 | F14: female | G14: Coimbatore | H14: Salaried - Healthcare | I14: Salaried | J14: 415765 | K14: 2 | L14: true | M14: false | N14: true | O14: NO | P14: 571 | Q14: 9543.6 | R14: 190.87 | S14: Home Loan | T14: ₹4,399,833 | U14: 2 | V14: 34.8 | W14: 9.2 | X14: Married | Y14: 1 | Z14: Rented | AA14: 7.9 | AC14: 0 | AD14: yes | AE14: 360 | AF14: 5815322.0 | AG14: 04-08-2026 | AH14: Verified
A15: CUST00014 | B15: saanvi gupta | C15: 98132 19781 | D15: saanvi.gupta943@outlook.com | E15: 60 | F15: female | G15: Hyderabad | H15: Salaried - IT/Tech | I15: Salaried | J15: ₹2,427,025 | K15: 1 | L15: 1 | M15: 0 | N15: NO | O15: 0 | P15: 430 | R15: 5173.34 | S15: Home Loan | T15: ₹7,181,754 | U15: 2 | V15: 21.5 | W15: 8.6 | X15: Married | Y15: 3 | Z15: owned | AA15: 6.5 | AC15: 1 | AD15: No | AE15: 300 | AF15: 9052888.0 | AG15: 12/13/2025 | AH15: verified
A16: CUST00015 | B16: Kiran Sethi | C16: 99547 25078 | D16: KIRAN.SETHI754@YAHOO.COM | E16: 63 | F16: M | G16: Surat | H16: Freelancer | I16: Self-Employed | K16: 2 | L16: Y | M16: NO | N16: Y | O16: false | P16: 503 | Q16: ₹150,821 | R16: 10772.93 | S16: Personal Loan | T16: ₹548,216 | U16: 1 | V16: 78.0 | W16: 6.9 | X16: Single | Y16: 2 | Z16: RENTED | AA16: 11.7 | AC16: 0 | AD16: 0 | AE16: 12 | AG16: 2026/03/31 | AH16: Verified
A17: CUST00016 | B17: Preeti Tiwari | C17: 9656152900 | D17: preeti.tiwari476@gmail.com | E17: 56 | F17: Male | G17: Hyderabad | H17: Business Owner | I17: Self-Employed | J17: ₹859,264 | K17: 0 | L17: no | M17: 0 | N17: false | O17: No | P17: 753 | Q17: 52643.01 | R17: 907.64 | S17: Home Loan | U17: 0 | V17: 20.1 | W17: 13.0 | X17: Married | Y17: 2 | Z17: Rented | AA17: 8.5 | AC17: 0 | AD17: 0 | AE17: 300 | AF17: 7128348.0 | AG17: 2026/01/19 | AH17: Verified
A18: CUST00017 | B18: Diya Mehta | C18: 9679984033 | D18: diya.mehta83@yahoo.com | E18: 30 | F18: male | G18: Nagpur | H18: Self Employed - Business | I18: Self-Employed | J18: 1197383 | K18: 1 | L18: true | M18: false | N18: false | O18: No | P18: 511 | Q18: ₹598,374 | R18: 16621.5 | S18: CREDIT CARD | U18: 4 | V18: 59.7 | W18: 7.3 | X18: Single | Y18: 1 | Z18: Owned | AA18: 8.1 | AC18: 0 | AD18: No | AE18: 18 | AG18: 02-05-2026 | AH18: Verified
A19: CUST00018 | B19: saanvi joshi | C19: 91311 65166 | D19: saanvi.joshi399@outlook.com | E19: 63 | F19: Female | G19: KOLKATA | H19: Business Owner | I19: Self-Employed | K19: 0 | L19: NO | M19: No | N19: NO | O19: No | Q19: ₹7,012 | R19: 179.8 | S19: Personal Loan | T19: 958,959 | U19: 1 | V19: 9.8 | W19: 5.8 | X19: Married | Y19: 1 | Z19: Rented | AA19: 11.6 | AC19: 2 | AD19: N | AE19: 12 | AG19: 23-04-2026 | AH19: Verified
A20: CUST00019 | B20: Shreya Verma | C20: 9475767056 | D20: shreya.verma230@gmail.com | E20: 62 | F20: male | G20: Mumbai | H20: Self Employed - Professional | I20: Self-Employed | J20: 1136179 | K20: 1 | L20: false | M20: no | N20: Yes | O20: NO | P20: 417 | Q20: -384462.24 | R20: 15378.49 | S20: Home Loan | T20: 7367537 | U20: 0 | V20: 40.0 | W20: 9.2 | X20: Divorced | Y20: 2 | Z20: Rented | AA20: 5.2 | AB20: 584014.0 | AC20: 2 | AD20: 0 | AE20: 300 | AF20: 9203259.0 | AG20: 05-12-2025 | AH20: Verified
A21: CUST00020 | B21: Deepak Saxena | C21: 9773496394 | D21: DEEPAK.SAXENA249@GMAIL.COM | E21: 65 | F21: Female | G21: Hyderabad | H21: SALARIED - PRIVATE | I21: Salaried | J21: ₹1,756,278 | K21: 2 | L21: Y | M21: no | N21: yes | O21: 0 | P21: 312 | R21: 20819.87 | S21: Credit Card | T21: ₹247,291 | U21: 6 | V21: 65.4 | W21: 12.5 | X21: Single | Y21: 1 | Z21: Rented | AA21: 29.0 | AB21: 756149.0 | AC21: 0 | AD21: N | AE21: 36 | AH21: Verified
A22: CUST00021 | B22: Rekha Rao | C22: 9991990632 | D22: rekha.rao958 at gmail.com | E22: 38 | F22: F | G22: Ahmedabad | H22: Business Owner | I22: Self-Employed | J22: 1889596 | K22: 1 | L22: yes | M22: no | N22: N | O22: no | P22: 663 | Q22: ₹904,548 | R22: 27410.56 | S22: Car Loan | U22: 1 | V22: 54.1 | W22: 3.0 | X22: Married | Y22: 1 | Z22: Rented | AA22: 4.3 | AC22: 1 | AD22: false | AE22: 24 | AF22: 939712.0 | AH22: Verified
A23: CUST00022 | B23: Rahul Iyer | C23: 09812921644 | D23: rahul.iyer596@outlook.com | F23: F | G23: Indore | H23: Freelancer | I23: Self-Employed | J23: 1,687,439 | K23: 1 | L23: Y | M23: 0 | N23: No | O23: NO | P23: 497 | Q23: 319480.74 | R23: 5414.93 | S23: personal loan | T23: 250845 | U23: 0 | V23: 51.0 | W23: 10.9 | X23: Divorced | Y23: 2 | Z23: Owned | AA23: 3.3 | AB23: 320612.0 | AC23: 0 | AD23: NO | AE23: 60 | AG23: 10/29/2025 | AH23: Verified
A24: CUST00023 | B24: Vihaan Bhatt | C24: 09413679331 | D24: vihaan.bhatt715@yahoo.com | E24: 61 | F24: F | G24: Hyderabad | H24: Salaried - Private | I24: Salaried | J24: ₹1,492,605 | K24: 3 | L24: yes | M24: no | N24: Y | O24: Yes | Q24: 102,172 | R24: 6385.76 | S24: Home Loan | T24: ₹5,625,069 | U24: 0 | V24: 64.8 | W24: 1.0 | X24: married | Y24: 2 | Z24: Owned | AA24: 29.8 | AB24: 723333.0 | AC24: 1 | AD24: NO | AE24: 180 | AF24: 7559662.0 | AG24: 08-03-2026 | AH24: Verified
A25: CUST00024 | B25: Tanya Iyer | C25: 97319 24051 | D25: tanya.iyer440@outlook.com | E25: 57 | F25: Male | G25: Hyderabad | H25: Self Employed - Professional | I25: Self-Employed | J25: ₹1,185,103 | K25: 3 | L25: yes | M25: YES | N25: Y | O25: NO | P25: 460 | Q25: 1902.6 | R25: 47.56 | S25: Home Loan | T25: 3943260 | U25: 0 | V25: 32.4 | W25: 4.4 | X25: Single | Y25: 0 | Z25: Owned | AA25: 8.2 | AC25: 1 | AD25: 0 | AE25: 180 | AF25: 4953857.0 | AG25: 05/31/2026 | AH25: Verified
A26: CUST00025 | B26: Ishaan Khanna | D26: ishaan.khanna847@yahoo.com | E26: 25 | F26: F | G26: Kolkata | H26: Salaried - IT/Tech | I26: Salaried | J26: 1510520 | K26: 1 | L26: true | M26: NO | N26: no | O26: N | P26: 578 | Q26: N/A | R26: 10548.46 | S26: Home Loan | T26: 2,174,795 | U26: 1 | V26: 89.5 | W26: 11.1 | X26: Single | Y26: 0 | Z26: Owned | AA26: 2.8 | AC26: 1 | AD26: false | AE26: 240 | AF26: 2814319.0 | AG26: 2025-11-23 | AH26: Verified
A27: CUST00026 | B27: Suresh Kapoor | C27: 9398668350 | D27: suresh.kapoor186@rediffmail.com | E27: 48 | F27: female | G27: Bangalore | H27: Business Owner | I27: Self-Employed | J27: ₹1,759,454 | K27: 3 | L27: yes | M27: no | N27: Yes | O27: 1 | P27: 721 | R27: 24409.74 | S27: Home Loan | U27: 1 | V27: 48.2 | W27: 4.9 | X27: Married | Y27: 4 | Z27: Owned | AA27: 14.0 | AC27: 1 | AD27: 0 | AE27: 300 | AF27: 9168240.0 | AG27: 05/18/2026 | AH27: Verified
A28: CUST00027 | B28: Anil Joshi | C28: 9771527524 | D28: anil.joshi453 at gmail.com | E28: 34 | F28: F | G28: Coimbatore | H28: Self Employed - Business | I28: Self-Employed | J28: -1508081 | K28: 2 | L28: Yes | M28: N | N28: YES | O28: No | P28: 545 | Q28: -642246.0 | R28: 20717.61 | S28: Credit Card | T28: ₹309,538 | U28: 0 | V28: 26.3 | W28: 12.7 | X28: Married | Y28: 3 | Z28: Rented | AA28: 2.3 | AC28: 0 | AD28: No | AE28: 36 | AG28: 30-04-2026 | AH28: Pending
A29: CUST00028 | B29: Rahul Kapoor | C29: +91-9691916368 | E29: 33 | F29: MALE | G29: Banglore | H29: Salaried - IT/Tech | I29: Salaried | J29: 2,040,394 | K29: 2 | L29: true | M29: N | N29: false | O29: true | P29: 605 | Q29: 1025268.51 | R29: 20923.85 | S29: Home Loan | T29: N/A | U29: 0 | V29: 51.0 | W29: 5.1 | X29: Single | Y29: 1 | Z29: Company Provided | AA29: 10.5 | AC29: 0 | AD29: N | AE29: 300 | AF29: 3188454.0 | AG29: 25 Apr 2026 | AH29: Verified
A30: CUST00029 | B30: Preeti Chopra | C30: 95145 48900 | D30: PREETI.CHOPRA680@YAHOO.COM | E30: 52 | F30: Male | G30: CHENNAI | H30: Freelancer | I30: Self-Employed | K30: 0 | L30: NO | M30: no | N30: NO | O30: NO | P30: 767 | Q30: 2597.56 | R30: 123.69 | S30: Home Loan | T30: ₹6,992,703 | U30: 6 | V30: 12.1 | W30: 11.8 | X30: Married | Y30: 2 | Z30: Owned | AA30: 2.7 | AB30: 655768.0 | AC30: 0 | AD30: true | AE30: 300 | AF30: 9566687.0 | AG30: 13 Sep 2025 | AH30: VERIFIED
A31: CUST00030 | B31: Rahul Mishra | D31: rahul.mishra944@outlook.com | E31: 35 | F31: M | G31: Indore | H31: Salaried - Government | I31: Salaried | J31: 721557 | K31: 2 | L31: Yes | M31: N | N31: NO | O31: true | P31: 357 | R31: 3628.83 | S31: Home Loan | T31: ₹2,721,127 | U31: 0 | V31: 44.1 | W31: 10.3 | X31: Married | Y31: 0 | Z31: Rented | AA31: 5.5 | AC31: 0 | AD31: no | AE31: 180 | AF31: 3443008.0 | AG31: 01/03/2026 | AH31: Verified
A32: CUST00031 | B32: Mahesh Sharma | C32: 9963968184 | E32: 64 | F32: MALE | G32: bengaluru | H32: Business Owner | I32: Self-Employed | J32: 1,749,407 | K32: 1 | L32: false | M32: Y | N32: No | O32: no | P32: 767 | Q32: 887268.36 | R32: 36969.51 | S32: Home Loan | U32: 0 | V32: 41.2 | W32: 5.5 | X32: MARRIED | Y32: 2 | Z32: Owned | AA32: 25.0 | AC32: 0 | AD32: false | AE32: 120 | AF32: 7650724.0 | AG32: 2026-05-07 | AH32: Verified
A33: CUST00032 | B33: lata iyer | C33: 99329 45529 | D33: lata.iyer819@yahoo.com | E33: 59 | F33: female | G33: Ahmedabad | H33: Self Employed - Professional | I33: Self-Employed | J33: 1351204 | K33: 0 | L33: No | M33: no | N33: NO | O33: NO | P33: 399 | Q33: 122,068 | R33: 2303.17 | S33: credit card | T33: ₹181,969 | U33: 3 | V33: 8.2 | W33: 5.6 | X33: Married | Y33: 3 | Z33: Owned | AA33: 12.6 | AB33: 739885.0 | AC33: 2 | AD33: NO | AE33: 24 | AH33: Verified
A34: CUST00033 | B34: Geeta Joshi | C34: +91-9965960427 | D34: geeta.joshi303@outlook.com | E34: 28 | F34: female | G34: bengaluru | H34: Self Employed - Business | I34: Self-Employed | J34: ₹1,246,296 | K34: 0 | L34: NO | M34: NO | N34: 0 | O34: N | P34: 870 | Q34: 45586.4 | R34: 1232.06 | S34: Credit Card | T34: ₹158,652 | U34: 1 | V34: 48.2 | W34: 10.2 | X34: Single | Y34: 2 | Z34: Rented | AA34: 6.6 | AB34: 325366.0 | AC34: 0 | AD34: true | AE34: 24 | AG34: 2026-07-04 | AH34: Verified
A35: CUST00034 | B35: Arjun Mishra | D35: arjun.mishra476@outlook.com | E35: 62 | F35: Female | G35: Hyderabad | H35: Self Employed - Business | I35: Self-Employed | J35: ₹490,198 | K35: 1 | L35: false | M35: No | N35: 0 | O35: Yes | P35: 850 | Q35: ₹39,901 | R35: 973.2 | S35: Car Loan | T35: 1432865 | U35: 0 | V35: 75.5 | W35: 2.5 | X35: MARRIED | Y35: 0 | Z35: Rented | AA35: 12.4 | AC35: 0 | AD35: No | AE35: 60 | AF35: 1631946.0 | AG35: 2025/12/24 | AH35: Verified
A36: CUST00035 | B36: Reyansh Pandey | E36: 24 | F36: F | G36: Jaipur | H36: Self Employed - Professional | I36: Self-Employed | J36: 812374 | K36: 1 | L36: no | M36: No | N36: Yes | O36: No | P36: 321 | Q36: -24653.2 | R36: 747.07 | S36: Personal Loan | T36: 182040 | U36: 3 | V36: 24.5 | W36: 12.5 | X36: Married | Y36: 2 | Z36: Rented | AA36: 0.9 | AC36: 1 | AD36: N | AE36: 36 | AG36: 2025-11-08 | AH36: Pending
A37: CUST00036 | B37: Shreya Nair | C37: 9957397689 | D37: shreya.nair179@gmail.com | E37: 63 | F37: F | G37: CHENNAI | H37: Salaried - Private | I37: Salaried | J37: ₹1,802,577 | K37: 2 | L37: No | M37: 1 | N37: 0 | O37: Yes | P37: 353 | R37: 3607.77 | S37: Credit Card | U37: 0 | V37: 47.6 | W37: 5.6 | X37: Married | Y37: 1 | Z37: Owned | AA37: 18.6 | AC37: 2 | AD37: no | AE37: 24 | AG37: 2026-04-17 | AH37: verified
A38: CUST00037 | B38: Vivaan Verma | C38: 96143 02907 | D38: VIVAAN.VERMA868@HOTMAIL.COM | E38: 48 | F38: Male | G38: Chandigarh | H38: Business Owner | I38: Self-Employed | J38: 608242 | K38: 2 | L38: N | M38: false | N38: 1 | O38: true | P38: 899 | Q38: ₹200,120 | R38: 6253.75 | S38: Home Loan | U38: 1 | V38: 48.1 | W38: 9.2 | X38: Married | Y38: 2 | Z38: Rented | AA38: 17.7 | AC38: 1 | AD38: 0 | AE38: 300 | AF38: 8933633.0 | AH38: Verified
A39: CUST00038 | B39: neha chopra | C39: 09546665485 | D39: neha.chopra748@gmail,com | E39: 41 | F39: female | G39: Lucknow | H39: Salaried - IT/Tech | I39: Salaried | J39: -1869932 | K39: 1 | L39: No | M39: false | N39: 0 | O39: Y | P39: 387 | Q39: ₹104,600 | R39: 5811.13 | S39: Car Loan | T39: 572871 | U39: 1 | V39: 60.7 | W39: 8.5 | X39: Married | Y39: 0 | Z39: Owned | AA39: 13.4 | AC39: 2 | AD39: N | AE39: 48 | AF39: 670306.0 | AG39: 02/22/2026 | AH39: Verified
A40: CUST00039 | B40: Sneha Reddy | C40: +91-9266140258 | E40: 35 | F40: Male | G40: Kanpur | H40: Freelancer | I40: Self-Employed | J40: 1,841,662 | K40: 3 | L40: Y | M40: yes | N40: 1 | O40: NO | P40: 874 | R40: 21115.12 | S40: Credit Card | T40: -339288 | U40: 5 | V40: 83.8 | W40: 4.2 | X40: Married | Y40: 2 | Z40: Owned | AA40: 5.0 | AB40: 802397.0 | AC40: 1 | AD40: NO | AE40: 18 | AH40: Pending
A41: CUST00040 | B41: Sai Yadav | C41: +91-9669601448 | D41: sai.yadav221 at hotmail.com | E41: 47 | F41: M | G41: lucknow | H41: Self Employed - Business | I41: Self-Employed | J41: 1852115 | K41: 1 | L41: yes | M41: NO | N41: N | O41: 0 | P41: 353 | Q41: ₹172,891 | R41: 2881.52 | S41: Credit Card | T41: -373353 | U41: 0 | V41: 47.1 | W41: 6.5 | X41: Single | Y41: 1 | Z41: Owned | AA41: 13.5 | AB41: 233167.0 | AC41: 1 | AD41: No | AE41: 24 | AG41: 18 Sep 2025 | AH41: Verified
A42: CUST00041 | B42: Simran Verma | D42: simran.verma210@outlook.com | E42: 34 | F42: MALE | G42: Jaipur | H42: Salaried - IT/Tech | I42: Salaried | K42: 2 | L42: 1 | M42: false | N42: N | O42: true | P42: 845 | R42: 16084.43 | S42: Car Loan | T42: N/A | U42: 0 | V42: 75.5 | W42: 6.7 | X42: Married | Y42: 0 | Z42: Owned | AA42: 5.8 | AC42: 1 | AD42: no | AE42: 60 | AF42: 475593.0 | AG42: 02/08/2026 | AH42: Verified
A43: CUST00042 | B43: Swati Kapoor | C43: 99933810 | D43: swati.kapoor707@outlook.com | E43: 26 | F43: FEMALE | G43: Hyderabad | H43: Self Employed - Professional | I43: Self-Employed | J43: 2127359 | K43: 0 | L43: no | M43: N | N43: N | O43: No | P43: 647 | Q43: ₹47,136 | R43: 2142.56 | S43: Credit Card | T43: 287,640 | U43: 1 | V43: 55.4 | W43: 3.1 | X43: Single | Y43: 1 | Z43: COMPANY PROVIDED | AA43: 3.3 | AB43: 227103.0 | AC43: 0 | AD43: false | AE43: 18 | AG43: 07/27/2026 | AH43: Verified
A44: CUST00043 | B44: Sunil Mishra | C44: 9630554118 | E44: 58 | F44: Female | G44: Lucknow | H44: Salaried - Healthcare | I44: Salaried | J44: 933161 | K44: 1 | L44: YES | M44: No | N44: false | O44: false | P44: 357 | R44: 12315.7 | S44: Car Loan | T44: 1268344 | U44: 1 | V44: 10.4 | W44: 12.5 | X44: Married | Y44: 3 | Z44: Rented | AA44: 18.6 | AC44: 0 | AD44: NO | AE44: 84 | AF44: 1559017.0 | AG44: 2026-04-13 | AH44: Verified
A45: CUST00044 | B45: Nisha Mishra | C45: 93021 20588 | D45: nisha.mishra330@rediffmail.com | E45: 51 | F45: Male | G45: Delhi | H45: Business Owner | I45: Self-Employed | J45: ₹734,118 | K45: 1 | L45: no | M45: No | N45: NO | O45: Y | P45: 476 | R45: 302.47 | S45: Home Loan | T45: 5186137 | U45: 1 | V45: 62.9 | W45: 5.6 | X45: Single | Y45: 1 | Z45: Rented | AA45: 20.5 | AB45: 623165.0 | AC45: 0 | AD45: false | AE45: 360 | AF45: 6843600.0 | AG45: 2026-01-18 | AH45: Verified
A46: CUST00045 | B46: Rekha Pandey | C46: 9747145068 | D46: rekha.pandey895@yahoo.com | E46: 42 | F46: male | G46: Chennai | H46: Salaried - Healthcare | I46: Salaried | J46: 1601206 | K46: 0 | L46: N | M46: NO | N46: 0 | O46: NO | P46: 386 | Q46: 49570.44 | R46: 1376.96 | S46: Car Loan | T46: 568002 | U46: 2 | V46: 83.8 | W46: 11.1 | X46: Single | Y46: 2 | Z46: Rented | AA46: 9.1 | AC46: 0 | AD46: false | AE46: 36 | AF46: 635223.0 | AG46: 01-05-2026 | AH46: Verified
A47: CUST00046 | B47: KRISHNA SINGH | C47: 91828 55381 | E47: 53 | F47: MALE | G47: Lucknow | H47: Self Employed - Business | I47: Self-Employed | J47: ₹1,880,077 | K47: 2 | L47: 1 | M47: YES | N47: 0 | O47: No | P47: 469 | Q47: -813527.74 | R47: 58109.12 | S47: Home Loan | U47: 2 | V47: 27.6 | W47: 6.8 | X47: Married | Y47: 2 | Z47: Owned | AA47: 16.2 | AB47: 756468.0 | AC47: 0 | AD47: No | AE47: 240 | AF47: 6011944.0 | AG47: 2026/06/14 | AH47: PENDING
A48: CUST00047 | B48: Neha Chauhan | C48: 94025500 | D48: neha.chauhan797@hotmail.com | E48: 53 | F48: Female | G48: KOLKATA | H48: Self Employed - Professional | I48: Self-Employed | J48: 880,485 | K48: 1 | L48: No | M48: Y | N48: N | O48: N | P48: 405 | Q48: 375,827 | R48: 8351.71 | S48: Credit Card | U48: 0 | V48: 20.2 | W48: 6.8 | X48: Married | Y48: 3 | Z48: Owned | AA48: 27.3 | AC48: 2 | AD48: Yes | AE48: 36 | AG48: 22-09-2025 | AH48: Verified
A49: CUST00048 | B49: Kavya Rao | C49: 9514642708 | D49: kavya.rao84@outlook.com | E49: 35 | F49: Male | G49: lucknow | H49: Salaried - Government | I49: Salaried | J49: 1706309 | K49: 1 | L49: no | M49: Y | N49: false | O49: false | P49: 442 | Q49: ₹776,890 | R49: 18497.39 | S49: HOME LOAN | U49: 0 | V49: 12.5 | W49: 4.0 | X49: Single | Y49: 2 | Z49: Rented | AA49: 7.5 | AB49: 366076.0 | AC49: 0 | AD49: false | AE49: 300 | AF49: 8725363.0 | AG49: 2026-07-10 | AH49: Verified
A50: CUST00049 | B50: Ayaan Saxena | C50: 9636687537 | D50: ayaan.saxena612@rediffmail.com | E50: 22 | F50: Male | G50: Chennai | H50: Salaried - IT/Tech | I50: Salaried | K50: 1 | L50: Yes | M50: false | N50: No | O50: No | P50: 387 | Q50: ₹659,703 | R50: 18848.66 | S50: Credit Card | T50: ₹295,806 | U50: 1 | V50: 79.7 | W50: 7.7 | X50: Married | Y50: 3 | Z50: Owned | AA50: 0.6 | AC50: 1 | AD50: false | AE50: 12 | AG50: 2026-02-18 | AH50: Verified
A51: CUST00050 | B51: Mahesh Mishra | C51: 92113082 | D51: mahesh.mishra791@rediffmail.com | E51: 42 | F51: Male | G51: Delhi | H51: Salaried - Healthcare | I51: Salaried | J51: -1719970 | K51: 1 | L51: N | M51: 1 | N51: No | O51: No | P51: 790 | R51: 32597.0 | S51: Credit Card | U51: 3 | V51: 48.5 | W51: 4.5 | X51: Married | Y51: 0 | Z51: Owned | AA51: 19.6 | AC51: 3 | AD51: N | AE51: 24 | AG51: 13-09-2025 | AH51: Verified
A52: CUST00051 | B52: Aryan Iyer | C52: 9483298103 | D52: aryan.iyer883@gmail.com | E52: 62 | F52: FEMALE | G52: Jaipur | H52: Salaried - Government | I52: Salaried | J52: 1843584 | K52: 1 | L52: yes | M52: N | N52: No | O52: No | P52: 647 | R52: 25048.48 | S52: Home Loan | T52: 4581529 | U52: 5 | V52: 54.3 | W52: 12.1 | X52: Single | Y52: 0 | Z52: Rented | AA52: 24.7 | AC52: 0 | AD52: false | AE52: 240 | AF52: 5619813.0 | AG52: 06/30/2026 | AH52: VERIFIED
A53: CUST00052 | B53: Rohan Tiwari | C53: 95766 42996 | D53: rohan.tiwari360@hotmail.com | E53: 23 | F53: female | G53: indore | H53: Salaried - IT/Tech | I53: Salaried | J53: 540,577 | K53: 1 | L53: YES | M53: 0 | N53: false | O53: N | P53: 463 | R53: 14715.89 | S53: Home Loan | U53: 0 | V53: 27.4 | W53: 9.7 | X53: Married | Y53: 3 | Z53: Owned | AA53: 0.6 | AC53: 0 | AD53: false | AE53: 120 | AF53: 2317806.0 | AG53: 2026-05-24 | AH53: Verified
A54: CUST00053 | B54: Ananya Mishra | C54: +91-9399240862 | D54: ananya.mishra256@gmail.com | F54: M | G54: chandigarh | H54: Freelancer | I54: Self-Employed | J54: 1923142 | K54: 1 | L54: NO | M54: 1 | N54: No | O54: NO | P54: 519 | Q54: 1149690.96 | R54: 38323.03 | S54: Home Loan | U54: 0 | V54: 86.0 | W54: 6.9 | X54: Single | Y54: 1 | Z54: Owned | AA54: 0.8 | AC54: 0 | AD54: no | AE54: 120 | AF54: 4093240.0 | AG54: 2026-01-21 | AH54: Verified
A55: CUST00054 | B55: Rekha Patel | D55: rekha.patel727 at yahoo.com | E55: 44 | F55: male | G55: Hyderabad | H55: Self Employed - Professional | I55: Self-Employed | J55: 882491 | K55: 1 | L55: 1 | M55: No | N55: no | O55: false | P55: 778 | Q55: 425,535 | R55: 9053.93 | S55: Personal Loan | T55: 691674 | U55: 4 | V55: 11.2 | W55: 6.1 | X55: Single | Y55: 1 | Z55: Owned | AA55: 9.6 | AC55: 0 | AD55: NO | AE55: 12 | AG55: 2026/04/13 | AH55: Verified
A56: CUST00055 | B56: Divya Shah | C56: +91-9237798236 | D56: divya.shah900@rediffmail.com | E56: 61 | F56: male | G56: Chennai | H56: Salaried - Education | I56: Salaried | J56: 2409163 | K56: 3 | L56: 0 | M56: Yes | N56: YES | O56: YES | P56: 468 | Q56: 234122.88 | R56: 4107.42 | S56: Personal Loan | T56: 412831 | U56: 5 | V56: 54.3 | W56: 4.4 | X56: Married | Y56: 0 | Z56: Company Provided | AA56: 8.5 | AC56: 1 | AD56: 0 | AE56: 24 | AG56: 2026/06/25 | AH56: Pending
A57: CUST00056 | B57: Ishaan Patel | D57: ishaan.patel640@rediffmail.com | E57: 42 | F57: Male | G57: Mumbai | H57: Salaried - Government | I57: Salaried | J57: ₹490,680 | K57: 0 | L57: N | M57: false | N57: N | O57: NO | P57: 885 | Q57: ₹20,441 | R57: 393.1 | S57: credit card | T57: 281115 | U57: 4 | V57: 56.8 | W57: 9.7 | X57: Married | Y57: 0 | Z57: Rented | AA57: 8.7 | AC57: 1 | AD57: false | AE57: 36 | AG57: 04/30/2026 | AH57: verified
A58: CUST00057 | B58: Diya Bansal | C58: 9254263081 | D58: diya.bansal321@outlook.com | F58: F | G58: Chennai | H58: Salaried - Healthcare | I58: Salaried | J58: 2459983 | K58: 0 | L58: false | M58: false | N58: 0 | O58: No | P58: 553 | Q58: -34655.66 | R58: 2310.38 | S58: Car Loan | T58: ₹1,105,620 | U58: 4 | V58: 44.7 | W58: 14.4 | X58: Single | Y58: 3 | Z58: company provided | AA58: 15.9 | AB58: 269507.0 | AC58: 3 | AD58: no | AE58: 48 | AF58: 1270882.0 | AH58: Pending
A59: CUST00058 | B59: Sneha Kapoor | D59: sneha.kapoor221@rediffmail.com | E59: 43 | F59: Male | G59: New Delhi | H59: Salaried - IT/Tech | I59: Salaried | K59: 0 | L59: NO | M59: 0 | N59: No | O59: No | P59: 308 | Q59: 201265.79 | R59: 5160.66 | S59: Personal Loan | T59: ₹975,321 | U59: 0 | V59: 39.7 | W59: 6.2 | X59: Married | Y59: 0 | Z59: Rented | AA59: 8.2 | AB59: 439762.0 | AC59: 0 | AD59: No | AE59: 60 | AH59: Verified
A60: CUST00059 | B60: Krishna Kumar | C60: 95229 50895 | D60: krishna.kumar383@outlook.com | E60: 56 | F60: female | G60: Chennai | H60: Self Employed - Professional | I60: Self-Employed | J60: 2435414 | K60: 3 | L60: YES | M60: true | N60: Y | O60: NO | P60: 785 | Q60: ₹758,874 | R60: 36136.86 | S60: personal loan | T60: 393,897 | U60: 5 | V60: 35.3 | W60: 6.0 | X60: Single | Y60: 3 | Z60: Rented | AA60: 15.4 | AC60: 0 | AD60: NO | AE60: 48 | AG60: 03-09-2025 | AH60: Verified
A61: CUST00060 | B61: Ramesh Kumar | C61: 9547256709 | E61: 65 | F61: Male | G61: Chandigarh | H61: Salaried - IT/Tech | I61: Salaried | K61: 1 | L61: false | M61: 0 | N61: true | O61: No | P61: 689 | R61: 2022.19 | S61: Personal Loan | T61: 83104 | U61: 1 | V61: 71.5 | W61: 3.0 | X61: Married | Y61: 1 | Z61: Owned | AA61: 6.4 | AC61: 1 | AD61: NO | AE61: 12 | AG61: 2026-08-22 | AH61: Verified
A62: CUST00061 | B62: Dhruv Bhatt | C62: 9449019278-XX | D62: dhruv.bhatt679@hotmail.com | E62: 54 | F62: FEMALE | G62: Lucknow | H62: Self Employed - Business | I62: Self-Employed | J62: 2227968 | K62: 0 | L62: NO | M62: No | N62: false | O62: NO | P62: 570 | Q62: 135,923 | R62: 5663.46 | S62: Personal Loan | U62: 1 | V62: 26.4 | W62: 14.6 | X62: Married | Y62: 1 | Z62: Owned | AA62: 21.2 | AB62: 411602.0 | AC62: 3 | AD62: NO | AE62: 36 | AG62: 2026-01-20 | AH62: Verified
A63: CUST00062 | B63: Ramesh Bhatt | C63: 9507693523-XX | D63: RAMESH.BHATT918@HOTMAIL.COM | E63: 43 | F63: F | G63: Surat | H63: Salaried - Private | I63: Salaried | K63: 1 | L63: No | M63: Yes | N63: no | O63: NO | P63: 790 | Q63: ₹193,411 | R63: 4204.59 | S63: Car Loan | T63: 1,478,637 | U63: 2 | V63: 18.0 | W63: 9.3 | X63: Married | Y63: 0 | Z63: Rented | AA63: 11.8 | AC63: 0 | AD63: N | AE63: 84 | AF63: 1692272.0 | AG63: 09 Aug 2026 | AH63: Verified
A64: CUST00063 | B64: Aarav Bhatt | C64: 9269587940 | D64: aarav.bhatt417@hotmail.com | E64: 51 | F64: M | G64: Surat | H64: Salaried - Healthcare | I64: Salaried | J64: ₹1,497,118 | K64: 1 | L64: No | M64: no | N64: yes | O64: 0 | P64: 847 | Q64: 663,541 | R64: 47395.75 | S64: personal loan | T64: 488,184 | U64: 4 | V64: 21.7 | W64: 13.8 | X64: Divorced | Y64: 1 | Z64: Rented | AA64: 28.1 | AC64: 2 | AD64: N | AE64: 12 | AG64: 25-01-2026 | AH64: Verified
A65: CUST00064 | B65: Reyansh Khanna | D65: reyansh.khanna292@hotmail.com | E65: 62 | F65: F | G65: Chennai | H65: Freelancer | I65: Self-Employed | K65: 1 | L65: 1 | M65: N | N65: false | O65: false | P65: 563 | Q65: ₹975,722 | R65: 81310.14 | S65: Car Loan | T65: 918,710 | U65: 1 | V65: 76.9 | W65: 2.8 | X65: Single | Y65: 3 | Z65: Rented | AA65: 15.6 | AB65: 651942.0 | AC65: 0 | AD65: N | AE65: 48 | AF65: 1136596.0 | AG65: 08/29/2025 | AH65: Verified
A66: CUST00065 | B66: Rahul Kapoor | C66: +91-9909340042 | D66: rahul.kapoor274@outlook.com | E66: 40 | F66: male | G66: Jaipur | H66: Salaried - Healthcare | I66: Salaried | K66: 2 | L66: YES | M66: YES | N66: NO | O66: no | P66: 814 | Q66: 715,107 | R66: 12545.73 | S66: Car Loan | T66: 546,238 | U66: 1 | V66: 94.4 | W66: 5.6 | X66: Married | Y66: 4 | Z66: Rented | AA66: 8.8 | AC66: 0 | AD66: N | AE66: 60 | AF66: 656289.0 | AG66: 08/01/2026 | AH66: Verified
A67: CUST00066 | B67: Anil Rao | D67: anil.rao773@rediffmail.com | E67: 26 | F67: Female | G67: Kochi | H67: SALARIED - HEALTHCARE | I67: Salaried | J67: 627586 | K67: 1 | L67: 0 | M67: true | N67: N | O67: 0 | P67: 507 | Q67: N/A | R67: 10269.13 | S67: Personal Loan | T67: -394056 | U67: 4 | V67: 47.0 | W67: 10.3 | X67: Single | Y67: 1 | Z67: Rented | AA67: 2.4 | AB67: 248958.0 | AC67: 0 | AD67: false | AE67: 60 | AG67: 19-04-2026 | AH67: Verified
A68: CUST00067 | B68: Manish Yadav | C68: 91233 75849 | D68: manish.yadav406@outlook.com | E68: 21 | F68: Male | G68: Bengaluru | H68: Salaried - Private | I68: Salaried | J68: N/A | K68: 2 | L68: YES | M68: YES | N68: No | O68: no | P68: 370 | R68: 29261.72 | S68: Credit Card | T68: N/A | U68: 0 | V68: 78.1 | W68: 11.5 | X68: Divorced | Y68: 2 | Z68: Owned | AA68: 0.3 | AC68: 0 | AD68: 0 | AE68: 36 | AG68: 06-03-2026 | AH68: Verified
A69: CUST00068 | B69: Mahesh Bhatia | C69: 9679069250 | D69: mahesh.bhatia137@outlook.com | E69: 28 | F69: MALE | G69: Coimbatore | H69: Salaried - Education | I69: Salaried | K69: 3 | L69: false | M69: yes | N69: Yes | O69: Yes | P69: 605 | Q69: 231,724 | R69: 3995.24 | S69: Home Loan | T69: 5962182 | U69: 0 | V69: 26.8 | W69: 7.0 | X69: Married | Y69: 0 | Z69: Rented | AA69: 5.4 | AB69: 645148.0 | AC69: 1 | AD69: Y | AE69: 120 | AF69: 7215233.0 | AG69: 29-09-2025 | AH69: Verified
A70: CUST00069 | B70: Aditya Kapoor | D70: aditya.kapoor689@gmail.com | E70: 36 | F70: M | G70: Nagpur | H70: Business Owner | I70: Self-Employed | J70: N/A | K70: 2 | L70: yes | M70: no | N70: false | O70: YES | P70: 596 | R70: 3107.62 | S70: CAR LOAN | T70: 972483 | U70: 0 | V70: 88.2 | W70: 14.8 | X70: Married | Y70: 1 | Z70: Owned | AA70: 8.5 | AC70: 1 | AD70: no | AE70: 84 | AF70: 1104196.0 | AG70: 05/06/2026 | AH70: Verified
A71: CUST00070 | B71: Isha Mishra | C71: 9820848547-XX | D71: isha.mishra391 at rediffmail.com | E71: 41 | F71: FEMALE | G71: Indore | H71: Self Employed - Business | I71: Self-Employed | J71: ₹1,557,823 | K71: 1 | L71: true | M71: No | N71: false | O71: no | P71: 607 | Q71: 801538.48 | R71: 38168.5 | S71: Home Loan | T71: ₹1,983,384 | U71: 1 | V71: 96.9 | W71: 8.4 | X71: Married | Y71: 0 | Z71: Owned | AA71: 13.0 | AC71: 2 | AD71: NO | AE71: 180 | AF71: 2306446.0 | AG71: 07-03-2026 | AH71: Verified
A72: CUST00071 | B72: Simran Verma | C72: 91781 51583 | D72: simran.verma193@rediffmail.com | E72: 63 | F72: Male | G72: Chandigarh | H72: Self Employed - Professional | I72: Self-Employed | J72: ₹1,696,553 | K72: 2 | L72: true | M72: no | N72: 1 | O72: No | P72: 420 | Q72: ₹760,272 | R72: 12671.2 | S72: home loan | T72: 3,535,019 | U72: 2 | V72: 71.9 | W72: 6.1 | X72: Married | Y72: 1 | Z72: Owned | AA72: 14.1 | AC72: 0 | AD72: N | AE72: 300 | AF72: 4477105.0 | AG72: 04/23/2026 | AH72: Verified
A73: CUST00072 | B73: Ananya Khanna | C73: 09318106480 | D73: ananya.khanna380@outlook.com | E73: 47 | F73: Male | G73: Ahmedabad | H73: Self Employed - Business | I73: Self-Employed | J73: ₹368,031 | K73: 1 | L73: true | M73: No | N73: NO | O73: 0 | P73: 456 | Q73: ₹43,323 | R73: 1666.26 | S73: Home Loan | T73: 6279740 | U73: 3 | V73: 52.4 | W73: 9.9 | X73: Single | Y73: 1 | Z73: rented | AA73: 25.1 | AC73: 0 | AD73: 0 | AE73: 240 | AF73: 7487437.0 | AG73: 01-06-2026 | AH73: Verified
A74: CUST00073 | B74: Seema Sethi | C74: +91-9682115008 | D74: seema.sethi658 at gmail.com | E74: 54 | F74: Male | G74: Bengaluru | H74: Salaried - Private | I74: Salaried | J74: 326775 | K74: 2 | L74: YES | M74: 0 | N74: 1 | O74: NO | P74: 309 | Q74: 42,883 | R74: 1045.93 | S74: CAR LOAN | T74: 426773 | U74: 1 | V74: 68.3 | W74: 9.3 | X74: Married | Y74: 1 | Z74: Owned | AA74: 16.7 | AB74: 547063.0 | AC74: 0 | AD74: Y | AE74: 24 | AF74: 490978.0 | AG74: 18-08-2026 | AH74: Verified
A75: CUST00074 | B75: Preeti Khanna | C75: 92924863 | D75: preeti.khanna110 at gmail.com | E75: 54 | F75: M | G75: Ahmedabad | H75: Self Employed - Professional | I75: Self-Employed | J75: ₹1,358,718 | K75: 1 | L75: N | M75: yes | N75: 0 | O75: 0 | P75: 715 | Q75: ₹374,189 | R75: 13858.86 | S75: PERSONAL LOAN | U75: 2 | V75: 85.5 | W75: 9.9 | X75: SINGLE | Y75: 2 | Z75: Owned | AA75: 11.6 | AC75: 0 | AD75: false | AE75: 24 | AG75: 2025/10/07 | AH75: Verified
A76: CUST00075 | B76: Saanvi Mishra | C76: 9942217648-XX | D76: saanvi.mishra340@rediffmail.com | E76: 27 | F76: male | G76: Ahmedabad | H76: Self Employed - Professional | I76: Self-Employed | J76: ₹2,294,392 | K76: 1 | L76: yes | M76: No | N76: NO | O76: No | P76: 856 | Q76: ₹775,748 | R76: 55410.54 | S76: personal loan | T76: ₹941,737 | U76: 0 | V76: 96.3 | W76: 8.9 | X76: Single | Y76: 2 | Z76: Owned | AA76: 0.7 | AB76: 330354.0 | AC76: 2 | AD76: N | AE76: 60 | AG76: 02/11/2026 | AH76: Verified
A77: CUST00076 | B77: Vinod Singh | C77: +91-9948790854 | D77: vinod.singh706@gmail.com | E77: 53 | F77: FEMALE | G77: Delhi | H77: Salaried - Government | I77: Salaried | K77: 2 | L77: YES | M77: YES | N77: NO | O77: no | P77: 706 | Q77: 1,240,188 | R77: 38755.87 | S77: Credit Card | T77: ₹352,463 | U77: 0 | V77: 99.3 | W77: 7.5 | X77: Married | Y77: 3 | Z77: Owned | AA77: 20.5 | AC77: 0 | AD77: No | AE77: 18 | AG77: 2026-08-26 | AH77: Verified
A78: CUST00077 | B78: Vikram Singh | C78: 9508021882 | D78: vikram.singh729@yahoo,com | E78: 45 | F78: female | G78: Kanpur | H78: SALARIED - GOVERNMENT | I78: Salaried | J78: 683864 | K78: 1 | L78: YES | M78: No | N78: no | O78: N | P78: 435 | R78: 918.45 | S78: Home Loan | U78: 1 | V78: 43.8 | W78: 0.6 | X78: Married | Y78: 0 | Z78: Rented | AA78: 8.0 | AC78: 0 | AD78: No | AE78: 120 | AF78: 8216672.0 | AG78: 2026/06/08 | AH78: verified
A79: CUST00078 | B79: rahul agarwal | C79: 09659531734 | D79: rahul.agarwal174 at hotmail.com | F79: male | G79: Jaipur | H79: Salaried - IT/Tech | I79: Salaried | J79: -1425779 | K79: 2 | L79: true | M79: Yes | N79: 0 | O79: no | P79: 795 | R79: 19129.88 | S79: Car Loan | T79: 817136 | U79: 2 | V79: 52.1 | W79: 9.3 | X79: Married | Y79: 0 | Z79: Owned | AA79: 4.1 | AC79: 0 | AD79: No | AE79: 60 | AF79: 912698.0 | AG79: 2026-07-25 | AH79: pending
A80: CUST00079 | B80: KRISHNA IYER | C80: 9444311586 | D80: krishna.iyer618@yahoo.com | E80: 51 | F80: female | G80: Kolkata | H80: Salaried - Education | I80: Salaried | J80: 1,638,560 | K80: 1 | L80: yes | M80: No | N80: NO | O80: 0 | P80: 548 | Q80: 320390.49 | R80: 11047.95 | S80: Home Loan | T80: ₹4,561,972 | U80: 0 | V80: 58.6 | W80: 9.0 | X80: Married | Y80: 2 | Z80: Rented | AA80: 28.6 | AC80: 1 | AD80: N | AE80: 240 | AF80: 6194339.0 | AG80: 2025-09-30 | AH80: Verified
A81: CUST00080 | B81: Kiran Rathi | C81: 95393 12437 | D81: kiran.rathi690@hotmail.com | E81: 29 | F81: M | G81: Ahmedabad | H81: Salaried - IT/Tech | I81: Salaried | J81: ₹946,523 | K81: 1 | L81: false | M81: no | N81: Y | O81: N | P81: 790 | Q81: 330664.41 | R81: 7188.36 | S81: Home Loan | T81: ₹6,060,426 | U81: 0 | V81: 97.0 | W81: 10.6 | X81: Single | Y81: 2 | Z81: Company Provided | AA81: 1.1 | AB81: 648520.0 | AC81: 0 | AD81: N | AE81: 360 | AF81: 8459761.0 | AG81: 07-08-2026 | AH81: Verified
A82: CUST00081 | B82: Anil Mehta | C82: 9954946593 | D82: anil.mehta441@gmail.com | F82: male | G82: Jaipur | H82: Self Employed - Professional | I82: Self-Employed | J82: 2441931 | K82: 0 | L82: no | M82: 0 | N82: N | O82: NO | P82: 683 | Q82: 95512.27 | R82: 1736.59 | S82: Personal Loan | T82: 411,724 | U82: 10 | V82: 50.9 | W82: 4.6 | X82: Single | Y82: 0 | Z82: Rented | AA82: 0.3 | AC82: 0 | AD82: N | AE82: 24 | AG82: 05/19/2026 | AH82: Verified
A83: CUST00082 | B83: Pooja Kumar | C83: 9570477095 | D83: pooja.kumar740@hotmail.com | E83: 41 | F83: Male | G83: Surat | H83: Salaried - Private | I83: Salaried | J83: ₹782,702 | K83: 2 | L83: yes | M83: N | N83: YES | O83: N | P83: 549 | R83: 5155.78 | S83: personal loan | T83: 397,067 | U83: 1 | V83: 96.1 | W83: 3.6 | X83: Married | Y83: 0 | Z83: rented | AA83: 8.8 | AB83: 610580.0 | AC83: 0 | AD83: No | AE83: 48 | AG83: 2025/08/28 | AH83: Verified
A84: CUST00083 | B84: Dhruv Nair | C84: 9907803348 | D84: dhruv.nair721@gmail.com | E84: 57 | F84: male | G84: Coimbatore | H84: Self Employed - Business | I84: Self-Employed | K84: 1 | L84: Y | M84: NO | N84: NO | O84: no | P84: 840 | Q84: ₹1,063,038 | R84: 33219.92 | S84: Home Loan | T84: 6628026 | U84: 0 | V84: 15.9 | W84: 5.4 | X84: Married | Y84: 0 | Z84: Rented | AA84: 24.1 | AC84: 1 | AD84: no | AE84: 240 | AF84: 7817527.0 | AG84: 2026-01-29 | AH84: Verified
A85: CUST00084 | B85: KAVYA TIWARI | C85: 92517 82582 | D85: kavya.tiwari524 at hotmail.com | E85: 47 | F85: F | G85: Nagpur | H85: Salaried - Education | I85: Salaried | J85: ₹1,079,107 | K85: 1 | L85: yes | M85: no | N85: no | O85: false | P85: 477 | Q85: 359286.03 | R85: 8355.49 | S85: Car Loan | U85: 0 | V85: 85.0 | W85: 9.4 | X85: Single | Y85: 4 | Z85: Rented | AA85: 5.3 | AC85: 1 | AD85: false | AE85: 60 | AF85: 705307.0 | AG85: 26 Mar 2026 | AH85: Verified
A86: CUST00085 | B86: Tanya Joshi | C86: +91-9279587066 | D86: tanya.joshi85@rediffmail.com | E86: 22 | F86: M | G86: Surat | H86: Salaried - Private | I86: Salaried | K86: 2 | L86: 1 | M86: 1 | N86: NO | O86: N | P86: 807 | Q86: 479,191 | R86: 25220.56 | S86: CREDIT CARD | U86: 3 | V86: 83.2 | W86: 5.6 | X86: Single | Y86: 0 | Z86: Rented | AA86: 0.7 | AC86: 0 | AD86: NO | AE86: 18 | AG86: 01/25/2026 | AH86: Verified
A87: CUST00086 | B87: Aditya Kapoor | C87: 93821 95698 | D87: aditya.kapoor357@gmail.com | E87: 49 | F87: Male | G87: Ahmedabad | H87: Self Employed - Professional | I87: Self-Employed | J87: 1,770,652 | K87: 0 | L87: NO | M87: N | N87: No | O87: NO | P87: 511 | Q87: 144,048 | R87: 9603.19 | S87: Car Loan | T87: N/A | U87: 0 | V87: 56.2 | W87: 5.0 | X87: single | Y87: 1 | Z87: Owned | AA87: 24.1 | AC87: 1 | AD87: No | AE87: 60 | AF87: 1747332.0 | AG87: 01/14/2026 | AH87: Verified
A88: CUST00087 | B88: Krishna Tiwari | C88: 92424 75723 | E88: 41 | F88: M | G88: Nagpur | H88: Business Owner | I88: Self-Employed | J88: 896,311 | K88: 1 | L88: false | M88: Y | N88: 0 | O88: No | P88: 395 | Q88: -216647.75 | R88: 3672.0 | S88: Car Loan | T88: 1,073,998 | U88: 1 | V88: 51.4 | W88: 8.8 | X88: Single | Y88: 3 | Z88: OWNED | AA88: 19.5 | AC88: 1 | AD88: 0 | AE88: 72 | AF88: 1213127.0 | AG88: 2026-04-02 | AH88: Verified
A89: CUST00088 | B89: Anjali Nair | C89: 9446673808 | D89: anjali.nair849 at outlook.com | E89: 42 | F89: Male | G89: Chandigarh | H89: Salaried - Healthcare | I89: Salaried | K89: 2 | L89: 1 | M89: 0 | N89: N | O89: yes | P89: 461 | Q89: 133191.48 | R89: 11099.29 | S89: Home Loan | T89: ₹3,197,168 | U89: 10 | V89: 91.4 | W89: 13.3 | X89: Married | Y89: 3 | Z89: Rented | AA89: 2.2 | AC89: 0 | AD89: false | AE89: 180 | AF89: 3718136.0 | AG89: 2026/07/12 | AH89: Verified
A90: CUST00089 | B90: Deepak Chauhan | C90: 09351410032 | D90: deepak.chauhan440@gmail.com | E90: 27 | F90: male | G90: Pune | H90: Business Owner | I90: Self-Employed | J90: ₹626,898 | K90: 3 | L90: Yes | M90: yes | N90: 0 | O90: yes | P90: 651 | R90: 7880.68 | S90: Personal Loan | T90: ₹550,905 | U90: 0 | V90: 41.4 | W90: 11.0 | X90: Married | Y90: 1 | Z90: Rented | AA90: 1.1 | AC90: 1 | AD90: NO | AE90: 24 | AG90: 09/30/2025 | AH90: Verified
A91: CUST00090 | B91: Aarav Bansal | C91: 97979538 | D91: aarav.bansal169@hotmail.com | F91: F | G91: Chennai | H91: Salaried - Education | I91: Salaried | J91: 2155492 | K91: 2 | L91: no | M91: yes | N91: yes | O91: NO | P91: 693 | Q91: -454639.36 | R91: 11657.42 | S91: Car Loan | U91: 0 | V91: 66.2 | W91: 3.9 | X91: SINGLE | Y91: 2 | Z91: Owned | AA91: 20.7 | AB91: 785303.0 | AC91: 2 | AD91: 0 | AE91: 72 | AF91: 683362.0 | AG91: 2026/03/14 | AH91: Verified
A92: CUST00091 | B92: Vihaan Rathi | C92: 99523 12670 | D92: vihaan.rathi978@yahoo.com | E92: 52 | F92: female | G92: Hyderabad | H92: Self Employed - Professional | I92: Self-Employed | K92: 2 | L92: NO | M92: YES | N92: N | O92: YES | P92: 669 | R92: 67113.7 | S92: Home Loan | T92: 6267920 | U92: 0 | V92: 56.9 | W92: 2.8 | X92: Married | Y92: 4 | Z92: Owned | AA92: 17.7 | AB92: 311807.0 | AC92: 2 | AD92: yes | AE92: 300 | AF92: 8001957.0 | AG92: 13 Jul 2026 | AH92: Verified
A93: CUST00092 | B93: Sunil Malhotra | C93: 9554810443-XX | D93: sunil.malhotra719@hotmail.com | E93: 26 | F93: male | G93: Jaipur | H93: Salaried - Government | I93: Salaried | K93: 2 | L93: Y | M93: NO | N93: false | O93: true | P93: 634 | Q93: 375065.44 | R93: 7212.8 | S93: Credit Card | U93: 2 | V93: 74.3 | W93: 12.7 | X93: MARRIED | Y93: 0 | Z93: Owned | AA93: 2.4 | AC93: 0 | AD93: 0 | AE93: 18 | AG93: 2025/10/26 | AH93: Verified
A94: CUST00093 | B94: Krishna Tiwari | C94: 09112187618 | E94: 43 | F94: M | G94: Kolkata | H94: Salaried - Healthcare | I94: Salaried | J94: 832,385 | K94: 1 | L94: no | M94: 0 | N94: no | O94: Y | P94: 330 | Q94: 167314.89 | R94: 4290.13 | S94: Car Loan | U94: 0 | V94: 72.7 | W94: 8.7 | X94: Married | Y94: 1 | Z94: Owned | AA94: 11.1 | AC94: 0 | AD94: N | AE94: 24 | AF94: 1718676.0 | AG94: 08/06/2026 | AH94: Verified
A95: CUST00094 | B95: Karan Yadav | C95: 96463 46564 | D95: karan.yadav3@gmail.com | E95: 21 | F95: male | G95: delhi | H95: Business Owner | I95: Self-Employed | K95: 2 | L95: 1 | M95: Yes | N95: NO | O95: N | P95: 866 | Q95: 880195.94 | R95: 15442.03 | S95: Home Loan | T95: N/A | U95: 0 | V95: 44.5 | W95: 10.9 | X95: Married | Y95: 0 | Z95: Owned | AA95: 0.3 | AC95: 2 | AD95: N | AE95: 360 | AF95: 4720997.0 | AG95: 03/19/2026 | AH95: Verified
A96: CUST00095 | B96: Neha Bhatia | C96: +91-9403124688 | D96: neha.bhatia793@outlook.com | E96: 41 | F96: Male | G96: Coimbatore | H96: Business Owner | I96: Self-Employed | J96: 333425 | K96: 2 | L96: YES | M96: yes | N96: 0 | O96: NO | P96: 548 | Q96: 92,811 | R96: 1894.1 | S96: Home Loan | T96: 7,981,149 | U96: 3 | V96: 74.6 | W96: 8.3 | X96: SINGLE | Y96: 0 | Z96: Company Provided | AA96: 0.8 | AC96: 1 | AD96: NO | AE96: 120 | AF96: 11075820.0 | AG96: 2025/08/26 | AH96: Verified
A97: CUST00096 | B97: MEERA BHATIA | C97: 09892510222 | D97: meera.bhatia745@outlook.com | E97: 27 | F97: male | G97: Kochi | H97: Self Employed - Professional | I97: Self-Employed | J97: 2,060,835 | K97: 2 | L97: Yes | M97: Yes | N97: NO | O97: NO | P97: 395 | Q97: 54,283 | R97: 2087.8 | S97: Home Loan | T97: N/A | U97: 4 | V97: 48.6 | W97: 11.3 | X97: Married | Y97: 2 | Z97: Rented | AA97: 2.5 | AC97: 0 | AD97: No | AE97: 180 | AF97: 8922791.0 | AG97: 01/06/2026 | AH97: Verified
A98: CUST00097 | B98: Rita Rathi | C98: 95219297 | D98: rita.rathi718 at outlook.com | E98: 41 | F98: F | G98: Jaipur | H98: Self Employed - Professional | I98: Self-Employed | K98: 2 | L98: 0 | M98: Y | N98: 0 | O98: YES | P98: 408 | Q98: 60482.86 | R98: 1475.19 | S98: Car Loan | U98: 0 | V98: 39.0 | W98: 11.6 | X98: Married | Y98: 1 | Z98: Rented | AA98: 2.1 | AC98: 0 | AD98: No | AE98: 72 | AF98: 1219440.0 | AG98: 02/09/2026 | AH98: Verified
A99: CUST00098 | B99: Sanjay Rao | C99: +91-9481975879 | D99: sanjay.rao406 at rediffmail.com | E99: 24 | F99: Female | G99: Jaipur | H99: Self Employed - Business | I99: Self-Employed | J99: ₹430,367 | K99: 0 | L99: no | M99: no | N99: false | O99: false | P99: 396 | R99: 994.24 | S99: Credit Card | U99: 0 | V99: 79.2 | W99: 3.5 | X99: Married | Y99: 1 | Z99: Rented | AA99: 2.8 | AB99: 589589.0 | AC99: 2 | AD99: NO | AE99: 12 | AG99: 2025-12-05 | AH99: Verified
A100: CUST00099 | B100: Tanya Rathi | C100: +91-9238288872 | D100: tanya.rathi95@outlook.com | E100: 28 | F100: Male | G100: bhopal | H100: Salaried - Private | I100: Salaried | J100: N/A | K100: 0 | L100: no | M100: No | N100: NO | O100: No | P100: 691 | R100: 2984.15 | S100: Car Loan | T100: -750292 | U100: 4 | V100: 31.1 | W100: 6.8 | X100: Married | Y100: 2 | Z100: Rented | AA100: 4.6 | AC100: 2 | AD100: 0 | AE100: 24 | AF100: 829789.0 | AG100: 2025/11/04 | AH100: Verified
...
